Workbook

Sheet 01_input_asset_master
A1: property_id | B1: property_name | C1: city | D1: county | E1: state | F1: property_type | G1: year_built | H1: gross_floor_area_sqft | I1: units | J1: occupancy_rate | K1: affordable_units_pct
A2: WI-MF-01 | B2: Riverbend Apartments | C2: Madison | D2: Dane | E2: WI | F2: Multifamily | G2: 1988 | H2: 165000 | I2: 180 | J2: 0.94 | K2: 0.25
A3: WI-MF-02 | B3: Lakeview Terrace | C3: Milwaukee | D3: Milwaukee | E3: WI | F3: Multifamily | G3: 1975 | H3: 220000 | I3: 240 | J3: 0.91 | K3: 0.6
A4: WI-MF-03 | B4: Northside Commons | C4: Green Bay | D4: Brown | E4: WI | F4: Multifamily | G4: 1995 | H4: 145000 | I4: 160 | J4: 0.96 | K4: 0.15
A5: WI-MF-04 | B5: Badger Ridge Homes | C5: Wausau | D5: Marathon | E5: WI | F5: Multifamily | G5: 1982 | H5: 120000 | I5: 130 | J5: 0.93 | K5: 0.4
A6: WI-MF-05 | B6: Oak Street Lofts | C6: Eau Claire | D6: Eau Claire | E6: WI | F6: Multifamily | G6: 2008 | H6: 98000 | I6: 105 | J6: 0.97 | K6: 0.1
A7: WI-MF-06 | B7: South Park Apartments | C7: Racine | D7: Racine | E7: WI | F7: Multifamily | G7: 1970 | H7: 185000 | I7: 210 | J7: 0.89 | K7: 0.55
A8: WI-MF-07 | B8: Fox River Flats | C8: Appleton | D8: Outagamie | E8: WI | F8: Multifamily | G8: 2001 | H8: 135000 | I8: 150 | J8: 0.95 | K8: 0.2
A9: WI-MF-08 | B9: Prairie View Residences | C9: La Crosse | D9: La Crosse | E9: WI | F9: Multifamily | G9: 1990 | H9: 110000 | I9: 120 | J9: 0.92 | K9: 0.35
A10: WI-MF-09 | B10: Capitol Square Homes | C10: Madison | D10: Dane | E10: WI | F10: Multifamily | G10: 2015 | H10: 175000 | I10: 190 | J10: 0.98 | K10: 0.05
A11: WI-MF-10 | B11: Harbor Point Apartments | C11: Kenosha | D11: Kenosha | E11: WI | F11: Multifamily | G11: 1980 | H11: 160000 | I11: 175 | J11: 0.9 | K11: 0.5

Sheet 02_input_energy_monthly
A1: property_id | B1: property_name | C1: city | D1: county | E1: state | F1: property_type | G1: month | H1: electricity_kwh | I1: natural_gas_therms | J1: electricity_cost_usd | K1: natural_gas_cost_usd | L1: electricity_rate_usd_kwh | M1: gas_rate_usd_therm | N1: owner_or_tenant_paid | O1: data_quality | P1: source_note
A2: WI-MF-01 | B2: Riverbend Apartments | C2: Madison | D2: Dane | E2: WI | F2: Multifamily | G2: 2025-01 | H2: 90495 | I2: 10534 | J2: 13121.77 | K2: 11587.4 | L2: 0.145 | M2: 1.1 | N2: Mixed / simulated | O2: Simulated from ENERGY STAR multifamily EUI benchmark; not actual utility bills | P2: ENERGY STAR Portfolio Manager Data Explorer / U.S. National Median EUI table
A3: WI-MF-01 | B3: Riverbend Apartments | C3: Madison | D3: Dane | E3: WI | F3: Multifamily | G3: 2025-02 | H3: 83708 | I3: 8826 | J3: 12137.66 | K3: 9708.6 | L3: 0.145 | M3: 1.1 | N3: Mixed / simulated | O3: Simulated from ENERGY STAR multifamily EUI benchmark; not actual utility bills | P3: ENERGY STAR Portfolio Manager Data Explorer / U.S. National Median EUI table
A4: WI-MF-01 | B4: Riverbend Apartments | C4: Madison | D4: Dane | E4: WI | F4: Multifamily | G4: 2025-03 | H4: 84839 | I4: 7402 | J4: 12301.65 | K4: 8142.2 | L4: 0.145 | M4: 1.1 | N4: Mixed / simulated | O4: Simulated from ENERGY STAR multifamily EUI benchmark; not actual utility bills | P4: ENERGY STAR Portfolio Manager Data Explorer / U.S. National Median EUI table
A5: WI-MF-01 | B5: Riverbend Apartments | C5: Madison | D5: Dane | E5: WI | F5: Multifamily | G5: 2025-04 | H5: 84839 | I5: 4555 | J5: 12301.65 | K5: 5010.5 | L5: 0.145 | M5: 1.1 | N5: Mixed / simulated | O5: Simulated from ENERGY STAR multifamily EUI benchmark; not actual utility bills | P5: ENERGY STAR Portfolio Manager Data Explorer / U.S. National Median EUI table
A6: WI-MF-01 | B6: Riverbend Apartments | C6: Madison | D6: Dane | E6: WI | F6: Multifamily | G6: 2025-05 | H6: 92757 | I6: 2562 | J6: 13449.76 | K6: 2818.2 | L6: 0.145 | M6: 1.1 | N6: Mixed / simulated | O6: Simulated from ENERGY STAR multifamily EUI benchmark; not actual utility bills | P6: ENERGY STAR Portfolio Manager Data Explorer / U.S. National Median EUI table
A7: WI-MF-01 | B7: Riverbend Apartments | C7: Madison | D7: Dane | E7: WI | F7: Multifamily | G7: 2025-06 | H7: 104069 | I7: 1139 | J7: 15090 | K7: 1252.9 | L7: 0.145 | M7: 1.1 | N7: Mixed / simulated | O7: Simulated from ENERGY STAR multifamily EUI benchmark; not actual utility bills | P7: ENERGY STAR Portfolio Manager Data Explorer / U.S. National Median EUI table
A8: WI-MF-01 | B8: Riverbend Apartments | C8: Madison | D8: Dane | E8: WI | F8: Multifamily | G8: 2025-07 | H8: 118775 | I8: 683 | J8: 17222.38 | K8: 751.3 | L8: 0.145 | M8: 1.1 | N8: Mixed / simulated | O8: Simulated from ENERGY STAR multifamily EUI benchmark; not actual utility bills | P8: ENERGY STAR Portfolio Manager Data Explorer / U.S. National Median EUI table
A9: WI-MF-01 | B9: Riverbend Apartments | C9: Madison | D9: Dane | E9: WI | F9: Multifamily | G9: 2025-08 | H9: 118775 | I9: 683 | J9: 17222.38 | K9: 751.3 | L9: 0.145 | M9: 1.1 | N9: Mixed / simulated | O9: Simulated from ENERGY STAR multifamily EUI benchmark; not actual utility bills | P9: ENERGY STAR Portfolio Manager Data Explorer / U.S. National Median EUI table
A10: WI-MF-01 | B10: Riverbend Apartments | C10: Madison | D10: Dane | E10: WI | F10: Multifamily | G10: 2025-09 | H10: 98413 | I10: 1708 | J10: 14269.88 | K10: 1878.8 | L10: 0.145 | M10: 1.1 | N10: Mixed / simulated | O10: Simulated from ENERGY STAR multifamily EUI benchmark; not actual utility bills | P10: ENERGY STAR Portfolio Manager Data Explorer / U.S. National Median EUI table
A11: WI-MF-01 | B11: Riverbend Apartments | C11: Madison | D11: Dane | E11: WI | F11: Multifamily | G11: 2025-10 | H11: 88233 | I11: 3986 | J11: 12793.78 | K11: 4384.6 | L11: 0.145 | M11: 1.1 | N11: Mixed / simulated | O11: Simulated from ENERGY STAR multifamily EUI benchmark; not actual utility bills | P11: ENERGY STAR Portfolio Manager Data Explorer / U.S. National Median EUI table
A12: WI-MF-01 | B12: Riverbend Apartments | C12: Madison | D12: Dane | E12: WI | F12: Multifamily | G12: 2025-11 | H12: 82577 | I12: 6548 | J12: 11973.66 | K12: 7202.8 | L12: 0.145 | M12: 1.1 | N12: Mixed / simulated | O12: Simulated from ENERGY STAR multifamily EUI benchmark; not actual utility bills | P12: ENERGY STAR Portfolio Manager Data Explorer / U.S. National Median EUI table
A13: WI-MF-01 | B13: Riverbend Apartments | C13: Madison | D13: Dane | E13: WI | F13: Multifamily | G13: 2025-12 | H13: 83708 | I13: 8313 | J13: 12137.66 | K13: 9144.3 | L13: 0.145 | M13: 1.1 | N13: Mixed / simulated | O13: Simulated from ENERGY STAR multifamily EUI benchmark; not actual utility bills | P13: ENERGY STAR Portfolio Manager Data Explorer / U.S. National Median EUI table
... A121: WI-MF-10 | B121: Harbor Point Apartments | C121: Kenosha | D121: Kenosha | E121: WI | F121: Multifamily | G121: 2025-12 | H121: 82942 | I121: 9110 | J121: 12026.59 | K121: 10021 | L121: 0.145 | M121: 1.1 | N121: Mixed / simulated | O121: Simulated from ENERGY STAR multifamily EUI benchmark; not actual utility bills | P121: ENERGY STAR Portfolio Manager Data Explorer / U.S. National Median EUI table

Sheet 11_calc_energy_summary
A1: property_id | B1: property_name | C1: gross_floor_area_sqft | D1: units | E1: annual_electricity_kwh | F1: annual_natural_gas_therms | G1: annual_electricity_cost_usd | H1: annual_gas_cost_usd | I1: annual_total_energy_cost_usd | J1: electricity_kbtu | K1: natural_gas_kbtu | L1: total_energy_kbtu | M1: site_eui_kbtu_sqft | N1: electricity_intensity_kwh_sqft | O1: gas_intensity_therms_sqft | P1: energy_cost_per_unit | Q1: energy_cost_per_sqft | R1: months_with_energy_data | S1: energy_data_coverage_pct | T1: benchmark_site_eui | U1: eui_vs_benchmark | V1: energy_performance_flag | W1: energy_data_coverage_flag | X1: energy_priority_rank | Y1: recommended_energy_action
A2: WI-MF-01 | B2: =_xlfn.XLOOKUP(Energy_Summary_Template[[#This Row],[property_id]],Energy_Monthly[property_id],Energy_Monthly[property_name]) -> Riverbend Apartments | C2: =_xlfn.XLOOKUP(A2,'01_input_asset_master'!A$2:A$11,'01_input_asset_master'!H$2:H$11) -> 165000 | D2: =_xlfn.XLOOKUP(A2,'01_input_asset_master'!A$2:A$11,'01_input_asset_master'!I$2:I$11) -> 180 | E2: =SUMIFS('02_input_energy_monthly'!H:H,'02_input_energy_monthly'!A:A,A2) -> 1131188 | F2: =SUMIFS('02_input_energy_monthly'!I:I,'02_input_energy_monthly'!A:A,A2) -> 56939 | G2: =SUMIFS('02_input_energy_monthly'!J:J,'02_input_energy_monthly'!A:A,A2) -> 164022.23 | H2: =SUMIFS('02_input_energy_monthly'!K:K,'02_input_energy_monthly'!A:A,A2) -> 62632.9 | I2: =Energy_Summary_Template[[#This Row],[annual_gas_cost_usd]]+Energy_Summary_Template[[#This Row],[annual_electricity_cost_usd]] -> 226655.13 | J2: =E2*3.412 -> 3859613.5 | K2: =F2*100 -> 5693900 | L2: =Energy_Summary_Template[[#This Row],[electricity_kbtu]]+Energy_Summary_Template[[#This Row],[natural_gas_kbtu]] -> 9553513.5 | M2: =L2/C2 -> 57.900082 | N2: =E2/C2 -> 6.8556848 | O2: =F2/C2 -> 0.34508485 | P2: =I2/D2 -> 1259.1952 | Q2: =I2/C2 -> 1.3736675 | R2: =COUNTIFS('02_input_energy_monthly'!A:A,A2,'02_input_energy_monthly'!H:H,">0")+COUNTIFS('02_input_energy_monthly'!A:A,A2,'02_input_energy_monthly'!H:H,0,'02_input_energy_monthly'!I:I,">0") -> 12 | S2: =R2/12 -> 1 | T2: =59.6 -> 59.6 | U2: =M2-T2 -> -1.6999184 | V2: =IF(M2>70,"High Energy Use",IF(M2>59.6,"Above Benchmark","At/Below Benchmark")) -> At/Below Benchmark | W2: =IF(S2>=0.95,"Good",IF(S2>=0.75,"Needs Review","Weak")) -> Good | X2: =_xlfn.RANK.EQ(M2,$M$2:$M$11,0) -> 5 | Y2: =IF(M2>65,"Energy audit + heating system review", IF(M2>59.6,"Monitor + targeted efficiency upgrades", "Maintain performance")) -> Maintain performance
A3: WI-MF-02 | B3: =_xlfn.XLOOKUP(Energy_Summary_Template[[#This Row],[property_id]],Energy_Monthly[property_id],Energy_Monthly[property_name]) -> Lakeview Terrace | C3: =_xlfn.XLOOKUP(A3,'01_input_asset_master'!A$2:A$11,'01_input_asset_master'!H$2:H$11) -> 220000 | D3: =_xlfn.XLOOKUP(A3,'01_input_asset_master'!A$2:A$11,'01_input_asset_master'!I$2:I$11) -> 240 | E3: =SUMIFS('02_input_energy_monthly'!H:H,'02_input_energy_monthly'!A:A,A3) -> 1622015 | F3: =SUMIFS('02_input_energy_monthly'!I:I,'02_input_energy_monthly'!A:A,A3) -> 90298 | G3: =SUMIFS('02_input_energy_monthly'!J:J,'02_input_energy_monthly'!A:A,A3) -> 235192.16 | H3: =SUMIFS('02_input_energy_monthly'!K:K,'02_input_energy_monthly'!A:A,A3) -> 99327.8 | I3: =Energy_Summary_Template[[#This Row],[annual_gas_cost_usd]]+Energy_Summary_Template[[#This Row],[annual_electricity_cost_usd]] -> 334519.96 | J3: =E3*3.412 -> 5534315.2 | K3: =F3*100 -> 9029800 | L3: =Energy_Summary_Template[[#This Row],[electricity_kbtu]]+Energy_Summary_Template[[#This Row],[natural_gas_kbtu]] -> 14564115 | M3: =L3/C3 -> 66.200524 | N3: =E3/C3 -> 7.3727955 | O3: =F3/C3 -> 0.41044545 | P3: =I3/D3 -> 1393.8332 | Q3: =I3/C3 -> 1.5205453 | R3: =COUNTIFS('02_input_energy_monthly'!A:A,A3,'02_input_energy_monthly'!H:H,">0")+COUNTIFS('02_input_energy_monthly'!A:A,A3,'02_input_energy_monthly'!H:H,0,'02_input_energy_monthly'!I:I,">0") -> 12 | S3: =R3/12 -> 1 | T3: =59.6 -> 59.6 | U3: =M3-T3 -> 6.6005235 | V3: =IF(M3>70,"High Energy Use",IF(M3>59.6,"Above Benchmark","At/Below Benchmark")) -> Above Benchmark | W3: =IF(S3>=0.95,"Good",IF(S3>=0.75,"Needs Review","Weak")) -> Good | X3: =_xlfn.RANK.EQ(M3,$M$2:$M$11,0) -> 2 | Y3: =IF(M3>65,"Energy audit + heating system review", IF(M3>59.6,"Monitor + targeted efficiency upgrades", "Maintain performance")) -> Energy audit + heating system review
A4: WI-MF-03 | B4: =_xlfn.XLOOKUP(Energy_Summary_Template[[#This Row],[property_id]],Energy_Monthly[property_id],Energy_Monthly[property_name]) -> Northside Commons | C4: =_xlfn.XLOOKUP(A4,'01_input_asset_master'!A$2:A$11,'01_input_asset_master'!H$2:H$11) -> 145000 | D4: =_xlfn.XLOOKUP(A4,'01_input_asset_master'!A$2:A$11,'01_input_asset_master'!I$2:I$11) -> 160 | E4: =SUMIFS('02_input_energy_monthly'!H:H,'02_input_energy_monthly'!A:A,A4) -> 980726 | F4: =SUMIFS('02_input_energy_monthly'!I:I,'02_input_energy_monthly'!A:A,A4) -> 45270 | G4: =SUMIFS('02_input_energy_monthly'!J:J,'02_input_energy_monthly'!A:A,A4) -> 142205.25 | H4: =SUMIFS('02_input_energy_monthly'!K:K,'02_input_energy_monthly'!A:A,A4) -> 49797 | I4: =Energy_Summary_Template[[#This Row],[annual_gas_cost_usd]]+Energy_Summary_Template[[#This Row],[annual_electricity_cost_usd]] -> 192002.25 | J4: =E4*3.412 -> 3346237.1 | K4: =F4*100 -> 4527000 | L4: =Energy_Summary_Template[[#This Row],[electricity_kbtu]]+Energy_Summary_Template[[#This Row],[natural_gas_kbtu]] -> 7873237.1 | M4: =L4/C4 -> 54.298187 | N4: =E4/C4 -> 6.7636276 | O4: =F4/C4 -> 0.3122069 | P4: =I4/D4 -> 1200.0141 | Q4: =I4/C4 -> 1.3241534 | R4: =COUNTIFS('02_input_energy_monthly'!A:A,A4,'02_input_energy_monthly'!H:H,">0")+COUNTIFS('02_input_energy_monthly'!A:A,A4,'02_input_energy_monthly'!H:H,0,'02_input_energy_monthly'!I:I,">0") -> 12 | S4: =R4/12 -> 1 | T4: =59.6 -> 59.6 | U4: =M4-T4 -> -5.301813 | V4: =IF(M4>70,"High Energy Use",IF(M4>59.6,"Above Benchmark","At/Below Benchmark")) -> At/Below Benchmark | W4: =IF(S4>=0.95,"Good",IF(S4>=0.75,"Needs Review","Weak")) -> Good | X4: =_xlfn.RANK.EQ(M4,$M$2:$M$11,0) -> 7 | Y4: =IF(M4>65,"Energy audit + heating system review", IF(M4>59.6,"Monitor + targeted efficiency upgrades", "Maintain performance")) -> Maintain performance
A5: WI-MF-04 | B5: =_xlfn.XLOOKUP(Energy_Summary_Template[[#This Row],[property_id]],Energy_Monthly[property_id],Energy_Monthly[property_name]) -> Badger Ridge Homes | C5: =_xlfn.XLOOKUP(A5,'01_input_asset_master'!A$2:A$11,'01_input_asset_master'!H$2:H$11) -> 120000 | D5: =_xlfn.XLOOKUP(A5,'01_input_asset_master'!A$2:A$11,'01_input_asset_master'!I$2:I$11) -> 130 | E5: =SUMIFS('02_input_energy_monthly'!H:H,'02_input_energy_monthly'!A:A,A5) -> 837617 | F5: =SUMIFS('02_input_energy_monthly'!I:I,'02_input_energy_monthly'!A:A,A5) -> 45461 | G5: =SUMIFS('02_input_energy_monthly'!J:J,'02_input_energy_monthly'!A:A,A5) -> 121454.46 | H5: =SUMIFS('02_input_energy_monthly'!K:K,'02_input_energy_monthly'!A:A,A5) -> 50007.1 | I5: =Energy_Summary_Template[[#This Row],[annual_gas_cost_usd]]+Energy_Summary_Template[[#This Row],[annual_electricity_cost_usd]] -> 171461.56 | J5: =E5*3.412 -> 2857949.2 | K5: =F5*100 -> 4546100 | L5: =Energy_Summary_Template[[#This Row],[electricity_kbtu]]+Energy_Summary_Template[[#This Row],[natural_gas_kbtu]] -> 7404049.2 | M5: =L5/C5 -> 61.70041 | N5: =E5/C5 -> 6.9801417 | O5: =F5/C5 -> 0.37884167 | P5: =I5/D5 -> 1318.9351 | Q5: =I5/C5 -> 1.4288463 | R5: =COUNTIFS('02_input_energy_monthly'!A:A,A5,'02_input_energy_monthly'!H:H,">0")+COUNTIFS('02_input_energy_monthly'!A:A,A5,'02_input_energy_monthly'!H:H,0,'02_input_energy_monthly'!I:I,">0") -> 12 | S5: =R5/12 -> 1 | T5: =59.6 -> 59.6 | U5: =M5-T5 -> 2.10041 | V5: =IF(M5>70,"High Energy Use",IF(M5>59.6,"Above Benchmark","At/Below Benchmark")) -> Above Benchmark | W5: =IF(S5>=0.95,"Good",IF(S5>=0.75,"Needs Review","Weak")) -> Good | X5: =_xlfn.RANK.EQ(M5,$M$2:$M$11,0) -> 4 | Y5: =IF(M5>65,"Energy audit + heating system review", IF(M5>59.6,"Monitor + targeted efficiency upgrades", "Maintain performance")) -> Monitor + targeted efficiency upgrades
A6: WI-MF-05 | B6: =_xlfn.XLOOKUP(Energy_Summary_Template[[#This Row],[property_id]],Energy_Monthly[property_id],Energy_Monthly[property_name]) -> Oak Street Lofts | C6: =_xlfn.XLOOKUP(A6,'01_input_asset_master'!A$2:A$11,'01_input_asset_master'!H$2:H$11) -> 98000 | D6: =_xlfn.XLOOKUP(A6,'01_input_asset_master'!A$2:A$11,'01_input_asset_master'!I$2:I$11) -> 105 | E6: =SUMIFS('02_input_energy_monthly'!H:H,'02_input_energy_monthly'!A:A,A6) -> 642364 | F6: =SUMIFS('02_input_energy_monthly'!I:I,'02_input_energy_monthly'!A:A,A6) -> 25318 | G6: =SUMIFS('02_input_energy_monthly'!J:J,'02_input_energy_monthly'!A:A,A6) -> 93142.75 | H6: =SUMIFS('02_input_energy_monthly'!K:K,'02_input_energy_monthly'!A:A,A6) -> 27849.8 | I6: =Energy_Summary_Template[[#This Row],[annual_gas_cost_usd]]+Energy_Summary_Template[[#This Row],[annual_electricity_cost_usd]] -> 120992.55 | J6: =E6*3.412 -> 2191746 | K6: =F6*100 -> 2531800 | L6: =Energy_Summary_Template[[#This Row],[electricity_kbtu]]+Energy_Summary_Template[[#This Row],[natural_gas_kbtu]] -> 4723546 | M6: =L6/C6 -> 48.199449 | N6: =E6/C6 -> 6.5547347 | O6: =F6/C6 -> 0.25834694 | P6: =I6/D6 -> 1152.31 | Q6: =I6/C6 -> 1.2346179 | R6: =COUNTIFS('02_input_energy_monthly'!A:A,A6,'02_input_energy_monthly'!H:H,">0")+COUNTIFS('02_input_energy_monthly'!A:A,A6,'02_input_energy_monthly'!H:H,0,'02_input_energy_monthly'!I:I,">0") -> 12 | S6: =R6/12 -> 1 | T6: =59.6 -> 59.6 | U6: =M6-T6 -> -11.400551 | V6: =IF(M6>70,"High Energy Use",IF(M6>59.6,"Above Benchmark","At/Below Benchmark")) -> At/Below Benchmark | W6: =IF(S6>=0.95,"Good",IF(S6>=0.75,"Needs Review","Weak")) -> Good | X6: =_xlfn.RANK.EQ(M6,$M$2:$M$11,0) -> 9 | Y6: =IF(M6>65,"Energy audit + heating system review", IF(M6>59.6,"Monitor + targeted efficiency upgrades", "Maintain performance")) -> Maintain performance
A7: WI-MF-06 | B7: =_xlfn.XLOOKUP(Energy_Summary_Template[[#This Row],[property_id]],Energy_Monthly[property_id],Energy_Monthly[property_name]) -> South Park Apartments | C7: =_xlfn.XLOOKUP(A7,'01_input_asset_master'!A$2:A$11,'01_input_asset_master'!H$2:H$11) -> 185000 | D7: =_xlfn.XLOOKUP(A7,'01_input_asset_master'!A$2:A$11,'01_input_asset_master'!I$2:I$11) -> 210 | E7: =SUMIFS('02_input_energy_monthly'!H:H,'02_input_energy_monthly'!A:A,A7) -> 1394876 | F7: =SUMIFS('02_input_energy_monthly'!I:I,'02_input_energy_monthly'!A:A,A7) -> 77653 | G7: =SUMIFS('02_input_energy_monthly'!J:J,'02_input_energy_monthly'!A:A,A7) -> 202257.01 | H7: =SUMIFS('02_input_energy_monthly'!K:K,'02_input_energy_monthly'!A:A,A7) -> 85418.3 | I7: =Energy_Summary_Template[[#This Row],[annual_gas_cost_usd]]+Energy_Summary_Template[[#This Row],[annual_electricity_cost_usd]] -> 287675.31 | J7: =E7*3.412 -> 4759316.9 | K7: =F7*100 -> 7765300 | L7: =Energy_Summary_Template[[#This Row],[electricity_kbtu]]+Energy_Summary_Template[[#This Row],[natural_gas_kbtu]] -> 12524617 | M7: =L7/C7 -> 67.700632 | N7: =E7/C7 -> 7.5398703 | O7: =F7/C7 -> 0.41974595 | P7: =I7/D7 -> 1369.8824 | Q7: =I7/C7 -> 1.5550017 | R7: =COUNTIFS('02_input_energy_monthly'!A:A,A7,'02_input_energy_monthly'!H:H,">0")+COUNTIFS('02_input_energy_monthly'!A:A,A7,'02_input_energy_monthly'!H:H,0,'02_input_energy_monthly'!I:I,">0") -> 12 | S7: =R7/12 -> 1 | T7: =59.6 -> 59.6 | U7: =M7-T7 -> 8.100632 | V7: =IF(M7>70,"High Energy Use",IF(M7>59.6,"Above Benchmark","At/Below Benchmark")) -> Above Benchmark | W7: =IF(S7>=0.95,"Good",IF(S7>=0.75,"Needs Review","Weak")) -> Good | X7: =_xlfn.RANK.EQ(M7,$M$2:$M$11,0) -> 1 | Y7: =IF(M7>65,"Energy audit + heating system review", IF(M7>59.6,"Monitor + targeted efficiency upgrades", "Maintain performance")) -> Energy audit + heating system review
A8: WI-MF-07 | B8: =_xlfn.XLOOKUP(Energy_Summary_Template[[#This Row],[property_id]],Energy_Monthly[property_id],Energy_Monthly[property_name]) -> Fox River Flats | C8: =_xlfn.XLOOKUP(A8,'01_input_asset_master'!A$2:A$11,'01_input_asset_master'!H$2:H$11) -> 135000 | D8: =_xlfn.XLOOKUP(A8,'01_input_asset_master'!A$2:A$11,'01_input_asset_master'!I$2:I$11) -> 150 | E8: =SUMIFS('02_input_energy_monthly'!H:H,'02_input_energy_monthly'!A:A,A8) -> 907943 | F8: =SUMIFS('02_input_energy_monthly'!I:I,'02_input_energy_monthly'!A:A,A8) -> 38951 | G8: =SUMIFS('02_input_energy_monthly'!J:J,'02_input_energy_monthly'!A:A,A8) -> 131651.71 | H8: =SUMIFS('02_input_energy_monthly'!K:K,'02_input_energy_monthly'!A:A,A8) -> 42846.1 | I8: =Energy_Summary_Template[[#This Row],[annual_gas_cost_usd]]+Energy_Summary_Template[[#This Row],[annual_electricity_cost_usd]] -> 174497.81 | J8: =E8*3.412 -> 3097901.5 | K8: =F8*100 -> 3895100 | L8: =Energy_Summary_Template[[#This Row],[electricity_kbtu]]+Energy_Summary_Template[[#This Row],[natural_gas_kbtu]] -> 6993001.5 | M8: =L8/C8 -> 51.800011 | N8: =E8/C8 -> 6.7255037 | O8: =F8/C8 -> 0.28852593 | P8: =I8/D8 -> 1163.3187 | Q8: =I8/C8 -> 1.2925764 | R8: =COUNTIFS('02_input_energy_monthly'!A:A,A8,'02_input_energy_monthly'!H:H,">0")+COUNTIFS('02_input_energy_monthly'!A:A,A8,'02_input_energy_monthly'!H:H,0,'02_input_energy_monthly'!I:I,">0") -> 12 | S8: =R8/12 -> 1 | T8: =59.6 -> 59.6 | U8: =M8-T8 -> -7.7999888 | V8: =IF(M8>70,"High Energy Use",IF(M8>59.6,"Above Benchmark","At/Below Benchmark")) -> At/Below Benchmark | W8: =IF(S8>=0.95,"Good",IF(S8>=0.75,"Needs Review","Weak")) -> Good | X8: =_xlfn.RANK.EQ(M8,$M$2:$M$11,0) -> 8 | Y8: =IF(M8>65,"Energy audit + heating system review", IF(M8>59.6,"Monitor + targeted efficiency upgrades", "Maintain performance")) -> Maintain performance
A9: WI-MF-08 | B9: =_xlfn.XLOOKUP(Energy_Summary_Template[[#This Row],[property_id]],Energy_Monthly[property_id],Energy_Monthly[property_name]) -> Prairie View Residences | C9: =_xlfn.XLOOKUP(A9,'01_input_asset_master'!A$2:A$11,'01_input_asset_master'!H$2:H$11) -> 110000 | D9: =_xlfn.XLOOKUP(A9,'01_input_asset_master'!A$2:A$11,'01_input_asset_master'!I$2:I$11) -> 120 | E9: =SUMIFS('02_input_energy_monthly'!H:H,'02_input_energy_monthly'!A:A,A9) -> 760039 | F9: =SUMIFS('02_input_energy_monthly'!I:I,'02_input_energy_monthly'!A:A,A9) -> 37317 | G9: =SUMIFS('02_input_energy_monthly'!J:J,'02_input_energy_monthly'!A:A,A9) -> 110205.61 | H9: =SUMIFS('02_input_energy_monthly'!K:K,'02_input_energy_monthly'!A:A,A9) -> 41048.7 | I9: =Energy_Summary_Template[[#This Row],[annual_gas_cost_usd]]+Energy_Summary_Template[[#This Row],[annual_electricity_cost_usd]] -> 151254.31 | J9: =E9*3.412 -> 2593253.1 | K9: =F9*100 -> 3731700 | L9: =Energy_Summary_Template[[#This Row],[electricity_kbtu]]+Energy_Summary_Template[[#This Row],[natural_gas_kbtu]] -> 6324953.1 | M9: =L9/C9 -> 57.499573 | N9: =E9/C9 -> 6.9094455 | O9: =F9/C9 -> 0.33924545 | P9: =I9/D9 -> 1260.4526 | Q9: =I9/C9 -> 1.3750392 | R9: =COUNTIFS('02_input_energy_monthly'!A:A,A9,'02_input_energy_monthly'!H:H,">0")+COUNTIFS('02_input_energy_monthly'!A:A,A9,'02_input_energy_monthly'!H:H,0,'02_input_energy_monthly'!I:I,">0") -> 12 | S9: =R9/12 -> 1 | T9: =59.6 -> 59.6 | U9: =M9-T9 -> -2.1004267 | V9: =IF(M9>70,"High Energy Use",IF(M9>59.6,"Above Benchmark","At/Below Benchmark")) -> At/Below Benchmark | W9: =IF(S9>=0.95,"Good",IF(S9>=0.75,"Needs Review","Weak")) -> Good | X9: =_xlfn.RANK.EQ(M9,$M$2:$M$11,0) -> 6 | Y9: =IF(M9>65,"Energy audit + heating system review", IF(M9>59.6,"Monitor + targeted efficiency upgrades", "Maintain performance")) -> Maintain performance
A10: WI-MF-09 | B10: =_xlfn.XLOOKUP(Energy_Summary_Template[[#This Row],[property_id]],Energy_Monthly[property_id],Energy_Monthly[property_name]) -> Capitol Square Homes | C10: =_xlfn.XLOOKUP(A10,'01_input_asset_master'!A$2:A$11,'01_input_asset_master'!H$2:H$11) -> 175000 | D10: =_xlfn.XLOOKUP(A10,'01_input_asset_master'!A$2:A$11,'01_input_asset_master'!I$2:I$11) -> 190 | E10: =SUMIFS('02_input_energy_monthly'!H:H,'02_input_energy_monthly'!A:A,A10) -> 1169146 | F10: =SUMIFS('02_input_energy_monthly'!I:I,'02_input_energy_monthly'!A:A,A10) -> 42358 | G10: =SUMIFS('02_input_energy_monthly'!J:J,'02_input_energy_monthly'!A:A,A10) -> 169526.15 | H10: =SUMIFS('02_input_energy_monthly'!K:K,'02_input_energy_monthly'!A:A,A10) -> 46593.8 | I10: =Energy_Summary_Template[[#This Row],[annual_gas_cost_usd]]+Energy_Summary_Template[[#This Row],[annual_electricity_cost_usd]] -> 216119.95 | J10: =E10*3.412 -> 3989126.2 | K10: =F10*100 -> 4235800 | L10: =Energy_Summary_Template[[#This Row],[electricity_kbtu]]+Energy_Summary_Template[[#This Row],[natural_gas_kbtu]] -> 8224926.2 | M10: =L10/C10 -> 46.999578 | N10: =E10/C10 -> 6.6808343 | O10: =F10/C10 -> 0.24204571 | P10: =I10/D10 -> 1137.4734 | Q10: =I10/C10 -> 1.2349711 | R10: =COUNTIFS('02_input_energy_monthly'!A:A,A10,'02_input_energy_monthly'!H:H,">0")+COUNTIFS('02_input_energy_monthly'!A:A,A10,'02_input_energy_monthly'!H:H,0,'02_input_energy_monthly'!I:I,">0") -> 12 | S10: =R10/12 -> 1 | T10: =59.6 -> 59.6 | U10: =M10-T10 -> -12.600422 | V10: =IF(M10>70,"High Energy Use",IF(M10>59.6,"Above Benchmark","At/Below Benchmark")) -> At/Below Benchmark | W10: =IF(S10>=0.95,"Good",IF(S10>=0.75,"Needs Review","Weak")) -> Good | X10: =_xlfn.RANK.EQ(M10,$M$2:$M$11,0) -> 10 | Y10: =IF(M10>65,"Energy audit + heating system review", IF(M10>59.6,"Monitor + targeted efficiency upgrades", "Maintain performance")) -> Maintain performance
A11: WI-MF-10 | B11: =_xlfn.XLOOKUP(Energy_Summary_Template[[#This Row],[property_id]],Energy_Monthly[property_id],Energy_Monthly[property_name]) -> Harbor Point Apartments | C11: =_xlfn.XLOOKUP(A11,'01_input_asset_master'!A$2:A$11,'01_input_asset_master'!H$2:H$11) -> 160000 | D11: =_xlfn.XLOOKUP(A11,'01_input_asset_master'!A$2:A$11,'01_input_asset_master'!I$2:I$11) -> 175 | E11: =SUMIFS('02_input_energy_monthly'!H:H,'02_input_energy_monthly'!A:A,A11) -> 1120844 | F11: =SUMIFS('02_input_energy_monthly'!I:I,'02_input_energy_monthly'!A:A,A11) -> 62399 | G11: =SUMIFS('02_input_energy_monthly'!J:J,'02_input_energy_monthly'!A:A,A11) -> 162522.35 | H11: =SUMIFS('02_input_energy_monthly'!K:K,'02_input_energy_monthly'!A:A,A11) -> 68638.9 | I11: =Energy_Summary_Template[[#This Row],[annual_gas_cost_usd]]+Energy_Summary_Template[[#This Row],[annual_electricity_cost_usd]] -> 231161.25 | J11: =E11*3.412 -> 3824319.7 | K11: =F11*100 -> 6239900 | L11: =Energy_Summary_Template[[#This Row],[electricity_kbtu]]+Energy_Summary_Template[[#This Row],[natural_gas_kbtu]] -> 10064220 | M11: =L11/C11 -> 62.901373 | N11: =E11/C11 -> 7.005275 | O11: =F11/C11 -> 0.38999375 | P11: =I11/D11 -> 1320.9214 | Q11: =I11/C11 -> 1.4447578 | R11: =COUNTIFS('02_input_energy_monthly'!A:A,A11,'02_input_energy_monthly'!H:H,">0")+COUNTIFS('02_input_energy_monthly'!A:A,A11,'02_input_energy_monthly'!H:H,0,'02_input_energy_monthly'!I:I,">0") -> 12 | S11: =R11/12 -> 1 | T11: =59.6 -> 59.6 | U11: =M11-T11 -> 3.3013733 | V11: =IF(M11>70,"High Energy Use",IF(M11>59.6,"Above Benchmark","At/Below Benchmark")) -> Above Benchmark | W11: =IF(S11>=0.95,"Good",IF(S11>=0.75,"Needs Review","Weak")) -> Good | X11: =_xlfn.RANK.EQ(M11,$M$2:$M$11,0) -> 3 | Y11: =IF(M11>65,"Energy audit + heating system review", IF(M11>59.6,"Monitor + targeted efficiency upgrades", "Maintain performance")) -> Monitor + targeted efficiency upgrades

Sheet 03_input_water_monthly
A1: property_id | B1: property_name | C1: city | D1: county | E1: month | F1: water_gallons | G1: water_cost_usd | H1: sewer_cost_usd | I1: irrigation_included | J1: owner_or_tenant_paid | K1: data_quality | L1: notes
A2: WI-MF-01 | B2: Riverbend Apartments | C2: Madison | D2: Dane | E2: 45658 | F2: 803652 | G2: 3544.11 | H2: 4303.56 | I2: No | J2: Owner/Paid by property | K2: Actual | L2: Simulated using EPA 82 gal/person/day reference; replace with water bills/Portfolio Manager export for real diligence.
A3: WI-MF-01 | B3: Riverbend Apartments | C3: Madison | D3: Dane | E3: 45689 | F3: 664746 | G3: 2931.53 | H3: 3559.71 | I3: No | J3: Owner/Paid by property | K3: Actual | L3: Simulated using EPA 82 gal/person/day reference; replace with water bills/Portfolio Manager export for real diligence.
A4: WI-MF-01 | B4: Riverbend Apartments | C4: Madison | D4: Dane | E4: 45717 | F4: 808895 | G4: 3567.23 | H4: 4331.63 | I4: No | J4: Owner/Paid by property | K4: Actual | L4: Simulated using EPA 82 gal/person/day reference; replace with water bills/Portfolio Manager export for real diligence.
A5: WI-MF-01 | B5: Riverbend Apartments | C5: Madison | D5: Dane | E5: 45748 | F5: 804546 | G5: 3548.05 | H5: 4308.34 | I5: No | J5: Owner/Paid by property | K5: Actual | L5: Simulated using EPA 82 gal/person/day reference; replace with water bills/Portfolio Manager export for real diligence.
A6: WI-MF-01 | B6: Riverbend Apartments | C6: Madison | D6: Dane | E6: 45778 | F6: 923382 | G6: 4072.12 | H6: 4944.71 | I6: Yes | J6: Owner/Paid by property | K6: Actual | L6: Simulated using EPA 82 gal/person/day reference; replace with water bills/Portfolio Manager export for real diligence.
A7: WI-MF-01 | B7: Riverbend Apartments | C7: Madison | D7: Dane | E7: 45809 | F7: 1018532 | G7: 4491.73 | H7: 5454.24 | I7: Yes | J7: Owner/Paid by property | K7: Actual | L7: Simulated using EPA 82 gal/person/day reference; replace with water bills/Portfolio Manager export for real diligence.
A8: WI-MF-01 | B8: Riverbend Apartments | C8: Madison | D8: Dane | E8: 45839 | F8: 1133183 | G8: 4997.34 | H8: 6068.2 | I8: Yes | J8: Owner/Paid by property | K8: Actual | L8: Simulated using EPA 82 gal/person/day reference; replace with water bills/Portfolio Manager export for real diligence.
A9: WI-MF-01 | B9: Riverbend Apartments | C9: Madison | D9: Dane | E9: 45870 | F9: 1053458 | G9: 4645.75 | H9: 5641.27 | I9: Yes | J9: Owner/Paid by property | K9: Actual | L9: Simulated using EPA 82 gal/person/day reference; replace with water bills/Portfolio Manager export for real diligence.
A10: WI-MF-01 | B10: Riverbend Apartments | C10: Madison | D10: Dane | E10: 45901 | F10: 899219 | G10: 3965.55 | H10: 4815.32 | I10: Yes | J10: Owner/Paid by property | K10: Actual | L10: Simulated using EPA 82 gal/person/day reference; replace with water bills/Portfolio Manager export for real diligence.
A11: WI-MF-01 | B11: Riverbend Apartments | C11: Madison | D11: Dane | E11: 45931 | F11: 836618 | G11: 3689.49 | H11: 4480.09 | I11: No | J11: Owner/Paid by property | K11: Actual | L11: Simulated using EPA 82 gal/person/day reference; replace with water bills/Portfolio Manager export for real diligence.
A12: WI-MF-01 | B12: Riverbend Apartments | C12: Madison | D12: Dane | E12: 45962 | F12: 771455 | G12: 3402.12 | H12: 4131.14 | I12: No | J12: Owner/Paid by property | K12: Actual | L12: Simulated using EPA 82 gal/person/day reference; replace with water bills/Portfolio Manager export for real diligence.
A13: WI-MF-01 | B13: Riverbend Apartments | C13: Madison | D13: Dane | E13: 45992 | F13: 804837 | G13: 3549.33 | H13: 4309.9 | I13: No | J13: Owner/Paid by property | K13: Actual | L13: Simulated using EPA 82 gal/person/day reference; replace with water bills/Portfolio Manager export for real diligence.
... A121: WI-MF-10 | B121: Harbor Point Apartments | C121: Kenosha | D121: Kenosha | E121: 45992 | F121: 873848 | G121: 3927.07 | H121: 4768.59 | I121: No | J121: Owner/Paid by property | K121: Actual | L121: Simulated using EPA 82 gal/person/day reference; replace with water bills/Portfolio Manager export for real diligence.

Sheet 12_calc_water_summary
A1: property_id | B1: property_name | C1: gross_floor_area_sqft | D1: unit | E1: annual_water_gallons | F1: annual_water_cost_usd | G1: annual_sewer_cost_usd | H1: annual_total_water_sewer_cost_usd | I1: water_intensity_gal_sqft | J1: water_per_unit_gal | K1: water_cost_per_unit | L1: water_cost_per_sqft | M1: months_with_water_data | N1: water_data_coverage_pct | O1: water_performance_flag | P1: water_cost_flag | Q1: recommended_water_action | R1: water_cost_priority_rank | S1: water_intensity_rank | T1: combined_water_priority_score | U1: combined_water_priority_rank
A2: WI-MF-01 | B2: =_xlfn.XLOOKUP(A2,'01_input_asset_master'!A$2:A$11,'01_input_asset_master'!B$2:B$11) -> Riverbend Apartments | C2: =_xlfn.XLOOKUP(A2,'01_input_asset_master'!A$2:A$11,'01_input_asset_master'!H$2:H$11) -> 165000 | D2: =_xlfn.XLOOKUP(A2,'01_input_asset_master'!A$2:A$11,'01_input_asset_master'!I$2:I$11) -> 180 | E2: =SUMIFS('03_input_water_monthly'!G:G,'03_input_water_monthly'!A:A,A2) -> 46404.35 | F2: =SUMIFS('03_input_water_monthly'!H:H,'03_input_water_monthly'!A:A,A2) -> 56348.11 | G2: =SUMIFS('03_input_water_monthly'!H:H,'03_input_water_monthly'!A:A,A2) -> 56348.11 | H2: =F2+G2 -> 112696.22 | I2: =E2/C2 -> 0.28123848 | J2: =E2/D2 -> 257.80194 | K2: =H2/D2 -> 626.09011 | L2: =H2/C2 -> 0.68300739 | M2: =COUNTIFS('03_input_water_monthly'!A:A,A2,'03_input_water_monthly'!E:E,">0") -> 12 | N2: =M2/12 -> 1 | O2: =IF(J2>75000,"High Water Use",IF(J2>55000,"Moderate","Efficient/Low")) -> Efficient/Low | P2: =IF(K2>700,"High Cost",IF(K2>500,"Moderate Cost","Low Cost")) -> Moderate Cost | Q2: =IF(O2="High Water Use","Leak detection + low-flow fixtures + irrigation review",IF(O2="Moderate","Monitor usage + fixture review","Maintain performance")) -> Maintain performance | R2: =_xlfn.RANK.EQ(K2,$K$2:$K$11,0) -> 4 | S2: =_xlfn.RANK.EQ(I2,$I$2:$I$11,0) -> 4 | T2: =_xlfn.RANK.EQ(J2,$J$2:$J$11,0)+_xlfn.RANK.EQ(K2,$K$2:$K$11,0) -> 8 | U2: =_xlfn.RANK.EQ(J2,$J$2:$J$11,0)+_xlfn.RANK.EQ(K2,$K$2:$K$11,0) -> 8 | Y2: Water performance analysis shows which multifamily properties have the highest annual water use and water/sewer cost after normalizing by units and square footage. The most useful KPI is water gallons per unit because it reflects resident-level and operational water demand. Properties with high water use per unit and high water/sewer cost per unit should be prioritized for leak detection, low-flow fixtures, plumbing review, and irrigation checks.
A3: WI-MF-02 | B3: =_xlfn.XLOOKUP(A3,'01_input_asset_master'!A$2:A$11,'01_input_asset_master'!B$2:B$11) -> Lakeview Terrace | C3: =_xlfn.XLOOKUP(A3,'01_input_asset_master'!A$2:A$11,'01_input_asset_master'!H$2:H$11) -> 220000 | D3: =_xlfn.XLOOKUP(A3,'01_input_asset_master'!A$2:A$11,'01_input_asset_master'!I$2:I$11) -> 240 | E3: =SUMIFS('03_input_water_monthly'!G:G,'03_input_water_monthly'!A:A,A3) -> 79558.5 | F3: =SUMIFS('03_input_water_monthly'!H:H,'03_input_water_monthly'!A:A,A3) -> 96606.74 | G3: =SUMIFS('03_input_water_monthly'!H:H,'03_input_water_monthly'!A:A,A3) -> 96606.74 | H3: =F3+G3 -> 193213.48 | I3: =E3/C3 -> 0.36162955 | J3: =E3/D3 -> 331.49375 | K3: =H3/D3 -> 805.05617 | L3: =H3/C3 -> 0.87824309 | M3: =COUNTIFS('03_input_water_monthly'!A:A,A3,'03_input_water_monthly'!E:E,">0") -> 12 | N3: =M3/12 -> 1 | O3: =IF(J3>75000,"High Water Use",IF(J3>55000,"Moderate","Efficient/Low")) -> Efficient/Low | P3: =IF(K3>700,"High Cost",IF(K3>500,"Moderate Cost","Low Cost")) -> High Cost | Q3: =IF(O3="High Water Use","Leak detection + low-flow fixtures + irrigation review",IF(O3="Moderate","Monitor usage + fixture review","Maintain performance")) -> Maintain performance | R3: =_xlfn.RANK.EQ(K3,$K$2:$K$11,0) -> 1 | S3: =_xlfn.RANK.EQ(I3,$I$2:$I$11,0) -> 1 | T3: =_xlfn.RANK.EQ(J3,$J$2:$J$11,0)+_xlfn.RANK.EQ(K3,$K$2:$K$11,0) -> 2 | U3: =_xlfn.RANK.EQ(J3,$J$2:$J$11,0)+_xlfn.RANK.EQ(K3,$K$2:$K$11,0) -> 2
A4: WI-MF-03 | B4: =_xlfn.XLOOKUP(A4,'01_input_asset_master'!A$2:A$11,'01_input_asset_master'!B$2:B$11) -> Northside Commons | C4: =_xlfn.XLOOKUP(A4,'01_input_asset_master'!A$2:A$11,'01_input_asset_master'!H$2:H$11) -> 145000 | D4: =_xlfn.XLOOKUP(A4,'01_input_asset_master'!A$2:A$11,'01_input_asset_master'!I$2:I$11) -> 160 | E4: =SUMIFS('03_input_water_monthly'!G:G,'03_input_water_monthly'!A:A,A4) -> 37799.44 | F4: =SUMIFS('03_input_water_monthly'!H:H,'03_input_water_monthly'!A:A,A4) -> 45899.32 | G4: =SUMIFS('03_input_water_monthly'!H:H,'03_input_water_monthly'!A:A,A4) -> 45899.32 | H4: =F4+G4 -> 91798.64 | I4: =E4/C4 -> 0.26068579 | J4: =E4/D4 -> 236.2465 | K4: =H4/D4 -> 573.7415 | L4: =H4/C4 -> 0.63309407 | M4: =COUNTIFS('03_input_water_monthly'!A:A,A4,'03_input_water_monthly'!E:E,">0") -> 12 | N4: =M4/12 -> 1 | O4: =IF(J4>75000,"High Water Use",IF(J4>55000,"Moderate","Efficient/Low")) -> Efficient/Low | P4: =IF(K4>700,"High Cost",IF(K4>500,"Moderate Cost","Low Cost")) -> Moderate Cost | Q4: =IF(O4="High Water Use","Leak detection + low-flow fixtures + irrigation review",IF(O4="Moderate","Monitor usage + fixture review","Maintain performance")) -> Maintain performance | R4: =_xlfn.RANK.EQ(K4,$K$2:$K$11,0) -> 6 | S4: =_xlfn.RANK.EQ(I4,$I$2:$I$11,0) -> 6 | T4: =_xlfn.RANK.EQ(J4,$J$2:$J$11,0)+_xlfn.RANK.EQ(K4,$K$2:$K$11,0) -> 12 | U4: =_xlfn.RANK.EQ(J4,$J$2:$J$11,0)+_xlfn.RANK.EQ(K4,$K$2:$K$11,0) -> 12
A5: WI-MF-04 | B5: =_xlfn.XLOOKUP(A5,'01_input_asset_master'!A$2:A$11,'01_input_asset_master'!B$2:B$11) -> Badger Ridge Homes | C5: =_xlfn.XLOOKUP(A5,'01_input_asset_master'!A$2:A$11,'01_input_asset_master'!H$2:H$11) -> 120000 | D5: =_xlfn.XLOOKUP(A5,'01_input_asset_master'!A$2:A$11,'01_input_asset_master'!I$2:I$11) -> 130 | E5: =SUMIFS('03_input_water_monthly'!G:G,'03_input_water_monthly'!A:A,A5) -> 32382.31 | F5: =SUMIFS('03_input_water_monthly'!H:H,'03_input_water_monthly'!A:A,A5) -> 39321.36 | G5: =SUMIFS('03_input_water_monthly'!H:H,'03_input_water_monthly'!A:A,A5) -> 39321.36 | H5: =F5+G5 -> 78642.72 | I5: =E5/C5 -> 0.26985258 | J5: =E5/D5 -> 249.09469 | K5: =H5/D5 -> 604.944 | L5: =H5/C5 -> 0.655356 | M5: =COUNTIFS('03_input_water_monthly'!A:A,A5,'03_input_water_monthly'!E:E,">0") -> 12 | N5: =M5/12 -> 1 | O5: =IF(J5>75000,"High Water Use",IF(J5>55000,"Moderate","Efficient/Low")) -> Efficient/Low | P5: =IF(K5>700,"High Cost",IF(K5>500,"Moderate Cost","Low Cost")) -> Moderate Cost | Q5: =IF(O5="High Water Use","Leak detection + low-flow fixtures + irrigation review",IF(O5="Moderate","Monitor usage + fixture review","Maintain performance")) -> Maintain performance | R5: =_xlfn.RANK.EQ(K5,$K$2:$K$11,0) -> 5 | S5: =_xlfn.RANK.EQ(I5,$I$2:$I$11,0) -> 5 | T5: =_xlfn.RANK.EQ(J5,$J$2:$J$11,0)+_xlfn.RANK.EQ(K5,$K$2:$K$11,0) -> 10 | U5: =_xlfn.RANK.EQ(J5,$J$2:$J$11,0)+_xlfn.RANK.EQ(K5,$K$2:$K$11,0) -> 10
A6: WI-MF-05 | B6: =_xlfn.XLOOKUP(A6,'01_input_asset_master'!A$2:A$11,'01_input_asset_master'!B$2:B$11) -> Oak Street Lofts | C6: =_xlfn.XLOOKUP(A6,'01_input_asset_master'!A$2:A$11,'01_input_asset_master'!H$2:H$11) -> 98000 | D6: =_xlfn.XLOOKUP(A6,'01_input_asset_master'!A$2:A$11,'01_input_asset_master'!I$2:I$11) -> 105 | E6: =SUMIFS('03_input_water_monthly'!G:G,'03_input_water_monthly'!A:A,A6) -> 20938.79 | F6: =SUMIFS('03_input_water_monthly'!H:H,'03_input_water_monthly'!A:A,A6) -> 25425.67 | G6: =SUMIFS('03_input_water_monthly'!H:H,'03_input_water_monthly'!A:A,A6) -> 25425.67 | H6: =F6+G6 -> 50851.34 | I6: =E6/C6 -> 0.21366112 | J6: =E6/D6 -> 199.41705 | K6: =H6/D6 -> 484.29848 | L6: =H6/C6 -> 0.51889122 | M6: =COUNTIFS('03_input_water_monthly'!A:A,A6,'03_input_water_monthly'!E:E,">0") -> 12 | N6: =M6/12 -> 1 | O6: =IF(J6>75000,"High Water Use",IF(J6>55000,"Moderate","Efficient/Low")) -> Efficient/Low | P6: =IF(K6>700,"High Cost",IF(K6>500,"Moderate Cost","Low Cost")) -> Low Cost | Q6: =IF(O6="High Water Use","Leak detection + low-flow fixtures + irrigation review",IF(O6="Moderate","Monitor usage + fixture review","Maintain performance")) -> Maintain performance | R6: =_xlfn.RANK.EQ(K6,$K$2:$K$11,0) -> 10 | S6: =_xlfn.RANK.EQ(I6,$I$2:$I$11,0) -> 10 | T6: =_xlfn.RANK.EQ(J6,$J$2:$J$11,0)+_xlfn.RANK.EQ(K6,$K$2:$K$11,0) -> 20 | U6: =_xlfn.RANK.EQ(J6,$J$2:$J$11,0)+_xlfn.RANK.EQ(K6,$K$2:$K$11,0) -> 20
A7: WI-MF-06 | B7: =_xlfn.XLOOKUP(A7,'01_input_asset_master'!A$2:A$11,'01_input_asset_master'!B$2:B$11) -> South Park Apartments | C7: =_xlfn.XLOOKUP(A7,'01_input_asset_master'!A$2:A$11,'01_input_asset_master'!H$2:H$11) -> 185000 | D7: =_xlfn.XLOOKUP(A7,'01_input_asset_master'!A$2:A$11,'01_input_asset_master'!I$2:I$11) -> 210 | E7: =SUMIFS('03_input_water_monthly'!G:G,'03_input_water_monthly'!A:A,A7) -> 66315.92 | F7: =SUMIFS('03_input_water_monthly'!H:H,'03_input_water_monthly'!A:A,A7) -> 80526.49 | G7: =SUMIFS('03_input_water_monthly'!H:H,'03_input_water_monthly'!A:A,A7) -> 80526.49 | H7: =F7+G7 -> 161052.98 | I7: =E7/C7 -> 0.35846443 | J7: =E7/D7 -> 315.7901 | K7: =H7/D7 -> 766.91895 | L7: =H7/C7 -> 0.87055665 | M7: =COUNTIFS('03_input_water_monthly'!A:A,A7,'03_input_water_monthly'!E:E,">0") -> 12 | N7: =M7/12 -> 1 | O7: =IF(J7>75000,"High Water Use",IF(J7>55000,"Moderate","Efficient/Low")) -> Efficient/Low | P7: =IF(K7>700,"High Cost",IF(K7>500,"Moderate Cost","Low Cost")) -> High Cost | Q7: =IF(O7="High Water Use","Leak detection + low-flow fixtures + irrigation review",IF(O7="Moderate","Monitor usage + fixture review","Maintain performance")) -> Maintain performance | R7: =_xlfn.RANK.EQ(K7,$K$2:$K$11,0) -> 2 | S7: =_xlfn.RANK.EQ(I7,$I$2:$I$11,0) -> 2 | T7: =_xlfn.RANK.EQ(J7,$J$2:$J$11,0)+_xlfn.RANK.EQ(K7,$K$2:$K$11,0) -> 4 | U7: =_xlfn.RANK.EQ(J7,$J$2:$J$11,0)+_xlfn.RANK.EQ(K7,$K$2:$K$11,0) -> 4
A8: WI-MF-07 | B8: =_xlfn.XLOOKUP(A8,'01_input_asset_master'!A$2:A$11,'01_input_asset_master'!B$2:B$11) -> Fox River Flats | C8: =_xlfn.XLOOKUP(A8,'01_input_asset_master'!A$2:A$11,'01_input_asset_master'!H$2:H$11) -> 135000 | D8: =_xlfn.XLOOKUP(A8,'01_input_asset_master'!A$2:A$11,'01_input_asset_master'!I$2:I$11) -> 150 | E8: =SUMIFS('03_input_water_monthly'!G:G,'03_input_water_monthly'!A:A,A8) -> 31331.91 | F8: =SUMIFS('03_input_water_monthly'!H:H,'03_input_water_monthly'!A:A,A8) -> 38045.88 | G8: =SUMIFS('03_input_water_monthly'!H:H,'03_input_water_monthly'!A:A,A8) -> 38045.88 | H8: =F8+G8 -> 76091.76 | I8: =E8/C8 -> 0.23208822 | J8: =E8/D8 -> 208.8794 | K8: =H8/D8 -> 507.2784 | L8: =H8/C8 -> 0.56364267 | M8: =COUNTIFS('03_input_water_monthly'!A:A,A8,'03_input_water_monthly'!E:E,">0") -> 12 | N8: =M8/12 -> 1 | O8: =IF(J8>75000,"High Water Use",IF(J8>55000,"Moderate","Efficient/Low")) -> Efficient/Low | P8: =IF(K8>700,"High Cost",IF(K8>500,"Moderate Cost","Low Cost")) -> Moderate Cost | Q8: =IF(O8="High Water Use","Leak detection + low-flow fixtures + irrigation review",IF(O8="Moderate","Monitor usage + fixture review","Maintain performance")) -> Maintain performance | R8: =_xlfn.RANK.EQ(K8,$K$2:$K$11,0) -> 8 | S8: =_xlfn.RANK.EQ(I8,$I$2:$I$11,0) -> 8 | T8: =_xlfn.RANK.EQ(J8,$J$2:$J$11,0)+_xlfn.RANK.EQ(K8,$K$2:$K$11,0) -> 16 | U8: =_xlfn.RANK.EQ(J8,$J$2:$J$11,0)+_xlfn.RANK.EQ(K8,$K$2:$K$11,0) -> 16
A9: WI-MF-08 | B9: =_xlfn.XLOOKUP(A9,'01_input_asset_master'!A$2:A$11,'01_input_asset_master'!B$2:B$11) -> Prairie View Residences | C9: =_xlfn.XLOOKUP(A9,'01_input_asset_master'!A$2:A$11,'01_input_asset_master'!H$2:H$11) -> 110000 | D9: =_xlfn.XLOOKUP(A9,'01_input_asset_master'!A$2:A$11,'01_input_asset_master'!I$2:I$11) -> 120 | E9: =SUMIFS('03_input_water_monthly'!G:G,'03_input_water_monthly'!A:A,A9) -> 27447.84 | F9: =SUMIFS('03_input_water_monthly'!H:H,'03_input_water_monthly'!A:A,A9) -> 33329.51 | G9: =SUMIFS('03_input_water_monthly'!H:H,'03_input_water_monthly'!A:A,A9) -> 33329.51 | H9: =F9+G9 -> 66659.02 | I9: =E9/C9 -> 0.24952582 | J9: =E9/D9 -> 228.732 | K9: =H9/D9 -> 555.49183 | L9: =H9/C9 -> 0.60599109 | M9: =COUNTIFS('03_input_water_monthly'!A:A,A9,'03_input_water_monthly'!E:E,">0") -> 12 | N9: =M9/12 -> 1 | O9: =IF(J9>75000,"High Water Use",IF(J9>55000,"Moderate","Efficient/Low")) -> Efficient/Low | P9: =IF(K9>700,"High Cost",IF(K9>500,"Moderate Cost","Low Cost")) -> Moderate Cost | Q9: =IF(O9="High Water Use","Leak detection + low-flow fixtures + irrigation review",IF(O9="Moderate","Monitor usage + fixture review","Maintain performance")) -> Maintain performance | R9: =_xlfn.RANK.EQ(K9,$K$2:$K$11,0) -> 7 | S9: =_xlfn.RANK.EQ(I9,$I$2:$I$11,0) -> 7 | T9: =_xlfn.RANK.EQ(J9,$J$2:$J$11,0)+_xlfn.RANK.EQ(K9,$K$2:$K$11,0) -> 14 | U9: =_xlfn.RANK.EQ(J9,$J$2:$J$11,0)+_xlfn.RANK.EQ(K9,$K$2:$K$11,0) -> 14
A10: WI-MF-09 | B10: =_xlfn.XLOOKUP(A10,'01_input_asset_master'!A$2:A$11,'01_input_asset_master'!B$2:B$11) -> Capitol Square Homes | C10: =_xlfn.XLOOKUP(A10,'01_input_asset_master'!A$2:A$11,'01_input_asset_master'!H$2:H$11) -> 175000 | D10: =_xlfn.XLOOKUP(A10,'01_input_asset_master'!A$2:A$11,'01_input_asset_master'!I$2:I$11) -> 190 | E10: =SUMIFS('03_input_water_monthly'!G:G,'03_input_water_monthly'!A:A,A10) -> 38401.79 | F10: =SUMIFS('03_input_water_monthly'!H:H,'03_input_water_monthly'!A:A,A10) -> 46630.74 | G10: =SUMIFS('03_input_water_monthly'!H:H,'03_input_water_monthly'!A:A,A10) -> 46630.74 | H10: =F10+G10 -> 93261.48 | I10: =E10/C10 -> 0.2194388 | J10: =E10/D10 -> 202.11468 | K10: =H10/D10 -> 490.84989 | L10: =H10/C10 -> 0.53292274 | M10: =COUNTIFS('03_input_water_monthly'!A:A,A10,'03_input_water_monthly'!E:E,">0") -> 12 | N10: =M10/12 -> 1 | O10: =IF(J10>75000,"High Water Use",IF(J10>55000,"Moderate","Efficient/Low")) -> Efficient/Low | P10: =IF(K10>700,"High Cost",IF(K10>500,"Moderate Cost","Low Cost")) -> Low Cost | Q10: =IF(O10="High Water Use","Leak detection + low-flow fixtures + irrigation review",IF(O10="Moderate","Monitor usage + fixture review","Maintain performance")) -> Maintain performance | R10: =_xlfn.RANK.EQ(K10,$K$2:$K$11,0) -> 9 | S10: =_xlfn.RANK.EQ(I10,$I$2:$I$11,0) -> 9 | T10: =_xlfn.RANK.EQ(J10,$J$2:$J$11,0)+_xlfn.RANK.EQ(K10,$K$2:$K$11,0) -> 18 | U10: =_xlfn.RANK.EQ(J10,$J$2:$J$11,0)+_xlfn.RANK.EQ(K10,$K$2:$K$11,0) -> 18
A11: WI-MF-10 | B11: =_xlfn.XLOOKUP(A11,'01_input_asset_master'!A$2:A$11,'01_input_asset_master'!B$2:B$11) -> Harbor Point Apartments | C11: =_xlfn.XLOOKUP(A11,'01_input_asset_master'!A$2:A$11,'01_input_asset_master'!H$2:H$11) -> 160000 | D11: =_xlfn.XLOOKUP(A11,'01_input_asset_master'!A$2:A$11,'01_input_asset_master'!I$2:I$11) -> 175 | E11: =SUMIFS('03_input_water_monthly'!G:G,'03_input_water_monthly'!A:A,A11) -> 53206.6 | F11: =SUMIFS('03_input_water_monthly'!H:H,'03_input_water_monthly'!A:A,A11) -> 64608.01 | G11: =SUMIFS('03_input_water_monthly'!H:H,'03_input_water_monthly'!A:A,A11) -> 64608.01 | H11: =F11+G11 -> 129216.02 | I11: =E11/C11 -> 0.33254125 | J11: =E11/D11 -> 304.03771 | K11: =H11/D11 -> 738.37726 | L11: =H11/C11 -> 0.80760012 | M11: =COUNTIFS('03_input_water_monthly'!A:A,A11,'03_input_water_monthly'!E:E,">0") -> 12 | N11: =M11/12 -> 1 | O11: =IF(J11>75000,"High Water Use",IF(J11>55000,"Moderate","Efficient/Low")) -> Efficient/Low | P11: =IF(K11>700,"High Cost",IF(K11>500,"Moderate Cost","Low Cost")) -> High Cost | Q11: =IF(O11="High Water Use","Leak detection + low-flow fixtures + irrigation review",IF(O11="Moderate","Monitor usage + fixture review","Maintain performance")) -> Maintain performance | R11: =_xlfn.RANK.EQ(K11,$K$2:$K$11,0) -> 3 | S11: =_xlfn.RANK.EQ(I11,$I$2:$I$11,0) -> 3 | T11: =_xlfn.RANK.EQ(J11,$J$2:$J$11,0)+_xlfn.RANK.EQ(K11,$K$2:$K$11,0) -> 6 | U11: =_xlfn.RANK.EQ(J11,$J$2:$J$11,0)+_xlfn.RANK.EQ(K11,$K$2:$K$11,0) -> 6
G20: =SUM('03_input_water_monthly'!D:D) -> 0

Sheet 04_input_waste_monthly
A1: property_id | B1: property_name | C1: city | D1: month | E1: landfill_tons | F1: recycling_tons | G1: compost_tons | H1: waste_cost_usd | I1: vendor | J1: data_quality | K1: source_note | L1: county | M1: state
A2: WI-MF-01 | B2: Riverbend Apartments | C2: Madison | D2: 2025-01 | E2: 9.45 | F2: 2.57 | G2: 0.26 | H2: 2167 | I2: Waste Management | J2: Actual | K2: Simulated property-level waste stream; structure aligns with ENERGY STAR Portfolio Manager waste tracking and EPA WARM materials-management categories. | L2: Dane | M2: WI
A3: WI-MF-01 | B3: Riverbend Apartments | C3: Madison | D3: 2025-02 | E3: 8.72 | F3: 2.23 | G3: 0.15 | H3: 1789 | I3: Waste Management | J3: Actual | K3: Simulated property-level waste stream; structure aligns with ENERGY STAR Portfolio Manager waste tracking and EPA WARM materials-management categories. | L3: Dane | M3: WI
A4: WI-MF-01 | B4: Riverbend Apartments | C4: Madison | D4: 2025-03 | E4: 9.44 | F4: 2.1 | G4: 0.18 | H4: 2008 | I4: Waste Management | J4: Actual | K4: Simulated property-level waste stream; structure aligns with ENERGY STAR Portfolio Manager waste tracking and EPA WARM materials-management categories. | L4: Dane | M4: WI
A5: WI-MF-01 | B5: Riverbend Apartments | C5: Madison | D5: 2025-04 | E5: 9.55 | F5: 2.22 | G5: 0.24 | H5: 2099 | I5: Waste Management | J5: Actual | K5: Simulated property-level waste stream; structure aligns with ENERGY STAR Portfolio Manager waste tracking and EPA WARM materials-management categories. | L5: Dane | M5: WI
A6: WI-MF-01 | B6: Riverbend Apartments | C6: Madison | D6: 2025-05 | E6: 9.33 | F6: 2.59 | G6: 0.26 | H6: 1964 | I6: Waste Management | J6: Actual | K6: Simulated property-level waste stream; structure aligns with ENERGY STAR Portfolio Manager waste tracking and EPA WARM materials-management categories. | L6: Dane | M6: WI
A7: WI-MF-01 | B7: Riverbend Apartments | C7: Madison | D7: 2025-06 | E7: 9.88 | F7: 2.92 | G7: 0.22 | H7: 1982 | I7: Waste Management | J7: Actual | K7: Simulated property-level waste stream; structure aligns with ENERGY STAR Portfolio Manager waste tracking and EPA WARM materials-management categories. | L7: Dane | M7: WI
A8: WI-MF-01 | B8: Riverbend Apartments | C8: Madison | D8: 2025-07 | E8: 9.55 | F8: 2.7 | G8: 0.25 | H8: 2168 | I8: Waste Management | J8: Actual | K8: Simulated property-level waste stream; structure aligns with ENERGY STAR Portfolio Manager waste tracking and EPA WARM materials-management categories. | L8: Dane | M8: WI
A9: WI-MF-01 | B9: Riverbend Apartments | C9: Madison | D9: 2025-08 | E9: 10.07 | F9: 2.53 | G9: 0.32 | H9: 2071 | I9: Waste Management | J9: Actual | K9: Simulated property-level waste stream; structure aligns with ENERGY STAR Portfolio Manager waste tracking and EPA WARM materials-management categories. | L9: Dane | M9: WI
A10: WI-MF-01 | B10: Riverbend Apartments | C10: Madison | D10: 2025-09 | E10: 9.37 | F10: 2.63 | G10: 0.25 | H10: 2152 | I10: Waste Management | J10: Actual | K10: Simulated property-level waste stream; structure aligns with ENERGY STAR Portfolio Manager waste tracking and EPA WARM materials-management categories. | L10: Dane | M10: WI
A11: WI-MF-01 | B11: Riverbend Apartments | C11: Madison | D11: 2025-10 | E11: 9.28 | F11: 2.59 | G11: 0.17 | H11: 1907 | I11: Waste Management | J11: Actual | K11: Simulated property-level waste stream; structure aligns with ENERGY STAR Portfolio Manager waste tracking and EPA WARM materials-management categories. | L11: Dane | M11: WI
A12: WI-MF-01 | B12: Riverbend Apartments | C12: Madison | D12: 2025-11 | E12: 9.81 | F12: 2.22 | G12: 0.2 | H12: 1888 | I12: Waste Management | J12: Actual | K12: Simulated property-level waste stream; structure aligns with ENERGY STAR Portfolio Manager waste tracking and EPA WARM materials-management categories. | L12: Dane | M12: WI
A13: WI-MF-01 | B13: Riverbend Apartments | C13: Madison | D13: 2025-12 | E13: 10.19 | F13: 2.74 | G13: 0.23 | H13: 2100 | I13: Waste Management | J13: Actual | K13: Simulated property-level waste stream; structure aligns with ENERGY STAR Portfolio Manager waste tracking and EPA WARM materials-management categories. | L13: Dane | M13: WI
... A121: WI-MF-10 | B121: Harbor Point Apartments | C121: Kenosha | D121: 2025-12 | E121: 10.32 | F121: 2.47 | G121: 0 | H121: 2114 | I121: Waste Management | J121: Estimated | K121: Simulated property-level waste stream; structure aligns with ENERGY STAR Portfolio Manager waste tracking and EPA WARM materials-management categories. | L121: Kenosha | M121: WI

Sheet 13_calc_waste_summary
A1: property_id | B1: property_name | C1: gross_floor_area_sqft | D1: units | E1: annual_landfill_tons | F1: annual_recycling_tons | G1: annual_compost_tons | H1: annual_total_waste_tons | I1: annual_waste_cost_usd | J1: diverted_waste_tons | K1: waste_diversion_rate | L1: waste_per_unit_tons | M1: waste_per_1000_sqft_tons | N1: waste_cost_per_unit | O1: waste_cost_per_sqft | P1: months_with_waste_data | Q1: waste_data_coverage_pct | R1: waste_performance_flag | S1: diversion_performance_flag | T1: recommended_waste_action | U1: waste_priority_rank | V1: diversion_priority_rank
A2: WI-MF-01 | B2: =_xlfn.XLOOKUP(A2,'01_input_asset_master'!A$2:A$11,'01_input_asset_master'!B$2:B$11) -> Riverbend Apartments | C2: =_xlfn.XLOOKUP(A2,'01_input_asset_master'!A$2:A$11,'01_input_asset_master'!H$2:H$11) -> 165000 | D2: =_xlfn.XLOOKUP(A2,'01_input_asset_master'!A$2:A$11,'01_input_asset_master'!I$2:I$11) -> 180 | E2: =SUMIFS(INDEX('04_input_waste_monthly'!$A:$Z,0,MATCH("landfill_tons",'04_input_waste_monthly'!$1:$1,0)),'04_input_waste_monthly'!$A:$A,A2) -> 114.64 | F2: =SUMIFS(INDEX('04_input_waste_monthly'!$A:$Z,0,MATCH("recycling_tons",'04_input_waste_monthly'!$1:$1,0)),'04_input_waste_monthly'!$A:$A,A2) -> 30.04 | G2: =SUMIFS(INDEX('04_input_waste_monthly'!$A:$Z,0,MATCH("compost_tons",'04_input_waste_monthly'!$1:$1,0)),'04_input_waste_monthly'!$A:$A,A2) -> 2.73 | H2: =E2+F2+G2 -> 147.41 | I2: =SUMIFS(INDEX('04_input_waste_monthly'!$A:$Z,0,MATCH("waste_cost_usd",'04_input_waste_monthly'!$1:$1,0)),'04_input_waste_monthly'!$A:$A,A2) -> 24295 | J2: =F2+G2 -> 32.77 | K2: =IF(H2=0,0,J2/H2) -> 0.22230514 | L2: =H2/D2 -> 0.81894444 | M2: =H2/(C2/1000) -> 0.89339394 | N2: =I2/D2 -> 134.97222 | O2: =I2/C2 -> 0.14724242 | P2: =COUNTIFS('04_input_waste_monthly'!$A:$A,A2,INDEX('04_input_waste_monthly'!$A:$Z,0,MATCH("landfill_tons",'04_input_waste_monthly'!$1:$1,0)),">0") -> 12 | Q2: =P2/12 -> 1 | R2: =IF(L2>0.8,"High Waste",IF(L2>0.5,"Moderate","Low")) -> High Waste | S2: =IF(K2>=0.5,"Strong Diversion",IF(K2>=0.3,"Moderate Diversion","Weak Diversion")) -> Weak Diversion | T2: =IF(AND(R2="High Waste",S2="Weak Diversion"),"Waste audit + recycling access + tenant education + vendor review",IF(S2="Weak Diversion","Improve recycling access + tenant education + vendor review",IF(R2="High Waste","Waste audit + contamination review + right-size bins","Maintain program + monitor diversion"))) -> Waste audit + recycling access + tenant education + vendor review | U2: =_xlfn.RANK.EQ(L2,$L$2:$L$11,0) -> 6 | V2: =_xlfn.RANK.EQ(K2,$K$2:$K$11,1) -> 5
A3: WI-MF-02 | B3: =_xlfn.XLOOKUP(A3,'01_input_asset_master'!A$2:A$11,'01_input_asset_master'!B$2:B$11) -> Lakeview Terrace | C3: =_xlfn.XLOOKUP(A3,'01_input_asset_master'!A$2:A$11,'01_input_asset_master'!H$2:H$11) -> 220000 | D3: =_xlfn.XLOOKUP(A3,'01_input_asset_master'!A$2:A$11,'01_input_asset_master'!I$2:I$11) -> 240 | E3: =SUMIFS(INDEX('04_input_waste_monthly'!$A:$Z,0,MATCH("landfill_tons",'04_input_waste_monthly'!$1:$1,0)),'04_input_waste_monthly'!$A:$A,A3) -> 163.27 | F3: =SUMIFS(INDEX('04_input_waste_monthly'!$A:$Z,0,MATCH("recycling_tons",'04_input_waste_monthly'!$1:$1,0)),'04_input_waste_monthly'!$A:$A,A3) -> 30.64 | G3: =SUMIFS(INDEX('04_input_waste_monthly'!$A:$Z,0,MATCH("compost_tons",'04_input_waste_monthly'!$1:$1,0)),'04_input_waste_monthly'!$A:$A,A3) -> 6.04 | H3: =E3+F3+G3 -> 199.95 | I3: =SUMIFS(INDEX('04_input_waste_monthly'!$A:$Z,0,MATCH("waste_cost_usd",'04_input_waste_monthly'!$1:$1,0)),'04_input_waste_monthly'!$A:$A,A3) -> 32107 | J3: =F3+G3 -> 36.68 | K3: =IF(H3=0,0,J3/H3) -> 0.18344586 | L3: =H3/D3 -> 0.833125 | M3: =H3/(C3/1000) -> 0.90886364 | N3: =I3/D3 -> 133.77917 | O3: =I3/C3 -> 0.14594091 | P3: =COUNTIFS('04_input_waste_monthly'!$A:$A,A3,INDEX('04_input_waste_monthly'!$A:$Z,0,MATCH("landfill_tons",'04_input_waste_monthly'!$1:$1,0)),">0") -> 12 | Q3: =P3/12 -> 1 | R3: =IF(L3>0.8,"High Waste",IF(L3>0.5,"Moderate","Low")) -> High Waste | S3: =IF(K3>=0.5,"Strong Diversion",IF(K3>=0.3,"Moderate Diversion","Weak Diversion")) -> Weak Diversion | T3: =IF(AND(R3="High Waste",S3="Weak Diversion"),"Waste audit + recycling access + tenant education + vendor review",IF(S3="Weak Diversion","Improve recycling access + tenant education + vendor review",IF(R3="High Waste","Waste audit + contamination review + right-size bins","Maintain program + monitor diversion"))) -> Waste audit + recycling access + tenant education + vendor review | U3: =_xlfn.RANK.EQ(L3,$L$2:$L$11,0) -> 3 | V3: =_xlfn.RANK.EQ(K3,$K$2:$K$11,1) -> 1
A4: WI-MF-03 | B4: =_xlfn.XLOOKUP(A4,'01_input_asset_master'!A$2:A$11,'01_input_asset_master'!B$2:B$11) -> Northside Commons | C4: =_xlfn.XLOOKUP(A4,'01_input_asset_master'!A$2:A$11,'01_input_asset_master'!H$2:H$11) -> 145000 | D4: =_xlfn.XLOOKUP(A4,'01_input_asset_master'!A$2:A$11,'01_input_asset_master'!I$2:I$11) -> 160 | E4: =SUMIFS(INDEX('04_input_waste_monthly'!$A:$Z,0,MATCH("landfill_tons",'04_input_waste_monthly'!$1:$1,0)),'04_input_waste_monthly'!$A:$A,A4) -> 95.26 | F4: =SUMIFS(INDEX('04_input_waste_monthly'!$A:$Z,0,MATCH("recycling_tons",'04_input_waste_monthly'!$1:$1,0)),'04_input_waste_monthly'!$A:$A,A4) -> 35.34 | G4: =SUMIFS(INDEX('04_input_waste_monthly'!$A:$Z,0,MATCH("compost_tons",'04_input_waste_monthly'!$1:$1,0)),'04_input_waste_monthly'!$A:$A,A4) -> 0 | H4: =E4+F4+G4 -> 130.6 | I4: =SUMIFS(INDEX('04_input_waste_monthly'!$A:$Z,0,MATCH("waste_cost_usd",'04_input_waste_monthly'!$1:$1,0)),'04_input_waste_monthly'!$A:$A,A4) -> 21834 | J4: =F4+G4 -> 35.34 | K4: =IF(H4=0,0,J4/H4) -> 0.27059724 | L4: =H4/D4 -> 0.81625 | M4: =H4/(C4/1000) -> 0.90068966 | N4: =I4/D4 -> 136.4625 | O4: =I4/C4 -> 0.15057931 | P4: =COUNTIFS('04_input_waste_monthly'!$A:$A,A4,INDEX('04_input_waste_monthly'!$A:$Z,0,MATCH("landfill_tons",'04_input_waste_monthly'!$1:$1,0)),">0") -> 12 | Q4: =P4/12 -> 1 | R4: =IF(L4>0.8,"High Waste",IF(L4>0.5,"Moderate","Low")) -> High Waste | S4: =IF(K4>=0.5,"Strong Diversion",IF(K4>=0.3,"Moderate Diversion","Weak Diversion")) -> Weak Diversion | T4: =IF(AND(R4="High Waste",S4="Weak Diversion"),"Waste audit + recycling access + tenant education + vendor review",IF(S4="Weak Diversion","Improve recycling access + tenant education + vendor review",IF(R4="High Waste","Waste audit + contamination review + right-size bins","Maintain program + monitor diversion"))) -> Waste audit + recycling access + tenant education + vendor review | U4: =_xlfn.RANK.EQ(L4,$L$2:$L$11,0) -> 7 | V4: =_xlfn.RANK.EQ(K4,$K$2:$K$11,1) -> 8 | X4: Waste analysis shows that the portfolio has complete waste data coverage, with 12 months of data available for each property. However, most properties show high waste generation per unit and weak diversion performance. South Park Apartments, Badger Ridge Homes, Lakeview Terrace, Capitol Square Homes, and Oak Street Lofts have the highest waste per unit and should be prioritized for waste audits. Diversion performance is especially weak at Lakeview Terrace, Harbor Point Apartments, South Park Apartments, Badger Ridge Homes, and Riverbend Apartments, suggesting a need for improved recycling access, tenant education, contamination review, and vendor coordination.
A5: WI-MF-04 | B5: =_xlfn.XLOOKUP(A5,'01_input_asset_master'!A$2:A$11,'01_input_asset_master'!B$2:B$11) -> Badger Ridge Homes | C5: =_xlfn.XLOOKUP(A5,'01_input_asset_master'!A$2:A$11,'01_input_asset_master'!H$2:H$11) -> 120000 | D5: =_xlfn.XLOOKUP(A5,'01_input_asset_master'!A$2:A$11,'01_input_asset_master'!I$2:I$11) -> 130 | E5: =SUMIFS(INDEX('04_input_waste_monthly'!$A:$Z,0,MATCH("landfill_tons",'04_input_waste_monthly'!$1:$1,0)),'04_input_waste_monthly'!$A:$A,A5) -> 85.29 | F5: =SUMIFS(INDEX('04_input_waste_monthly'!$A:$Z,0,MATCH("recycling_tons",'04_input_waste_monthly'!$1:$1,0)),'04_input_waste_monthly'!$A:$A,A5) -> 23.91 | G5: =SUMIFS(INDEX('04_input_waste_monthly'!$A:$Z,0,MATCH("compost_tons",'04_input_waste_monthly'!$1:$1,0)),'04_input_waste_monthly'!$A:$A,A5) -> 0 | H5: =E5+F5+G5 -> 109.2 | I5: =SUMIFS(INDEX('04_input_waste_monthly'!$A:$Z,0,MATCH("waste_cost_usd",'04_input_waste_monthly'!$1:$1,0)),'04_input_waste_monthly'!$A:$A,A5) -> 18459 | J5: =F5+G5 -> 23.91 | K5: =IF(H5=0,0,J5/H5) -> 0.21895604 | L5: =H5/D5 -> 0.84 | M5: =H5/(C5/1000) -> 0.91 | N5: =I5/D5 -> 141.99231 | O5: =I5/C5 -> 0.153825 | P5: =COUNTIFS('04_input_waste_monthly'!$A:$A,A5,INDEX('04_input_waste_monthly'!$A:$Z,0,MATCH("landfill_tons",'04_input_waste_monthly'!$1:$1,0)),">0") -> 12 | Q5: =P5/12 -> 1 | R5: =IF(L5>0.8,"High Waste",IF(L5>0.5,"Moderate","Low")) -> High Waste | S5: =IF(K5>=0.5,"Strong Diversion",IF(K5>=0.3,"Moderate Diversion","Weak Diversion")) -> Weak Diversion | T5: =IF(AND(R5="High Waste",S5="Weak Diversion"),"Waste audit + recycling access + tenant education + vendor review",IF(S5="Weak Diversion","Improve recycling access + tenant education + vendor review",IF(R5="High Waste","Waste audit + contamination review + right-size bins","Maintain program + monitor diversion"))) -> Waste audit + recycling access + tenant education + vendor review | U5: =_xlfn.RANK.EQ(L5,$L$2:$L$11,0) -> 2 | V5: =_xlfn.RANK.EQ(K5,$K$2:$K$11,1) -> 4
A6: WI-MF-05 | B6: =_xlfn.XLOOKUP(A6,'01_input_asset_master'!A$2:A$11,'01_input_asset_master'!B$2:B$11) -> Oak Street Lofts | C6: =_xlfn.XLOOKUP(A6,'01_input_asset_master'!A$2:A$11,'01_input_asset_master'!H$2:H$11) -> 98000 | D6: =_xlfn.XLOOKUP(A6,'01_input_asset_master'!A$2:A$11,'01_input_asset_master'!I$2:I$11) -> 105 | E6: =SUMIFS(INDEX('04_input_waste_monthly'!$A:$Z,0,MATCH("landfill_tons",'04_input_waste_monthly'!$1:$1,0)),'04_input_waste_monthly'!$A:$A,A6) -> 62.72 | F6: =SUMIFS(INDEX('04_input_waste_monthly'!$A:$Z,0,MATCH("recycling_tons",'04_input_waste_monthly'!$1:$1,0)),'04_input_waste_monthly'!$A:$A,A6) -> 22.15 | G6: =SUMIFS(INDEX('04_input_waste_monthly'!$A:$Z,0,MATCH("compost_tons",'04_input_waste_monthly'!$1:$1,0)),'04_input_waste_monthly'!$A:$A,A6) -> 2.01 | H6: =E6+F6+G6 -> 86.88 | I6: =SUMIFS(INDEX('04_input_waste_monthly'!$A:$Z,0,MATCH("waste_cost_usd",'04_input_waste_monthly'!$1:$1,0)),'04_input_waste_monthly'!$A:$A,A6) -> 14911 | J6: =F6+G6 -> 24.16 | K6: =IF(H6=0,0,J6/H6) -> 0.27808471 | L6: =H6/D6 -> 0.82742857 | M6: =H6/(C6/1000) -> 0.88653061 | N6: =I6/D6 -> 142.00952 | O6: =I6/C6 -> 0.15215306 | P6: =COUNTIFS('04_input_waste_monthly'!$A:$A,A6,INDEX('04_input_waste_monthly'!$A:$Z,0,MATCH("landfill_tons",'04_input_waste_monthly'!$1:$1,0)),">0") -> 12 | Q6: =P6/12 -> 1 | R6: =IF(L6>0.8,"High Waste",IF(L6>0.5,"Moderate","Low")) -> High Waste | S6: =IF(K6>=0.5,"Strong Diversion",IF(K6>=0.3,"Moderate Diversion","Weak Diversion")) -> Weak Diversion | T6: =IF(AND(R6="High Waste",S6="Weak Diversion"),"Waste audit + recycling access + tenant education + vendor review",IF(S6="Weak Diversion","Improve recycling access + tenant education + vendor review",IF(R6="High Waste","Waste audit + contamination review + right-size bins","Maintain program + monitor diversion"))) -> Waste audit + recycling access + tenant education + vendor review | U6: =_xlfn.RANK.EQ(L6,$L$2:$L$11,0) -> 5 | V6: =_xlfn.RANK.EQ(K6,$K$2:$K$11,1) -> 9
A7: WI-MF-06 | B7: =_xlfn.XLOOKUP(A7,'01_input_asset_master'!A$2:A$11,'01_input_asset_master'!B$2:B$11) -> South Park Apartments | C7: =_xlfn.XLOOKUP(A7,'01_input_asset_master'!A$2:A$11,'01_input_asset_master'!H$2:H$11) -> 185000 | D7: =_xlfn.XLOOKUP(A7,'01_input_asset_master'!A$2:A$11,'01_input_asset_master'!I$2:I$11) -> 210 | E7: =SUMIFS(INDEX('04_input_waste_monthly'!$A:$Z,0,MATCH("landfill_tons",'04_input_waste_monthly'!$1:$1,0)),'04_input_waste_monthly'!$A:$A,A7) -> 141.36 | F7: =SUMIFS(INDEX('04_input_waste_monthly'!$A:$Z,0,MATCH("recycling_tons",'04_input_waste_monthly'!$1:$1,0)),'04_input_waste_monthly'!$A:$A,A7) -> 37.73 | G7: =SUMIFS(INDEX('04_input_waste_monthly'!$A:$Z,0,MATCH("compost_tons",'04_input_waste_monthly'!$1:$1,0)),'04_input_waste_monthly'!$A:$A,A7) -> 0 | H7: =E7+F7+G7 -> 179.09 | I7: =SUMIFS(INDEX('04_input_waste_monthly'!$A:$Z,0,MATCH("waste_cost_usd",'04_input_waste_monthly'!$1:$1,0)),'04_input_waste_monthly'!$A:$A,A7) -> 28952 | J7: =F7+G7 -> 37.73 | K7: =IF(H7=0,0,J7/H7) -> 0.2106762 | L7: =H7/D7 -> 0.85280952 | M7: =H7/(C7/1000) -> 0.96805405 | N7: =I7/D7 -> 137.86667 | O7: =I7/C7 -> 0.1564973 | P7: =COUNTIFS('04_input_waste_monthly'!$A:$A,A7,INDEX('04_input_waste_monthly'!$A:$Z,0,MATCH("landfill_tons",'04_input_waste_monthly'!$1:$1,0)),">0") -> 12 | Q7: =P7/12 -> 1 | R7: =IF(L7>0.8,"High Waste",IF(L7>0.5,"Moderate","Low")) -> High Waste | S7: =IF(K7>=0.5,"Strong Diversion",IF(K7>=0.3,"Moderate Diversion","Weak Diversion")) -> Weak Diversion | T7: =IF(AND(R7="High Waste",S7="Weak Diversion"),"Waste audit + recycling access + tenant education + vendor review",IF(S7="Weak Diversion","Improve recycling access + tenant education + vendor review",IF(R7="High Waste","Waste audit + contamination review + right-size bins","Maintain program + monitor diversion"))) -> Waste audit + recycling access + tenant education + vendor review | U7: =_xlfn.RANK.EQ(L7,$L$2:$L$11,0) -> 1 | V7: =_xlfn.RANK.EQ(K7,$K$2:$K$11,1) -> 3
A8: WI-MF-07 | B8: =_xlfn.XLOOKUP(A8,'01_input_asset_master'!A$2:A$11,'01_input_asset_master'!B$2:B$11) -> Fox River Flats | C8: =_xlfn.XLOOKUP(A8,'01_input_asset_master'!A$2:A$11,'01_input_asset_master'!H$2:H$11) -> 135000 | D8: =_xlfn.XLOOKUP(A8,'01_input_asset_master'!A$2:A$11,'01_input_asset_master'!I$2:I$11) -> 150 | E8: =SUMIFS(INDEX('04_input_waste_monthly'!$A:$Z,0,MATCH("landfill_tons",'04_input_waste_monthly'!$1:$1,0)),'04_input_waste_monthly'!$A:$A,A8) -> 87.67 | F8: =SUMIFS(INDEX('04_input_waste_monthly'!$A:$Z,0,MATCH("recycling_tons",'04_input_waste_monthly'!$1:$1,0)),'04_input_waste_monthly'!$A:$A,A8) -> 31.75 | G8: =SUMIFS(INDEX('04_input_waste_monthly'!$A:$Z,0,MATCH("compost_tons",'04_input_waste_monthly'!$1:$1,0)),'04_input_waste_monthly'!$A:$A,A8) -> 0 | H8: =E8+F8+G8 -> 119.42 | I8: =SUMIFS(INDEX('04_input_waste_monthly'!$A:$Z,0,MATCH("waste_cost_usd",'04_input_waste_monthly'!$1:$1,0)),'04_input_waste_monthly'!$A:$A,A8) -> 20402 | J8: =F8+G8 -> 31.75 | K8: =IF(H8=0,0,J8/H8) -> 0.26586836 | L8: =H8/D8 -> 0.79613333 | M8: =H8/(C8/1000) -> 0.88459259 | N8: =I8/D8 -> 136.01333 | O8: =I8/C8 -> 0.15112593 | P8: =COUNTIFS('04_input_waste_monthly'!$A:$A,A8,INDEX('04_input_waste_monthly'!$A:$Z,0,MATCH("landfill_tons",'04_input_waste_monthly'!$1:$1,0)),">0") -> 12 | Q8: =P8/12 -> 1 | R8: =IF(L8>0.8,"High Waste",IF(L8>0.5,"Moderate","Low")) -> Moderate | S8: =IF(K8>=0.5,"Strong Diversion",IF(K8>=0.3,"Moderate Diversion","Weak Diversion")) -> Weak Diversion | T8: =IF(AND(R8="High Waste",S8="Weak Diversion"),"Waste audit + recycling access + tenant education + vendor review",IF(S8="Weak Diversion","Improve recycling access + tenant education + vendor review",IF(R8="High Waste","Waste audit + contamination review + right-size bins","Maintain program + monitor diversion"))) -> Improve recycling access + tenant education + vendor review | U8: =_xlfn.RANK.EQ(L8,$L$2:$L$11,0) -> 9 | V8: =_xlfn.RANK.EQ(K8,$K$2:$K$11,1) -> 6
A9: WI-MF-08 | B9: =_xlfn.XLOOKUP(A9,'01_input_asset_master'!A$2:A$11,'01_input_asset_master'!B$2:B$11) -> Prairie View Residences | C9: =_xlfn.XLOOKUP(A9,'01_input_asset_master'!A$2:A$11,'01_input_asset_master'!H$2:H$11) -> 110000 | D9: =_xlfn.XLOOKUP(A9,'01_input_asset_master'!A$2:A$11,'01_input_asset_master'!I$2:I$11) -> 120 | E9: =SUMIFS(INDEX('04_input_waste_monthly'!$A:$Z,0,MATCH("landfill_tons",'04_input_waste_monthly'!$1:$1,0)),'04_input_waste_monthly'!$A:$A,A9) -> 67.62 | F9: =SUMIFS(INDEX('04_input_waste_monthly'!$A:$Z,0,MATCH("recycling_tons",'04_input_waste_monthly'!$1:$1,0)),'04_input_waste_monthly'!$A:$A,A9) -> 24.9 | G9: =SUMIFS(INDEX('04_input_waste_monthly'!$A:$Z,0,MATCH("compost_tons",'04_input_waste_monthly'!$1:$1,0)),'04_input_waste_monthly'!$A:$A,A9) -> 0 | H9: =E9+F9+G9 -> 92.52 | I9: =SUMIFS(INDEX('04_input_waste_monthly'!$A:$Z,0,MATCH("waste_cost_usd",'04_input_waste_monthly'!$1:$1,0)),'04_input_waste_monthly'!$A:$A,A9) -> 15752 | J9: =F9+G9 -> 24.9 | K9: =IF(H9=0,0,J9/H9) -> 0.269131 | L9: =H9/D9 -> 0.771 | M9: =H9/(C9/1000) -> 0.84109091 | N9: =I9/D9 -> 131.26667 | O9: =I9/C9 -> 0.1432 | P9: =COUNTIFS('04_input_waste_monthly'!$A:$A,A9,INDEX('04_input_waste_monthly'!$A:$Z,0,MATCH("landfill_tons",'04_input_waste_monthly'!$1:$1,0)),">0") -> 12 | Q9: =P9/12 -> 1 | R9: =IF(L9>0.8,"High Waste",IF(L9>0.5,"Moderate","Low")) -> Moderate | S9: =IF(K9>=0.5,"Strong Diversion",IF(K9>=0.3,"Moderate Diversion","Weak Diversion")) -> Weak Diversion | T9: =IF(AND(R9="High Waste",S9="Weak Diversion"),"Waste audit + recycling access + tenant education + vendor review",IF(S9="Weak Diversion","Improve recycling access + tenant education + vendor review",IF(R9="High Waste","Waste audit + contamination review + right-size bins","Maintain program + monitor diversion"))) -> Improve recycling access + tenant education + vendor review | U9: =_xlfn.RANK.EQ(L9,$L$2:$L$11,0) -> 10 | V9: =_xlfn.RANK.EQ(K9,$K$2:$K$11,1) -> 7
A10: WI-MF-09 | B10: =_xlfn.XLOOKUP(A10,'01_input_asset_master'!A$2:A$11,'01_input_asset_master'!B$2:B$11) -> Capitol Square Homes | C10: =_xlfn.XLOOKUP(A10,'01_input_asset_master'!A$2:A$11,'01_input_asset_master'!H$2:H$11) -> 175000 | D10: =_xlfn.XLOOKUP(A10,'01_input_asset_master'!A$2:A$11,'01_input_asset_master'!I$2:I$11) -> 190 | E10: =SUMIFS(INDEX('04_input_waste_monthly'!$A:$Z,0,MATCH("landfill_tons",'04_input_waste_monthly'!$1:$1,0)),'04_input_waste_monthly'!$A:$A,A10) -> 105.34 | F10: =SUMIFS(INDEX('04_input_waste_monthly'!$A:$Z,0,MATCH("recycling_tons",'04_input_waste_monthly'!$1:$1,0)),'04_input_waste_monthly'!$A:$A,A10) -> 49.69 | G10: =SUMIFS(INDEX('04_input_waste_monthly'!$A:$Z,0,MATCH("compost_tons",'04_input_waste_monthly'!$1:$1,0)),'04_input_waste_monthly'!$A:$A,A10) -> 2.85 | H10: =E10+F10+G10 -> 157.88 | I10: =SUMIFS(INDEX('04_input_waste_monthly'!$A:$Z,0,MATCH("waste_cost_usd",'04_input_waste_monthly'!$1:$1,0)),'04_input_waste_monthly'!$A:$A,A10) -> 26278 | J10: =F10+G10 -> 52.54 | K10: =IF(H10=0,0,J10/H10) -> 0.33278439 | L10: =H10/D10 -> 0.83094737 | M10: =H10/(C10/1000) -> 0.90217143 | N10: =I10/D10 -> 138.30526 | O10: =I10/C10 -> 0.15016 | P10: =COUNTIFS('04_input_waste_monthly'!$A:$A,A10,INDEX('04_input_waste_monthly'!$A:$Z,0,MATCH("landfill_tons",'04_input_waste_monthly'!$1:$1,0)),">0") -> 12 | Q10: =P10/12 -> 1 | R10: =IF(L10>0.8,"High Waste",IF(L10>0.5,"Moderate","Low")) -> High Waste | S10: =IF(K10>=0.5,"Strong Diversion",IF(K10>=0.3,"Moderate Diversion","Weak Diversion")) -> Moderate Diversion | T10: =IF(AND(R10="High Waste",S10="Weak Diversion"),"Waste audit + recycling access + tenant education + vendor review",IF(S10="Weak Diversion","Improve recycling access + tenant education + vendor review",IF(R10="High Waste","Waste audit + contamination review + right-size bins","Maintain program + monitor diversion"))) -> Waste audit + contamination review + right-size bins | U10: =_xlfn.RANK.EQ(L10,$L$2:$L$11,0) -> 4 | V10: =_xlfn.RANK.EQ(K10,$K$2:$K$11,1) -> 10
A11: WI-MF-10 | B11: =_xlfn.XLOOKUP(A11,'01_input_asset_master'!A$2:A$11,'01_input_asset_master'!B$2:B$11) -> Harbor Point Apartments | C11: =_xlfn.XLOOKUP(A11,'01_input_asset_master'!A$2:A$11,'01_input_asset_master'!H$2:H$11) -> 160000 | D11: =_xlfn.XLOOKUP(A11,'01_input_asset_master'!A$2:A$11,'01_input_asset_master'!I$2:I$11) -> 175 | E11: =SUMIFS(INDEX('04_input_waste_monthly'!$A:$Z,0,MATCH("landfill_tons",'04_input_waste_monthly'!$1:$1,0)),'04_input_waste_monthly'!$A:$A,A11) -> 112.2 | F11: =SUMIFS(INDEX('04_input_waste_monthly'!$A:$Z,0,MATCH("recycling_tons",'04_input_waste_monthly'!$1:$1,0)),'04_input_waste_monthly'!$A:$A,A11) -> 29.37 | G11: =SUMIFS(INDEX('04_input_waste_monthly'!$A:$Z,0,MATCH("compost_tons",'04_input_waste_monthly'!$1:$1,0)),'04_input_waste_monthly'!$A:$A,A11) -> 0 | H11: =E11+F11+G11 -> 141.57 | I11: =SUMIFS(INDEX('04_input_waste_monthly'!$A:$Z,0,MATCH("waste_cost_usd",'04_input_waste_monthly'!$1:$1,0)),'04_input_waste_monthly'!$A:$A,A11) -> 23732 | J11: =F11+G11 -> 29.37 | K11: =IF(H11=0,0,J11/H11) -> 0.20745921 | L11: =H11/D11 -> 0.80897143 | M11: =H11/(C11/1000) -> 0.8848125 | N11: =I11/D11 -> 135.61143 | O11: =I11/C11 -> 0.148325 | P11: =COUNTIFS('04_input_waste_monthly'!$A:$A,A11,INDEX('04_input_waste_monthly'!$A:$Z,0,MATCH("landfill_tons",'04_input_waste_monthly'!$1:$1,0)),">0") -> 12 | Q11: =P11/12 -> 1 | R11: =IF(L11>0.8,"High Waste",IF(L11>0.5,"Moderate","Low")) -> High Waste | S11: =IF(K11>=0.5,"Strong Diversion",IF(K11>=0.3,"Moderate Diversion","Weak Diversion")) -> Weak Diversion | T11: =IF(AND(R11="High Waste",S11="Weak Diversion"),"Waste audit + recycling access + tenant education + vendor review",IF(S11="Weak Diversion","Improve recycling access + tenant education + vendor review",IF(R11="High Waste","Waste audit + contamination review + right-size bins","Maintain program + monitor diversion"))) -> Waste audit + recycling access + tenant education + vendor review | U11: =_xlfn.RANK.EQ(L11,$L$2:$L$11,0) -> 8 | V11: =_xlfn.RANK.EQ(K11,$K$2:$K$11,1) -> 2

Sheet 05_input_emission_factors
A1: factor_id | B1: source_name | C1: source_year | D1: geography | E1: fuel_or_energy_type | F1: scope | G1: input_unit | H1: co2_factor | I1: ch4_factor | J1: n2o_factor | K1: co2e_factor | L1: co2e_unit | M1: conversion_notes | N1: source_url | O1: use_in_project | P1: quality_note
A2: EF-ELEC-WI-STATE | B2: EPA eGRID Summary Tables | C2: 2023 | D2: Wisconsin (state output emission rate) | E2: Purchased electricity | F2: Scope 2 location-based | G2: kWh | H2: 1157.0 | I2: 0.1 | J2: 0.014 | K2: 0.5278 | L2: kg CO2e/kWh | M2: Converted from 1,163.6 lb CO2e/MWh using 0.45359237 kg/lb and 1,000 kWh/MWh | N2: https://www.epa.gov/egrid/summary-data | O2: Default factor for all Wisconsin properties in this simulated portfolio | P2: Use state factor for simplicity; for real client, confirm exact eGRID subregion/utility territory
A3: EF-ELEC-MROW | B3: EPA eGRID Summary Tables | C3: 2023 | D3: MROW / MRO West eGRID subregion | E3: Purchased electricity | F3: Scope 2 location-based | G3: kWh | H3: 920.1 | I3: 0.097 | J3: 0.014 | K3: 0.420299 | L3: kg CO2e/kWh | M3: Converted from 926.6 lb CO2e/MWh | N3: https://www.epa.gov/egrid/summary-data | O3: Optional sensitivity factor for Wisconsin properties in MRO West territory | P3: Use only if property is in this eGRID subregion
A4: EF-ELEC-RFCW | B4: EPA eGRID Summary Tables | C4: 2023 | D4: RFCW / RFC West eGRID subregion | E4: Purchased electricity | F4: Scope 2 location-based | G4: kWh | H4: 911.4 | I4: 0.071 | J4: 0.01 | K4: 0.415536 | L4: kg CO2e/kWh | M4: Converted from 916.1 lb CO2e/MWh | N4: https://www.epa.gov/egrid/summary-data | O4: Optional sensitivity factor for Wisconsin properties in RFC West territory | P4: Use only if property is in this eGRID subregion
A5: EF-ELEC-US | B5: EPA eGRID Summary Tables | C5: 2023 | D5: United States average | E5: Purchased electricity | F5: Scope 2 location-based | G5: kWh | H5: 767.2 | I5: 0.057 | J5: 0.008 | K5: 0.349674 | L5: kg CO2e/kWh | M5: Converted from 770.9 lb CO2e/MWh | N5: https://www.epa.gov/egrid/summary-data | O5: Benchmark/sensitivity only; do not use as default for Wisconsin | P5: State/subregion factor is more defensible
A6: EF-NG-US-THERM | B6: EPA GHG Emission Factors Hub | C6: 2025 | D6: United States | E6: Natural gas stationary combustion | F6: Scope 1 | G6: therm | H6: 5.306 | I6: 0.0001 | J6: 1e-05 | K6: 5.31145 | L6: kg CO2e/therm | M6: 1 therm = 0.1 MMBtu. EPA factors: 53.06 kg CO2/MMBtu, 1.0 g CH4/MMBtu, 0.10 g N2O/MMBtu; GWP CH4=28, N2O=265 | N6: https://www.epa.gov/climateleadership/ghg-emission-factors-hub | O6: Default factor for natural gas used by multifamily buildings | P6: Combustion emissions only; does not include upstream gas leakage
A7: EF-STEAM-HEAT | B7: EPA GHG Emission Factors Hub | C7: 2025 | D7: United States | E7: Purchased steam/heat | F7: Scope 2 or Scope 3 depending accounting boundary | G7: MMBtu | H7: 66.33 | I7: 0.00125 | J7: 0.000125 | K7: 66.398125 | L7: kg CO2e/MMBtu | M7: EPA steam/heat factor assumes natural gas fuel at 80% thermal efficiency | N7: https://www.epa.gov/climateleadership/ghg-emission-factors-hub | O7: Use only if a property buys district steam/heat | P7: Not needed for your current 10-property data unless district energy exists

Sheet 14_calc_emissions_summary
A1: property_id | B1: property_name | C1: gross_floor_area_sqft | D1: units | E1: annual_electricity_kwh | F1: annual_natural_gas_therms | G1: electricity_emission_factor_kgco2e_kwh | H1: natural_gas_emission_factor_kgco2e_therm | I1: scope2_electricity_emissions_tco2e | J1: scope1_natural_gas_emissions_tco2e | K1: total_scope1_scope2_emissions_tco2e | L1: emissions_intensity_kgco2e_sqft | M1: emissions_per_unit_tco2e | N1: scope2_share_pct | O1: scope1_share_pct | P1: carbon_performance_flag | Q1: carbon_priority_rank | R1: recommended_carbon_action
A2: WI-MF-01 | B2: =_xlfn.XLOOKUP(A2,'01_input_asset_master'!A$2:A$11,'01_input_asset_master'!B$2:B$11) -> Riverbend Apartments | C2: =_xlfn.XLOOKUP(A2,'01_input_asset_master'!A$2:A$11,'01_input_asset_master'!H$2:H$11) -> 165000 | D2: =_xlfn.XLOOKUP(A2,'01_input_asset_master'!A$2:A$11,'01_input_asset_master'!I$2:I$11) -> 180 | E2: =_xlfn.XLOOKUP(A2,'11_calc_energy_summary'!A$2:A$11,'11_calc_energy_summary'!E$2:E$11) -> 1131188 | F2: =_xlfn.XLOOKUP(A2,'11_calc_energy_summary'!A$2:A$11,'11_calc_energy_summary'!F$2:F$11) -> 56939 | G2: =0.527779 -> 0.527779 | H2: =5.31145 -> 5.31145 | I2: =E2*G2/1000 -> 597.01727 | J2: =F2*H2/1000 -> 302.42865 | K2: =I2+J2 -> 899.44592 | L2: =K2*1000/C2 -> 5.4511874 | M2: =K2/D2 -> 4.9969218 | N2: =IF(K2=0,0,I2/K2) -> 0.66376116 | O2: =IF(K2=0,0,J2/K2) -> 0.33623884 | P2: =IF(L2>6,"High Carbon Intensity",IF(L2>5,"Moderate Carbon Intensity","Lower Carbon Intensity")) -> Moderate Carbon Intensity | Q2: =_xlfn.RANK.EQ(L2,$L$2:$L$11,0) -> 5 | R2: =IF(P2="High Carbon Intensity","Energy audit + electricity efficiency + gas/heating system review",IF(AND(P2="Moderate Carbon Intensity",O2>0.33),"Monitor + boiler/DHW controls review","Maintain + monitor emissions")) -> Monitor + boiler/DHW controls review
A3: WI-MF-02 | B3: =_xlfn.XLOOKUP(A3,'01_input_asset_master'!A$2:A$11,'01_input_asset_master'!B$2:B$11) -> Lakeview Terrace | C3: =_xlfn.XLOOKUP(A3,'01_input_asset_master'!A$2:A$11,'01_input_asset_master'!H$2:H$11) -> 220000 | D3: =_xlfn.XLOOKUP(A3,'01_input_asset_master'!A$2:A$11,'01_input_asset_master'!I$2:I$11) -> 240 | E3: =_xlfn.XLOOKUP(A3,'11_calc_energy_summary'!A$2:A$11,'11_calc_energy_summary'!E$2:E$11) -> 1622015 | F3: =_xlfn.XLOOKUP(A3,'11_calc_energy_summary'!A$2:A$11,'11_calc_energy_summary'!F$2:F$11) -> 90298 | G3: =0.527779 -> 0.527779 | H3: =5.31145 -> 5.31145 | I3: =E3*G3/1000 -> 856.06545 | J3: =F3*H3/1000 -> 479.61331 | K3: =I3+J3 -> 1335.6788 | L3: =K3*1000/C3 -> 6.0712671 | M3: =K3/D3 -> 5.5653282 | N3: =IF(K3=0,0,I3/K3) -> 0.64092166 | O3: =IF(K3=0,0,J3/K3) -> 0.35907834 | P3: =IF(L3>6,"High Carbon Intensity",IF(L3>5,"Moderate Carbon Intensity","Lower Carbon Intensity")) -> High Carbon Intensity | Q3: =_xlfn.RANK.EQ(L3,$L$2:$L$11,0) -> 2 | R3: =IF(P3="High Carbon Intensity","Energy audit + electricity efficiency + gas/heating system review",IF(AND(P3="Moderate Carbon Intensity",O3>0.33),"Monitor + boiler/DHW controls review","Maintain + monitor emissions")) -> Energy audit + electricity efficiency + gas/heating system review
A4: WI-MF-03 | B4: =_xlfn.XLOOKUP(A4,'01_input_asset_master'!A$2:A$11,'01_input_asset_master'!B$2:B$11) -> Northside Commons | C4: =_xlfn.XLOOKUP(A4,'01_input_asset_master'!A$2:A$11,'01_input_asset_master'!H$2:H$11) -> 145000 | D4: =_xlfn.XLOOKUP(A4,'01_input_asset_master'!A$2:A$11,'01_input_asset_master'!I$2:I$11) -> 160 | E4: =_xlfn.XLOOKUP(A4,'11_calc_energy_summary'!A$2:A$11,'11_calc_energy_summary'!E$2:E$11) -> 980726 | F4: =_xlfn.XLOOKUP(A4,'11_calc_energy_summary'!A$2:A$11,'11_calc_energy_summary'!F$2:F$11) -> 45270 | G4: =0.527779 -> 0.527779 | H4: =5.31145 -> 5.31145 | I4: =E4*G4/1000 -> 517.60659 | J4: =F4*H4/1000 -> 240.44934 | K4: =I4+J4 -> 758.05593 | L4: =K4*1000/C4 -> 5.2279719 | M4: =K4/D4 -> 4.7378496 | N4: =IF(K4=0,0,I4/K4) -> 0.68280791 | O4: =IF(K4=0,0,J4/K4) -> 0.31719209 | P4: =IF(L4>6,"High Carbon Intensity",IF(L4>5,"Moderate Carbon Intensity","Lower Carbon Intensity")) -> Moderate Carbon Intensity | Q4: =_xlfn.RANK.EQ(L4,$L$2:$L$11,0) -> 7 | R4: =IF(P4="High Carbon Intensity","Energy audit + electricity efficiency + gas/heating system review",IF(AND(P4="Moderate Carbon Intensity",O4>0.33),"Monitor + boiler/DHW controls review","Maintain + monitor emissions")) -> Maintain + monitor emissions
A5: WI-MF-04 | B5: =_xlfn.XLOOKUP(A5,'01_input_asset_master'!A$2:A$11,'01_input_asset_master'!B$2:B$11) -> Badger Ridge Homes | C5: =_xlfn.XLOOKUP(A5,'01_input_asset_master'!A$2:A$11,'01_input_asset_master'!H$2:H$11) -> 120000 | D5: =_xlfn.XLOOKUP(A5,'01_input_asset_master'!A$2:A$11,'01_input_asset_master'!I$2:I$11) -> 130 | E5: =_xlfn.XLOOKUP(A5,'11_calc_energy_summary'!A$2:A$11,'11_calc_energy_summary'!E$2:E$11) -> 837617 | F5: =_xlfn.XLOOKUP(A5,'11_calc_energy_summary'!A$2:A$11,'11_calc_energy_summary'!F$2:F$11) -> 45461 | G5: =0.527779 -> 0.527779 | H5: =5.31145 -> 5.31145 | I5: =E5*G5/1000 -> 442.07666 | J5: =F5*H5/1000 -> 241.46383 | K5: =I5+J5 -> 683.54049 | L5: =K5*1000/C5 -> 5.6961708 | M5: =K5/D5 -> 5.2580038 | N5: =IF(K5=0,0,I5/K5) -> 0.64674539 | O5: =IF(K5=0,0,J5/K5) -> 0.35325461 | P5: =IF(L5>6,"High Carbon Intensity",IF(L5>5,"Moderate Carbon Intensity","Lower Carbon Intensity")) -> Moderate Carbon Intensity | Q5: =_xlfn.RANK.EQ(L5,$L$2:$L$11,0) -> 4 | R5: =IF(P5="High Carbon Intensity","Energy audit + electricity efficiency + gas/heating system review",IF(AND(P5="Moderate Carbon Intensity",O5>0.33),"Monitor + boiler/DHW controls review","Maintain + monitor emissions")) -> Monitor + boiler/DHW controls review
A6: WI-MF-05 | B6: =_xlfn.XLOOKUP(A6,'01_input_asset_master'!A$2:A$11,'01_input_asset_master'!B$2:B$11) -> Oak Street Lofts | C6: =_xlfn.XLOOKUP(A6,'01_input_asset_master'!A$2:A$11,'01_input_asset_master'!H$2:H$11) -> 98000 | D6: =_xlfn.XLOOKUP(A6,'01_input_asset_master'!A$2:A$11,'01_input_asset_master'!I$2:I$11) -> 105 | E6: =_xlfn.XLOOKUP(A6,'11_calc_energy_summary'!A$2:A$11,'11_calc_energy_summary'!E$2:E$11) -> 642364 | F6: =_xlfn.XLOOKUP(A6,'11_calc_energy_summary'!A$2:A$11,'11_calc_energy_summary'!F$2:F$11) -> 25318 | G6: =0.527779 -> 0.527779 | H6: =5.31145 -> 5.31145 | I6: =E6*G6/1000 -> 339.02623 | J6: =F6*H6/1000 -> 134.47529 | K6: =I6+J6 -> 473.50152 | L6: =K6*1000/C6 -> 4.8316482 | M6: =K6/D6 -> 4.5095383 | N6: =IF(K6=0,0,I6/K6) -> 0.71599819 | O6: =IF(K6=0,0,J6/K6) -> 0.28400181 | P6: =IF(L6>6,"High Carbon Intensity",IF(L6>5,"Moderate Carbon Intensity","Lower Carbon Intensity")) -> Lower Carbon Intensity | Q6: =_xlfn.RANK.EQ(L6,$L$2:$L$11,0) -> 9 | R6: =IF(P6="High Carbon Intensity","Energy audit + electricity efficiency + gas/heating system review",IF(AND(P6="Moderate Carbon Intensity",O6>0.33),"Monitor + boiler/DHW controls review","Maintain + monitor emissions")) -> Maintain + monitor emissions
A7: WI-MF-06 | B7: =_xlfn.XLOOKUP(A7,'01_input_asset_master'!A$2:A$11,'01_input_asset_master'!B$2:B$11) -> South Park Apartments | C7: =_xlfn.XLOOKUP(A7,'01_input_asset_master'!A$2:A$11,'01_input_asset_master'!H$2:H$11) -> 185000 | D7: =_xlfn.XLOOKUP(A7,'01_input_asset_master'!A$2:A$11,'01_input_asset_master'!I$2:I$11) -> 210 | E7: =_xlfn.XLOOKUP(A7,'11_calc_energy_summary'!A$2:A$11,'11_calc_energy_summary'!E$2:E$11) -> 1394876 | F7: =_xlfn.XLOOKUP(A7,'11_calc_energy_summary'!A$2:A$11,'11_calc_energy_summary'!F$2:F$11) -> 77653 | G7: =0.527779 -> 0.527779 | H7: =5.31145 -> 5.31145 | I7: =E7*G7/1000 -> 736.18626 | J7: =F7*H7/1000 -> 412.45003 | K7: =I7+J7 -> 1148.6363 | L7: =K7*1000/C7 -> 6.2088448 | M7: =K7/D7 -> 5.4696966 | N7: =IF(K7=0,0,I7/K7) -> 0.64092199 | O7: =IF(K7=0,0,J7/K7) -> 0.35907801 | P7: =IF(L7>6,"High Carbon Intensity",IF(L7>5,"Moderate Carbon Intensity","Lower Carbon Intensity")) -> High Carbon Intensity | Q7: =_xlfn.RANK.EQ(L7,$L$2:$L$11,0) -> 1 | R7: =IF(P7="High Carbon Intensity","Energy audit + electricity efficiency + gas/heating system review",IF(AND(P7="Moderate Carbon Intensity",O7>0.33),"Monitor + boiler/DHW controls review","Maintain + monitor emissions")) -> Energy audit + electricity efficiency + gas/heating system review
A8: WI-MF-07 | B8: =_xlfn.XLOOKUP(A8,'01_input_asset_master'!A$2:A$11,'01_input_asset_master'!B$2:B$11) -> Fox River Flats | C8: =_xlfn.XLOOKUP(A8,'01_input_asset_master'!A$2:A$11,'01_input_asset_master'!H$2:H$11) -> 135000 | D8: =_xlfn.XLOOKUP(A8,'01_input_asset_master'!A$2:A$11,'01_input_asset_master'!I$2:I$11) -> 150 | E8: =_xlfn.XLOOKUP(A8,'11_calc_energy_summary'!A$2:A$11,'11_calc_energy_summary'!E$2:E$11) -> 907943 | F8: =_xlfn.XLOOKUP(A8,'11_calc_energy_summary'!A$2:A$11,'11_calc_energy_summary'!F$2:F$11) -> 38951 | G8: =0.527779 -> 0.527779 | H8: =5.31145 -> 5.31145 | I8: =E8*G8/1000 -> 479.19325 | J8: =F8*H8/1000 -> 206.88629 | K8: =I8+J8 -> 686.07954 | L8: =K8*1000/C8 -> 5.0820706 | M8: =K8/D8 -> 4.5738636 | N8: =IF(K8=0,0,I8/K8) -> 0.69845145 | O8: =IF(K8=0,0,J8/K8) -> 0.30154855 | P8: =IF(L8>6,"High Carbon Intensity",IF(L8>5,"Moderate Carbon Intensity","Lower Carbon Intensity")) -> Moderate Carbon Intensity | Q8: =_xlfn.RANK.EQ(L8,$L$2:$L$11,0) -> 8 | R8: =IF(P8="High Carbon Intensity","Energy audit + electricity efficiency + gas/heating system review",IF(AND(P8="Moderate Carbon Intensity",O8>0.33),"Monitor + boiler/DHW controls review","Maintain + monitor emissions")) -> Maintain + monitor emissions
A9: WI-MF-08 | B9: =_xlfn.XLOOKUP(A9,'01_input_asset_master'!A$2:A$11,'01_input_asset_master'!B$2:B$11) -> Prairie View Residences | C9: =_xlfn.XLOOKUP(A9,'01_input_asset_master'!A$2:A$11,'01_input_asset_master'!H$2:H$11) -> 110000 | D9: =_xlfn.XLOOKUP(A9,'01_input_asset_master'!A$2:A$11,'01_input_asset_master'!I$2:I$11) -> 120 | E9: =_xlfn.XLOOKUP(A9,'11_calc_energy_summary'!A$2:A$11,'11_calc_energy_summary'!E$2:E$11) -> 760039 | F9: =_xlfn.XLOOKUP(A9,'11_calc_energy_summary'!A$2:A$11,'11_calc_energy_summary'!F$2:F$11) -> 37317 | G9: =0.527779 -> 0.527779 | H9: =5.31145 -> 5.31145 | I9: =E9*G9/1000 -> 401.13262 | J9: =F9*H9/1000 -> 198.20738 | K9: =I9+J9 -> 599.34 | L9: =K9*1000/C9 -> 5.4485455 | M9: =K9/D9 -> 4.9945 | N9: =IF(K9=0,0,I9/K9) -> 0.66929059 | O9: =IF(K9=0,0,J9/K9) -> 0.33070941 | P9: =IF(L9>6,"High Carbon Intensity",IF(L9>5,"Moderate Carbon Intensity","Lower Carbon Intensity")) -> Moderate Carbon Intensity | Q9: =_xlfn.RANK.EQ(L9,$L$2:$L$11,0) -> 6 | R9: =IF(P9="High Carbon Intensity","Energy audit + electricity efficiency + gas/heating system review",IF(AND(P9="Moderate Carbon Intensity",O9>0.33),"Monitor + boiler/DHW controls review","Maintain + monitor emissions")) -> Monitor + boiler/DHW controls review
A10: WI-MF-09 | B10: =_xlfn.XLOOKUP(A10,'01_input_asset_master'!A$2:A$11,'01_input_asset_master'!B$2:B$11) -> Capitol Square Homes | C10: =_xlfn.XLOOKUP(A10,'01_input_asset_master'!A$2:A$11,'01_input_asset_master'!H$2:H$11) -> 175000 | D10: =_xlfn.XLOOKUP(A10,'01_input_asset_master'!A$2:A$11,'01_input_asset_master'!I$2:I$11) -> 190 | E10: =_xlfn.XLOOKUP(A10,'11_calc_energy_summary'!A$2:A$11,'11_calc_energy_summary'!E$2:E$11) -> 1169146 | F10: =_xlfn.XLOOKUP(A10,'11_calc_energy_summary'!A$2:A$11,'11_calc_energy_summary'!F$2:F$11) -> 42358 | G10: =0.527779 -> 0.527779 | H10: =5.31145 -> 5.31145 | I10: =E10*G10/1000 -> 617.05071 | J10: =F10*H10/1000 -> 224.9824 | K10: =I10+J10 -> 842.03311 | L10: =K10*1000/C10 -> 4.8116177 | M10: =K10/D10 -> 4.4317532 | N10: =IF(K10=0,0,I10/K10) -> 0.73281051 | O10: =IF(K10=0,0,J10/K10) -> 0.26718949 | P10: =IF(L10>6,"High Carbon Intensity",IF(L10>5,"Moderate Carbon Intensity","Lower Carbon Intensity")) -> Lower Carbon Intensity | Q10: =_xlfn.RANK.EQ(L10,$L$2:$L$11,0) -> 10 | R10: =IF(P10="High Carbon Intensity","Energy audit + electricity efficiency + gas/heating system review",IF(AND(P10="Moderate Carbon Intensity",O10>0.33),"Monitor + boiler/DHW controls review","Maintain + monitor emissions")) -> Maintain + monitor emissions
A11: WI-MF-10 | B11: =_xlfn.XLOOKUP(A11,'01_input_asset_master'!A$2:A$11,'01_input_asset_master'!B$2:B$11) -> Harbor Point Apartments | C11: =_xlfn.XLOOKUP(A11,'01_input_asset_master'!A$2:A$11,'01_input_asset_master'!H$2:H$11) -> 160000 | D11: =_xlfn.XLOOKUP(A11,'01_input_asset_master'!A$2:A$11,'01_input_asset_master'!I$2:I$11) -> 175 | E11: =_xlfn.XLOOKUP(A11,'11_calc_energy_summary'!A$2:A$11,'11_calc_energy_summary'!E$2:E$11) -> 1120844 | F11: =_xlfn.XLOOKUP(A11,'11_calc_energy_summary'!A$2:A$11,'11_calc_energy_summary'!F$2:F$11) -> 62399 | G11: =0.527779 -> 0.527779 | H11: =5.31145 -> 5.31145 | I11: =E11*G11/1000 -> 591.55793 | J11: =F11*H11/1000 -> 331.42917 | K11: =I11+J11 -> 922.98709 | L11: =K11*1000/C11 -> 5.7686693 | M11: =K11/D11 -> 5.274212 | N11: =IF(K11=0,0,I11/K11) -> 0.64091679 | O11: =IF(K11=0,0,J11/K11) -> 0.35908321 | P11: =IF(L11>6,"High Carbon Intensity",IF(L11>5,"Moderate Carbon Intensity","Lower Carbon Intensity")) -> Moderate Carbon Intensity | Q11: =_xlfn.RANK.EQ(L11,$L$2:$L$11,0) -> 3 | R11: =IF(P11="High Carbon Intensity","Energy audit + electricity efficiency + gas/heating system review",IF(AND(P11="Moderate Carbon Intensity",O11>0.33),"Monitor + boiler/DHW controls review","Maintain + monitor emissions")) -> Monitor + boiler/DHW controls review

Sheet 06_input_benchmark_data
A1: benchmark_id | B1: category | C1: property_type | D1: benchmark_metric | E1: benchmark_value | F1: unit | G1: source_name | H1: source_year | I1: source_url | J1: how_to_use | K1: notes
A2: BM-MF-SOURCE-EUI-ENERGYSTAR-2024 | B2: Energy | C2: Multifamily Housing | D2: National median Source EUI | E2: 118.1 | F2: kBtu/sqft/year | G2: ENERGY STAR Portfolio Manager U.S. National Median Table | H2: 2024 | I2: https://portfoliomanager.energystar.gov/pdf/reference/US%20National%20Median%20Table.pdf | J2: Compare portfolio source EUI to national median; source EUI is recommended for equitable comparison across fuel types. | K2: Pulled from August 2024 U.S. Energy Use Intensity by Property Type, Multifamily Housing row.
A3: BM-MF-SITE-EUI-ENERGYSTAR-2024 | B3: Energy | C3: Multifamily Housing | D3: National median Site EUI | E3: 59.6 | F3: kBtu/sqft/year | G3: ENERGY STAR Portfolio Manager U.S. National Median Table | H3: 2024 | I3: https://portfoliomanager.energystar.gov/pdf/reference/US%20National%20Median%20Table.pdf | J3: Primary benchmark for your simulated monthly energy tab and property-level EUI comparison. | K3: Pulled from August 2024 U.S. Energy Use Intensity by Property Type, Multifamily Housing row.
A4: BM-MF-REFERENCE-SOURCE | B4: Reference | C4: Multifamily Housing | D4: Peer comparison reference data source | F4: text | G4: Fannie Mae Industry Survey via ENERGY STAR | H4: 2024 | I4: https://portfoliomanager.energystar.gov/pdf/reference/US%20National%20Median%20Table.pdf | J4: Document the peer-group basis for the multifamily benchmark. | K4: ENERGY STAR table lists Fannie Mae Industry Survey as the reference data source for Multifamily Housing.
A5: BM-MF-SITE-EUI-GOOD-TARGET | B5: Internal target | C5: Multifamily Housing | D5: Good performance target Site EUI | E5: 50.0 | F5: kBtu/sqft/year | G5: Internal target derived from ENERGY STAR median | H5: 2026 | I5: https://portfoliomanager.energystar.gov/pdf/reference/US%20National%20Median%20Table.pdf | J5: Flag properties below this level as strong performers for your portfolio project. | K5: Analyst-defined target: about 16% below national median Site EUI of 59.6.
A6: BM-MF-SITE-EUI-WEAK-THRESHOLD | B6: Internal threshold | C6: Multifamily Housing | D6: Weak performance threshold Site EUI | E6: 70.0 | F6: kBtu/sqft/year | G6: Internal threshold derived from ENERGY STAR median | H6: 2026 | I6: https://portfoliomanager.energystar.gov/pdf/reference/US%20National%20Median%20Table.pdf | J6: Flag properties above this level for energy audit or retrofit prioritization. | K6: Analyst-defined threshold: about 17% above national median Site EUI of 59.6.
A7: BM-DATA-COVERAGE-GOOD | B7: Data quality | C7: All portfolio assets | D7: Good annual utility data coverage | E7: 0.95 | F7: share of months with actual data | G7: GRESB-style internal readiness threshold | H7: 2026 | I7: https://documents.gresb.com/generated_files/real_estate/2025/real_estate/reference_guide/complete.html | J7: Use to score energy/water/waste data completeness in the GRESB readiness tab. | K7: Not official GRESB scoring; practical readiness threshold for first-year reporting.
A8: BM-DATA-COVERAGE-MIN | B8: Data quality | C8: All portfolio assets | D8: Minimum usable annual utility data coverage | E8: 0.75 | F8: share of months with actual or estimated data | G8: GRESB-style internal readiness threshold | H8: 2026 | I8: https://documents.gresb.com/generated_files/real_estate/2025/real_estate/reference_guide/complete.html | J8: Flag assets below this as high data-risk and not ready for credible reporting. | K8: Analyst-defined threshold. Use for a simulated readiness model, not official GRESB scoring.
A9: BM-WATER-INTENSITY-INTERNAL | B9: Water | C9: Multifamily Housing | D9: Internal water intensity target | E9: 45000 | F9: gallons/unit/year | G9: Internal portfolio target | H9: 2026 | I9: https://www.energystar.gov/buildings/benchmark | J9: Use as a working target until actual property/utility water benchmarks are available. | K9: Private property water bills are usually required for accurate benchmarking; this is a placeholder target.
A10: BM-WASTE-DIVERSION-INTERNAL | B10: Waste | C10: Multifamily Housing | D10: Internal waste diversion target | E10: 0.3 | F10: share of total waste diverted | G10: Internal portfolio target | H10: 2026 | I10: https://www.epa.gov/waste-reduction-model | J10: Use as an initial target for waste management performance and improvement planning. | K10: Use EPA WARM later for emissions impact of landfill/recycling/compost scenarios.
A11: BM-GHG-INTENSITY-INTERNAL | B11: GHG | C11: Multifamily Housing | D11: Internal GHG intensity target | E11: 0.006 | F11: tCO2e/sqft/year | G11: Internal portfolio target using EPA emissions factors | H11: 2026 | I11: https://www.epa.gov/egrid | J11: Use as a portfolio screening target after calculating Scope 1 and Scope 2 emissions. | K11: This target depends on actual fuel mix and EPA eGRID/natural gas factors.

Sheet 15_calc_integrated_priority
A1: property_id | B1: property_name | C1: gross_floor_area_sqft | D1: units | E1: site_eui_kbtu_sqft | F1: energy_performance_flag | G1: energy_cost_per_unit | H1: energy_priority_rank | I1: annual_water_gallons | J1: water_per_unit_gal | K1: water_cost_per_unit | L1: water_performance_flag | M1: annual_total_waste_tons | N1: waste_per_unit_tons | O1: waste_diversion_rate | P1: waste_performance_flag | Q1: diversion_performance_flag | R1: total_scope1_scope2_emissions_tco2e | S1: emissions_intensity_kgco2e_sqft | T1: emissions_per_unit_tco2e | U1: carbon_performance_flag | V1: carbon_priority_rank | W1: energy_data_coverage_pct | X1: water_data_coverage_pct | Y1: waste_data_coverage_pct | Z1: integrated_priority_score | AA1: integrated_priority_rank | AB1: overall_priority_flag | AC1: recommended_integrated_action | AD1: number_of_major_issues | AE1: primary_issue
A2: WI-MF-02 | B2: =_xlfn.XLOOKUP(A2,'01_input_asset_master'!A$2:A$11,'01_input_asset_master'!B$2:B$11) -> Lakeview Terrace | C2: =_xlfn.XLOOKUP(A2,'01_input_asset_master'!A$2:A$11,'01_input_asset_master'!H$2:H$11) -> 220000 | D2: =_xlfn.XLOOKUP(A2,'01_input_asset_master'!A$2:A$11,'01_input_asset_master'!I$2:I$11) -> 240 | E2: =_xlfn.XLOOKUP($A2,'11_calc_energy_summary'!$A$2:$A$11,'11_calc_energy_summary'!$M$2:$M$11) -> 66.200524 | F2: =_xlfn.XLOOKUP($A2,'11_calc_energy_summary'!$A$2:$A$11,'11_calc_energy_summary'!$V$2:$V$11) -> Above Benchmark | G2: =_xlfn.XLOOKUP(A2,'11_calc_energy_summary'!A$2:A$11,'11_calc_energy_summary'!P$2:P$11) -> 1393.8332 | H2: =_xlfn.RANK.EQ(E2,$E$2:$E$11,0) -> 2 | I2: =_xlfn.XLOOKUP(A2,'12_calc_water_summary'!A$2:A$11,'12_calc_water_summary'!E$2:E$11) -> 79558.5 | J2: =_xlfn.XLOOKUP($A2,'12_calc_water_summary'!$A$2:$A$11,'12_calc_water_summary'!$J$2:$J$11) -> 331.49375 | K2: =_xlfn.XLOOKUP(A2,'12_calc_water_summary'!A$2:A$11,'12_calc_water_summary'!K$2:K$11) -> 805.05617 | L2: =_xlfn.XLOOKUP($A2,'12_calc_water_summary'!$A$2:$A$11,'12_calc_water_summary'!$O$2:$O$11) -> Efficient/Low | M2: =_xlfn.XLOOKUP(A2,'13_calc_waste_summary'!A$2:A$11,'13_calc_waste_summary'!H$2:H$11) -> 199.95 | N2: =_xlfn.XLOOKUP($A2,'13_calc_waste_summary'!$A$2:$A$11,'13_calc_waste_summary'!$L$2:$L$11) -> 0.833125 | O2: =_xlfn.XLOOKUP($A2,'13_calc_waste_summary'!$A$2:$A$11,'13_calc_waste_summary'!$K$2:$K$11) -> 0.18344586 | P2: =_xlfn.XLOOKUP(A2,'13_calc_waste_summary'!A$2:A$11,'13_calc_waste_summary'!R$2:R$11) -> High Waste | Q2: =_xlfn.XLOOKUP(A2,'13_calc_waste_summary'!A$2:A$11,'13_calc_waste_summary'!S$2:S$11) -> Weak Diversion | R2: =_xlfn.XLOOKUP(A2,'14_calc_emissions_summary'!A$2:A$11,'14_calc_emissions_summary'!K$2:K$11) -> 1335.6788 | S2: =_xlfn.XLOOKUP($A2,'14_calc_emissions_summary'!$A$2:$A$11,'14_calc_emissions_summary'!$L$2:$L$11) -> 6.0712671 | T2: =_xlfn.XLOOKUP(A2,'14_calc_emissions_summary'!A$2:A$11,'14_calc_emissions_summary'!M$2:M$11) -> 5.5653282 | U2: =_xlfn.XLOOKUP($A2,'14_calc_emissions_summary'!$A$2:$A$11,'14_calc_emissions_summary'!$P$2:$P$11) -> High Carbon Intensity | V2: =_xlfn.XLOOKUP(A2,'14_calc_emissions_summary'!A$2:A$11,'14_calc_emissions_summary'!Q$2:Q$11) -> 2 | W2: =_xlfn.XLOOKUP($A2,'11_calc_energy_summary'!$A$2:$A$11,'11_calc_energy_summary'!$S$2:$S$11) -> 1 | X2: =_xlfn.XLOOKUP(A2,'12_calc_water_summary'!A$2:A$11,'12_calc_water_summary'!N$2:N$11) -> 1 | Y2: =_xlfn.XLOOKUP(A2,'13_calc_waste_summary'!A$2:A$11,'13_calc_waste_summary'!Q$2:Q$11) -> 1 | Z2: =IF(F2="High Energy Use",3,IF(F2="Above Benchmark",2,1))+IF(L2="High Water Use",3,IF(L2="Moderate",2,1))+IF(P2="High Waste",3,IF(P2="Moderate",2,1))+IF(U2="High Carbon Intensity",3,IF(U2="Moderate Carbon Intensity",2,1))+IF(Q2="Weak Diversion",1,0)+IF(MIN(W2:Y2)<0.95,1,0) -> 10 | AA2: =_xlfn.RANK.EQ(Z2,$Z$2:$Z$11,0) -> 1 | AB2: =IF(Z2>=10,"High Portfolio Priority",IF(Z2>=8,"Medium Portfolio Priority","Lower Portfolio Priority")) -> High Portfolio Priority | AC2: =IF(AND(F2="Above Benchmark",U2="High Carbon Intensity",P2="High Waste",Q2="Weak Diversion"),"Comprehensive audit: energy, carbon, and waste/diversion",IF(AND(F2="Above Benchmark",U2="High Carbon Intensity"),"Energy and carbon retrofit focus",IF(AND(P2="High Waste",Q2="Weak Diversion"),"Waste audit + recycling/diversion program",IF(L2="High Water Use","Water audit + leak detection + fixture review","Maintain performance + monitor KPIs")))) -> Comprehensive audit: energy, carbon, and waste/diversion | AD2: =IF(OR(F2="Above Benchmark",F2="High Energy Use"),1,0)+IF(L2="High Water Use",1,0)+IF(P2="High Waste",1,0)+IF(Q2="Weak Diversion",1,0)+IF(U2="High Carbon Intensity",1,0) -> 4 | AE2: =IF(AND(F2="Above Benchmark",U2="High Carbon Intensity"),"Energy + Carbon",IF(AND(P2="High Waste",Q2="Weak Diversion"),"Waste + Diversion",IF(F2="Above Benchmark","Energy",IF(U2="High Carbon Intensity","Carbon",IF(L2="High Water Use","Water","Monitor"))))) -> Energy + Carbon
A3: WI-MF-06 | B3: =_xlfn.XLOOKUP(A3,'01_input_asset_master'!A$2:A$11,'01_input_asset_master'!B$2:B$11) -> South Park Apartments | C3: =_xlfn.XLOOKUP(A3,'01_input_asset_master'!A$2:A$11,'01_input_asset_master'!H$2:H$11) -> 185000 | D3: =_xlfn.XLOOKUP(A3,'01_input_asset_master'!A$2:A$11,'01_input_asset_master'!I$2:I$11) -> 210 | E3: =_xlfn.XLOOKUP($A3,'11_calc_energy_summary'!$A$2:$A$11,'11_calc_energy_summary'!$M$2:$M$11) -> 67.700632 | F3: =_xlfn.XLOOKUP($A3,'11_calc_energy_summary'!$A$2:$A$11,'11_calc_energy_summary'!$V$2:$V$11) -> Above Benchmark | G3: =_xlfn.XLOOKUP(A3,'11_calc_energy_summary'!A$2:A$11,'11_calc_energy_summary'!P$2:P$11) -> 1369.8824 | H3: =_xlfn.RANK.EQ(E3,$E$2:$E$11,0) -> 1 | I3: =_xlfn.XLOOKUP(A3,'12_calc_water_summary'!A$2:A$11,'12_calc_water_summary'!E$2:E$11) -> 66315.92 | J3: =_xlfn.XLOOKUP($A3,'12_calc_water_summary'!$A$2:$A$11,'12_calc_water_summary'!$J$2:$J$11) -> 315.7901 | K3: =_xlfn.XLOOKUP(A3,'12_calc_water_summary'!A$2:A$11,'12_calc_water_summary'!K$2:K$11) -> 766.91895 | L3: =_xlfn.XLOOKUP($A3,'12_calc_water_summary'!$A$2:$A$11,'12_calc_water_summary'!$O$2:$O$11) -> Efficient/Low | M3: =_xlfn.XLOOKUP(A3,'13_calc_waste_summary'!A$2:A$11,'13_calc_waste_summary'!H$2:H$11) -> 179.09 | N3: =_xlfn.XLOOKUP($A3,'13_calc_waste_summary'!$A$2:$A$11,'13_calc_waste_summary'!$L$2:$L$11) -> 0.85280952 | O3: =_xlfn.XLOOKUP($A3,'13_calc_waste_summary'!$A$2:$A$11,'13_calc_waste_summary'!$K$2:$K$11) -> 0.2106762 | P3: =_xlfn.XLOOKUP(A3,'13_calc_waste_summary'!A$2:A$11,'13_calc_waste_summary'!R$2:R$11) -> High Waste | Q3: =_xlfn.XLOOKUP(A3,'13_calc_waste_summary'!A$2:A$11,'13_calc_waste_summary'!S$2:S$11) -> Weak Diversion | R3: =_xlfn.XLOOKUP(A3,'14_calc_emissions_summary'!A$2:A$11,'14_calc_emissions_summary'!K$2:K$11) -> 1148.6363 | S3: =_xlfn.XLOOKUP($A3,'14_calc_emissions_summary'!$A$2:$A$11,'14_calc_emissions_summary'!$L$2:$L$11) -> 6.2088448 | T3: =_xlfn.XLOOKUP(A3,'14_calc_emissions_summary'!A$2:A$11,'14_calc_emissions_summary'!M$2:M$11) -> 5.4696966 | U3: =_xlfn.XLOOKUP($A3,'14_calc_emissions_summary'!$A$2:$A$11,'14_calc_emissions_summary'!$P$2:$P$11) -> High Carbon Intensity | V3: =_xlfn.XLOOKUP(A3,'14_calc_emissions_summary'!A$2:A$11,'14_calc_emissions_summary'!Q$2:Q$11) -> 1 | W3: =_xlfn.XLOOKUP($A3,'11_calc_energy_summary'!$A$2:$A$11,'11_calc_energy_summary'!$S$2:$S$11) -> 1 | X3: =_xlfn.XLOOKUP(A3,'12_calc_water_summary'!A$2:A$11,'12_calc_water_summary'!N$2:N$11) -> 1 | Y3: =_xlfn.XLOOKUP(A3,'13_calc_waste_summary'!A$2:A$11,'13_calc_waste_summary'!Q$2:Q$11) -> 1 | Z3: =IF(F3="High Energy Use",3,IF(F3="Above Benchmark",2,1))+IF(L3="High Water Use",3,IF(L3="Moderate",2,1))+IF(P3="High Waste",3,IF(P3="Moderate",2,1))+IF(U3="High Carbon Intensity",3,IF(U3="Moderate Carbon Intensity",2,1))+IF(Q3="Weak Diversion",1,0)+IF(MIN(W3:Y3)<0.95,1,0) -> 10 | AA3: =_xlfn.RANK.EQ(Z3,$Z$2:$Z$11,0) -> 1 | AB3: =IF(Z3>=10,"High Portfolio Priority",IF(Z3>=8,"Medium Portfolio Priority","Lower Portfolio Priority")) -> High Portfolio Priority | AC3: =IF(AND(F3="Above Benchmark",U3="High Carbon Intensity",P3="High Waste",Q3="Weak Diversion"),"Comprehensive audit: energy, carbon, and waste/diversion",IF(AND(F3="Above Benchmark",U3="High Carbon Intensity"),"Energy and carbon retrofit focus",IF(AND(P3="High Waste",Q3="Weak Diversion"),"Waste audit + recycling/diversion program",IF(L3="High Water Use","Water audit + leak detection + fixture review","Maintain performance + monitor KPIs")))) -> Comprehensive audit: energy, carbon, and waste/diversion | AD3: =IF(OR(F3="Above Benchmark",F3="High Energy Use"),1,0)+IF(L3="High Water Use",1,0)+IF(P3="High Waste",1,0)+IF(Q3="Weak Diversion",1,0)+IF(U3="High Carbon Intensity",1,0) -> 4 | AE3: =IF(AND(F3="Above Benchmark",U3="High Carbon Intensity"),"Energy + Carbon",IF(AND(P3="High Waste",Q3="Weak Diversion"),"Waste + Diversion",IF(F3="Above Benchmark","Energy",IF(U3="High Carbon Intensity","Carbon",IF(L3="High Water Use","Water","Monitor"))))) -> Energy + Carbon | AI3: The integrated performance summary identifies Lakeview Terrace and South Park Apartments as the highest-priority assets in the portfolio. Both properties combine above-benchmark energy use, high carbon intensity, high waste generation, and weak diversion performance. Harbor Point Apartments and Badger Ridge Homes form the second-priority group because they also show above-benchmark energy use and weak waste diversion, though their carbon intensity is moderate rather than high. Across the full portfolio, water performance appears efficient, while waste diversion is the most consistent weakness, with most properties below 30% diversion. This suggests the portfolio should prioritize comprehensive energy/carbon/waste reviews for the top two assets and a broader waste-diversion improvement program across the portfolio.
A4: WI-MF-10 | B4: =_xlfn.XLOOKUP(A4,'01_input_asset_master'!A$2:A$11,'01_input_asset_master'!B$2:B$11) -> Harbor Point Apartments | C4: =_xlfn.XLOOKUP(A4,'01_input_asset_master'!A$2:A$11,'01_input_asset_master'!H$2:H$11) -> 160000 | D4: =_xlfn.XLOOKUP(A4,'01_input_asset_master'!A$2:A$11,'01_input_asset_master'!I$2:I$11) -> 175 | E4: =_xlfn.XLOOKUP($A4,'11_calc_energy_summary'!$A$2:$A$11,'11_calc_energy_summary'!$M$2:$M$11) -> 62.901373 | F4: =_xlfn.XLOOKUP($A4,'11_calc_energy_summary'!$A$2:$A$11,'11_calc_energy_summary'!$V$2:$V$11) -> Above Benchmark | G4: =_xlfn.XLOOKUP(A4,'11_calc_energy_summary'!A$2:A$11,'11_calc_energy_summary'!P$2:P$11) -> 1320.9214 | H4: =_xlfn.RANK.EQ(E4,$E$2:$E$11,0) -> 3 | I4: =_xlfn.XLOOKUP(A4,'12_calc_water_summary'!A$2:A$11,'12_calc_water_summary'!E$2:E$11) -> 53206.6 | J4: =_xlfn.XLOOKUP($A4,'12_calc_water_summary'!$A$2:$A$11,'12_calc_water_summary'!$J$2:$J$11) -> 304.03771 | K4: =_xlfn.XLOOKUP(A4,'12_calc_water_summary'!A$2:A$11,'12_calc_water_summary'!K$2:K$11) -> 738.37726 | L4: =_xlfn.XLOOKUP($A4,'12_calc_water_summary'!$A$2:$A$11,'12_calc_water_summary'!$O$2:$O$11) -> Efficient/Low | M4: =_xlfn.XLOOKUP(A4,'13_calc_waste_summary'!A$2:A$11,'13_calc_waste_summary'!H$2:H$11) -> 141.57 | N4: =_xlfn.XLOOKUP($A4,'13_calc_waste_summary'!$A$2:$A$11,'13_calc_waste_summary'!$L$2:$L$11) -> 0.80897143 | O4: =_xlfn.XLOOKUP($A4,'13_calc_waste_summary'!$A$2:$A$11,'13_calc_waste_summary'!$K$2:$K$11) -> 0.20745921 | P4: =_xlfn.XLOOKUP(A4,'13_calc_waste_summary'!A$2:A$11,'13_calc_waste_summary'!R$2:R$11) -> High Waste | Q4: =_xlfn.XLOOKUP(A4,'13_calc_waste_summary'!A$2:A$11,'13_calc_waste_summary'!S$2:S$11) -> Weak Diversion | R4: =_xlfn.XLOOKUP(A4,'14_calc_emissions_summary'!A$2:A$11,'14_calc_emissions_summary'!K$2:K$11) -> 922.98709 | S4: =_xlfn.XLOOKUP($A4,'14_calc_emissions_summary'!$A$2:$A$11,'14_calc_emissions_summary'!$L$2:$L$11) -> 5.7686693 | T4: =_xlfn.XLOOKUP(A4,'14_calc_emissions_summary'!A$2:A$11,'14_calc_emissions_summary'!M$2:M$11) -> 5.274212 | U4: =_xlfn.XLOOKUP($A4,'14_calc_emissions_summary'!$A$2:$A$11,'14_calc_emissions_summary'!$P$2:$P$11) -> Moderate Carbon Intensity | V4: =_xlfn.XLOOKUP(A4,'14_calc_emissions_summary'!A$2:A$11,'14_calc_emissions_summary'!Q$2:Q$11) -> 3 | W4: =_xlfn.XLOOKUP($A4,'11_calc_energy_summary'!$A$2:$A$11,'11_calc_energy_summary'!$S$2:$S$11) -> 1 | X4: =_xlfn.XLOOKUP(A4,'12_calc_water_summary'!A$2:A$11,'12_calc_water_summary'!N$2:N$11) -> 1 | Y4: =_xlfn.XLOOKUP(A4,'13_calc_waste_summary'!A$2:A$11,'13_calc_waste_summary'!Q$2:Q$11) -> 1 | Z4: =IF(F4="High Energy Use",3,IF(F4="Above Benchmark",2,1))+IF(L4="High Water Use",3,IF(L4="Moderate",2,1))+IF(P4="High Waste",3,IF(P4="Moderate",2,1))+IF(U4="High Carbon Intensity",3,IF(U4="Moderate Carbon Intensity",2,1))+IF(Q4="Weak Diversion",1,0)+IF(MIN(W4:Y4)<0.95,1,0) -> 9 | AA4: =_xlfn.RANK.EQ(Z4,$Z$2:$Z$11,0) -> 3 | AB4: =IF(Z4>=10,"High Portfolio Priority",IF(Z4>=8,"Medium Portfolio Priority","Lower Portfolio Priority")) -> Medium Portfolio Priority | AC4: =IF(AND(F4="Above Benchmark",U4="High Carbon Intensity",P4="High Waste",Q4="Weak Diversion"),"Comprehensive audit: energy, carbon, and waste/diversion",IF(AND(F4="Above Benchmark",U4="High Carbon Intensity"),"Energy and carbon retrofit focus",IF(AND(P4="High Waste",Q4="Weak Diversion"),"Waste audit + recycling/diversion program",IF(L4="High Water Use","Water audit + leak detection + fixture review","Maintain performance + monitor KPIs")))) -> Waste audit + recycling/diversion program | AD4: =IF(OR(F4="Above Benchmark",F4="High Energy Use"),1,0)+IF(L4="High Water Use",1,0)+IF(P4="High Waste",1,0)+IF(Q4="Weak Diversion",1,0)+IF(U4="High Carbon Intensity",1,0) -> 3 | AE4: =IF(AND(F4="Above Benchmark",U4="High Carbon Intensity"),"Energy + Carbon",IF(AND(P4="High Waste",Q4="Weak Diversion"),"Waste + Diversion",IF(F4="Above Benchmark","Energy",IF(U4="High Carbon Intensity","Carbon",IF(L4="High Water Use","Water","Monitor"))))) -> Waste + Diversion
A5: WI-MF-04 | B5: =_xlfn.XLOOKUP(A5,'01_input_asset_master'!A$2:A$11,'01_input_asset_master'!B$2:B$11) -> Badger Ridge Homes | C5: =_xlfn.XLOOKUP(A5,'01_input_asset_master'!A$2:A$11,'01_input_asset_master'!H$2:H$11) -> 120000 | D5: =_xlfn.XLOOKUP(A5,'01_input_asset_master'!A$2:A$11,'01_input_asset_master'!I$2:I$11) -> 130 | E5: =_xlfn.XLOOKUP($A5,'11_calc_energy_summary'!$A$2:$A$11,'11_calc_energy_summary'!$M$2:$M$11) -> 61.70041 | F5: =_xlfn.XLOOKUP($A5,'11_calc_energy_summary'!$A$2:$A$11,'11_calc_energy_summary'!$V$2:$V$11) -> Above Benchmark | G5: =_xlfn.XLOOKUP(A5,'11_calc_energy_summary'!A$2:A$11,'11_calc_energy_summary'!P$2:P$11) -> 1318.9351 | H5: =_xlfn.RANK.EQ(E5,$E$2:$E$11,0) -> 4 | I5: =_xlfn.XLOOKUP(A5,'12_calc_water_summary'!A$2:A$11,'12_calc_water_summary'!E$2:E$11) -> 32382.31 | J5: =_xlfn.XLOOKUP($A5,'12_calc_water_summary'!$A$2:$A$11,'12_calc_water_summary'!$J$2:$J$11) -> 249.09469 | K5: =_xlfn.XLOOKUP(A5,'12_calc_water_summary'!A$2:A$11,'12_calc_water_summary'!K$2:K$11) -> 604.944 | L5: =_xlfn.XLOOKUP($A5,'12_calc_water_summary'!$A$2:$A$11,'12_calc_water_summary'!$O$2:$O$11) -> Efficient/Low | M5: =_xlfn.XLOOKUP(A5,'13_calc_waste_summary'!A$2:A$11,'13_calc_waste_summary'!H$2:H$11) -> 109.2 | N5: =_xlfn.XLOOKUP($A5,'13_calc_waste_summary'!$A$2:$A$11,'13_calc_waste_summary'!$L$2:$L$11) -> 0.84 | O5: =_xlfn.XLOOKUP($A5,'13_calc_waste_summary'!$A$2:$A$11,'13_calc_waste_summary'!$K$2:$K$11) -> 0.21895604 | P5: =_xlfn.XLOOKUP(A5,'13_calc_waste_summary'!A$2:A$11,'13_calc_waste_summary'!R$2:R$11) -> High Waste | Q5: =_xlfn.XLOOKUP(A5,'13_calc_waste_summary'!A$2:A$11,'13_calc_waste_summary'!S$2:S$11) -> Weak Diversion | R5: =_xlfn.XLOOKUP(A5,'14_calc_emissions_summary'!A$2:A$11,'14_calc_emissions_summary'!K$2:K$11) -> 683.54049 | S5: =_xlfn.XLOOKUP($A5,'14_calc_emissions_summary'!$A$2:$A$11,'14_calc_emissions_summary'!$L$2:$L$11) -> 5.6961708 | T5: =_xlfn.XLOOKUP(A5,'14_calc_emissions_summary'!A$2:A$11,'14_calc_emissions_summary'!M$2:M$11) -> 5.2580038 | U5: =_xlfn.XLOOKUP($A5,'14_calc_emissions_summary'!$A$2:$A$11,'14_calc_emissions_summary'!$P$2:$P$11) -> Moderate Carbon Intensity | V5: =_xlfn.XLOOKUP(A5,'14_calc_emissions_summary'!A$2:A$11,'14_calc_emissions_summary'!Q$2:Q$11) -> 4 | W5: =_xlfn.XLOOKUP($A5,'11_calc_energy_summary'!$A$2:$A$11,'11_calc_energy_summary'!$S$2:$S$11) -> 1 | X5: =_xlfn.XLOOKUP(A5,'12_calc_water_summary'!A$2:A$11,'12_calc_water_summary'!N$2:N$11) -> 1 | Y5: =_xlfn.XLOOKUP(A5,'13_calc_waste_summary'!A$2:A$11,'13_calc_waste_summary'!Q$2:Q$11) -> 1 | Z5: =IF(F5="High Energy Use",3,IF(F5="Above Benchmark",2,1))+IF(L5="High Water Use",3,IF(L5="Moderate",2,1))+IF(P5="High Waste",3,IF(P5="Moderate",2,1))+IF(U5="High Carbon Intensity",3,IF(U5="Moderate Carbon Intensity",2,1))+IF(Q5="Weak Diversion",1,0)+IF(MIN(W5:Y5)<0.95,1,0) -> 9 | AA5: =_xlfn.RANK.EQ(Z5,$Z$2:$Z$11,0) -> 3 | AB5: =IF(Z5>=10,"High Portfolio Priority",IF(Z5>=8,"Medium Portfolio Priority","Lower Portfolio Priority")) -> Medium Portfolio Priority | AC5: =IF(AND(F5="Above Benchmark",U5="High Carbon Intensity",P5="High Waste",Q5="Weak Diversion"),"Comprehensive audit: energy, carbon, and waste/diversion",IF(AND(F5="Above Benchmark",U5="High Carbon Intensity"),"Energy and carbon retrofit focus",IF(AND(P5="High Waste",Q5="Weak Diversion"),"Waste audit + recycling/diversion program",IF(L5="High Water Use","Water audit + leak detection + fixture review","Maintain performance + monitor KPIs")))) -> Waste audit + recycling/diversion program | AD5: =IF(OR(F5="Above Benchmark",F5="High Energy Use"),1,0)+IF(L5="High Water Use",1,0)+IF(P5="High Waste",1,0)+IF(Q5="Weak Diversion",1,0)+IF(U5="High Carbon Intensity",1,0) -> 3 | AE5: =IF(AND(F5="Above Benchmark",U5="High Carbon Intensity"),"Energy + Carbon",IF(AND(P5="High Waste",Q5="Weak Diversion"),"Waste + Diversion",IF(F5="Above Benchmark","Energy",IF(U5="High Carbon Intensity","Carbon",IF(L5="High Water Use","Water","Monitor"))))) -> Waste + Diversion
A6: WI-MF-01 | B6: =_xlfn.XLOOKUP(A6,'01_input_asset_master'!A$2:A$11,'01_input_asset_master'!B$2:B$11) -> Riverbend Apartments | C6: =_xlfn.XLOOKUP(A6,'01_input_asset_master'!A$2:A$11,'01_input_asset_master'!H$2:H$11) -> 165000 | D6: =_xlfn.XLOOKUP(A6,'01_input_asset_master'!A$2:A$11,'01_input_asset_master'!I$2:I$11) -> 180 | E6: =_xlfn.XLOOKUP($A6,'11_calc_energy_summary'!$A$2:$A$11,'11_calc_energy_summary'!$M$2:$M$11) -> 57.900082 | F6: =_xlfn.XLOOKUP($A6,'11_calc_energy_summary'!$A$2:$A$11,'11_calc_energy_summary'!$V$2:$V$11) -> At/Below Benchmark | G6: =_xlfn.XLOOKUP(A6,'11_calc_energy_summary'!A$2:A$11,'11_calc_energy_summary'!P$2:P$11) -> 1259.1952 | H6: =_xlfn.RANK.EQ(E6,$E$2:$E$11,0) -> 5 | I6: =_xlfn.XLOOKUP(A6,'12_calc_water_summary'!A$2:A$11,'12_calc_water_summary'!E$2:E$11) -> 46404.35 | J6: =_xlfn.XLOOKUP($A6,'12_calc_water_summary'!$A$2:$A$11,'12_calc_water_summary'!$J$2:$J$11) -> 257.80194 | K6: =_xlfn.XLOOKUP(A6,'12_calc_water_summary'!A$2:A$11,'12_calc_water_summary'!K$2:K$11) -> 626.09011 | L6: =_xlfn.XLOOKUP($A6,'12_calc_water_summary'!$A$2:$A$11,'12_calc_water_summary'!$O$2:$O$11) -> Efficient/Low | M6: =_xlfn.XLOOKUP(A6,'13_calc_waste_summary'!A$2:A$11,'13_calc_waste_summary'!H$2:H$11) -> 147.41 | N6: =_xlfn.XLOOKUP($A6,'13_calc_waste_summary'!$A$2:$A$11,'13_calc_waste_summary'!$L$2:$L$11) -> 0.81894444 | O6: =_xlfn.XLOOKUP($A6,'13_calc_waste_summary'!$A$2:$A$11,'13_calc_waste_summary'!$K$2:$K$11) -> 0.22230514 | P6: =_xlfn.XLOOKUP(A6,'13_calc_waste_summary'!A$2:A$11,'13_calc_waste_summary'!R$2:R$11) -> High Waste | Q6: =_xlfn.XLOOKUP(A6,'13_calc_waste_summary'!A$2:A$11,'13_calc_waste_summary'!S$2:S$11) -> Weak Diversion | R6: =_xlfn.XLOOKUP(A6,'14_calc_emissions_summary'!A$2:A$11,'14_calc_emissions_summary'!K$2:K$11) -> 899.44592 | S6: =_xlfn.XLOOKUP($A6,'14_calc_emissions_summary'!$A$2:$A$11,'14_calc_emissions_summary'!$L$2:$L$11) -> 5.4511874 | T6: =_xlfn.XLOOKUP(A6,'14_calc_emissions_summary'!A$2:A$11,'14_calc_emissions_summary'!M$2:M$11) -> 4.9969218 | U6: =_xlfn.XLOOKUP($A6,'14_calc_emissions_summary'!$A$2:$A$11,'14_calc_emissions_summary'!$P$2:$P$11) -> Moderate Carbon Intensity | V6: =_xlfn.XLOOKUP(A6,'14_calc_emissions_summary'!A$2:A$11,'14_calc_emissions_summary'!Q$2:Q$11) -> 5 | W6: =_xlfn.XLOOKUP($A6,'11_calc_energy_summary'!$A$2:$A$11,'11_calc_energy_summary'!$S$2:$S$11) -> 1 | X6: =_xlfn.XLOOKUP(A6,'12_calc_water_summary'!A$2:A$11,'12_calc_water_summary'!N$2:N$11) -> 1 | Y6: =_xlfn.XLOOKUP(A6,'13_calc_waste_summary'!A$2:A$11,'13_calc_waste_summary'!Q$2:Q$11) -> 1 | Z6: =IF(F6="High Energy Use",3,IF(F6="Above Benchmark",2,1))+IF(L6="High Water Use",3,IF(L6="Moderate",2,1))+IF(P6="High Waste",3,IF(P6="Moderate",2,1))+IF(U6="High Carbon Intensity",3,IF(U6="Moderate Carbon Intensity",2,1))+IF(Q6="Weak Diversion",1,0)+IF(MIN(W6:Y6)<0.95,1,0) -> 8 | AA6: =_xlfn.RANK.EQ(Z6,$Z$2:$Z$11,0) -> 5 | AB6: =IF(Z6>=10,"High Portfolio Priority",IF(Z6>=8,"Medium Portfolio Priority","Lower Portfolio Priority")) -> Medium Portfolio Priority | AC6: =IF(AND(F6="Above Benchmark",U6="High Carbon Intensity",P6="High Waste",Q6="Weak Diversion"),"Comprehensive audit: energy, carbon, and waste/diversion",IF(AND(F6="Above Benchmark",U6="High Carbon Intensity"),"Energy and carbon retrofit focus",IF(AND(P6="High Waste",Q6="Weak Diversion"),"Waste audit + recycling/diversion program",IF(L6="High Water Use","Water audit + leak detection + fixture review","Maintain performance + monitor KPIs")))) -> Waste audit + recycling/diversion program | AD6: =IF(OR(F6="Above Benchmark",F6="High Energy Use"),1,0)+IF(L6="High Water Use",1,0)+IF(P6="High Waste",1,0)+IF(Q6="Weak Diversion",1,0)+IF(U6="High Carbon Intensity",1,0) -> 2 | AE6: =IF(AND(F6="Above Benchmark",U6="High Carbon Intensity"),"Energy + Carbon",IF(AND(P6="High Waste",Q6="Weak Diversion"),"Waste + Diversion",IF(F6="Above Benchmark","Energy",IF(U6="High Carbon Intensity","Carbon",IF(L6="High Water Use","Water","Monitor"))))) -> Waste + Diversion
A7: WI-MF-03 | B7: =_xlfn.XLOOKUP(A7,'01_input_asset_master'!A$2:A$11,'01_input_asset_master'!B$2:B$11) -> Northside Commons | C7: =_xlfn.XLOOKUP(A7,'01_input_asset_master'!A$2:A$11,'01_input_asset_master'!H$2:H$11) -> 145000 | D7: =_xlfn.XLOOKUP(A7,'01_input_asset_master'!A$2:A$11,'01_input_asset_master'!I$2:I$11) -> 160 | E7: =_xlfn.XLOOKUP($A7,'11_calc_energy_summary'!$A$2:$A$11,'11_calc_energy_summary'!$M$2:$M$11) -> 54.298187 | F7: =_xlfn.XLOOKUP($A7,'11_calc_energy_summary'!$A$2:$A$11,'11_calc_energy_summary'!$V$2:$V$11) -> At/Below Benchmark | G7: =_xlfn.XLOOKUP(A7,'11_calc_energy_summary'!A$2:A$11,'11_calc_energy_summary'!P$2:P$11) -> 1200.0141 | H7: =_xlfn.RANK.EQ(E7,$E$2:$E$11,0) -> 7 | I7: =_xlfn.XLOOKUP(A7,'12_calc_water_summary'!A$2:A$11,'12_calc_water_summary'!E$2:E$11) -> 37799.44 | J7: =_xlfn.XLOOKUP($A7,'12_calc_water_summary'!$A$2:$A$11,'12_calc_water_summary'!$J$2:$J$11) -> 236.2465 | K7: =_xlfn.XLOOKUP(A7,'12_calc_water_summary'!A$2:A$11,'12_calc_water_summary'!K$2:K$11) -> 573.7415 | L7: =_xlfn.XLOOKUP($A7,'12_calc_water_summary'!$A$2:$A$11,'12_calc_water_summary'!$O$2:$O$11) -> Efficient/Low | M7: =_xlfn.XLOOKUP(A7,'13_calc_waste_summary'!A$2:A$11,'13_calc_waste_summary'!H$2:H$11) -> 130.6 | N7: =_xlfn.XLOOKUP($A7,'13_calc_waste_summary'!$A$2:$A$11,'13_calc_waste_summary'!$L$2:$L$11) -> 0.81625 | O7: =_xlfn.XLOOKUP($A7,'13_calc_waste_summary'!$A$2:$A$11,'13_calc_waste_summary'!$K$2:$K$11) -> 0.27059724 | P7: =_xlfn.XLOOKUP(A7,'13_calc_waste_summary'!A$2:A$11,'13_calc_waste_summary'!R$2:R$11) -> High Waste | Q7: =_xlfn.XLOOKUP(A7,'13_calc_waste_summary'!A$2:A$11,'13_calc_waste_summary'!S$2:S$11) -> Weak Diversion | R7: =_xlfn.XLOOKUP(A7,'14_calc_emissions_summary'!A$2:A$11,'14_calc_emissions_summary'!K$2:K$11) -> 758.05593 | S7: =_xlfn.XLOOKUP($A7,'14_calc_emissions_summary'!$A$2:$A$11,'14_calc_emissions_summary'!$L$2:$L$11) -> 5.2279719 | T7: =_xlfn.XLOOKUP(A7,'14_calc_emissions_summary'!A$2:A$11,'14_calc_emissions_summary'!M$2:M$11) -> 4.7378496 | U7: =_xlfn.XLOOKUP($A7,'14_calc_emissions_summary'!$A$2:$A$11,'14_calc_emissions_summary'!$P$2:$P$11) -> Moderate Carbon Intensity | V7: =_xlfn.XLOOKUP(A7,'14_calc_emissions_summary'!A$2:A$11,'14_calc_emissions_summary'!Q$2:Q$11) -> 7 | W7: =_xlfn.XLOOKUP($A7,'11_calc_energy_summary'!$A$2:$A$11,'11_calc_energy_summary'!$S$2:$S$11) -> 1 | X7: =_xlfn.XLOOKUP(A7,'12_calc_water_summary'!A$2:A$11,'12_calc_water_summary'!N$2:N$11) -> 1 | Y7: =_xlfn.XLOOKUP(A7,'13_calc_waste_summary'!A$2:A$11,'13_calc_waste_summary'!Q$2:Q$11) -> 1 | Z7: =IF(F7="High Energy Use",3,IF(F7="Above Benchmark",2,1))+IF(L7="High Water Use",3,IF(L7="Moderate",2,1))+IF(P7="High Waste",3,IF(P7="Moderate",2,1))+IF(U7="High Carbon Intensity",3,IF(U7="Moderate Carbon Intensity",2,1))+IF(Q7="Weak Diversion",1,0)+IF(MIN(W7:Y7)<0.95,1,0) -> 8 | AA7: =_xlfn.RANK.EQ(Z7,$Z$2:$Z$11,0) -> 5 | AB7: =IF(Z7>=10,"High Portfolio Priority",IF(Z7>=8,"Medium Portfolio Priority","Lower Portfolio Priority")) -> Medium Portfolio Priority | AC7: =IF(AND(F7="Above Benchmark",U7="High Carbon Intensity",P7="High Waste",Q7="Weak Diversion"),"Comprehensive audit: energy, carbon, and waste/diversion",IF(AND(F7="Above Benchmark",U7="High Carbon Intensity"),"Energy and carbon retrofit focus",IF(AND(P7="High Waste",Q7="Weak Diversion"),"Waste audit + recycling/diversion program",IF(L7="High Water Use","Water audit + leak detection + fixture review","Maintain performance + monitor KPIs")))) -> Waste audit + recycling/diversion program | AD7: =IF(OR(F7="Above Benchmark",F7="High Energy Use"),1,0)+IF(L7="High Water Use",1,0)+IF(P7="High Waste",1,0)+IF(Q7="Weak Diversion",1,0)+IF(U7="High Carbon Intensity",1,0) -> 2 | AE7: =IF(AND(F7="Above Benchmark",U7="High Carbon Intensity"),"Energy + Carbon",IF(AND(P7="High Waste",Q7="Weak Diversion"),"Waste + Diversion",IF(F7="Above Benchmark","Energy",IF(U7="High Carbon Intensity","Carbon",IF(L7="High Water Use","Water","Monitor"))))) -> Waste + Diversion
A8: WI-MF-05 | B8: =_xlfn.XLOOKUP(A8,'01_input_asset_master'!A$2:A$11,'01_input_asset_master'!B$2:B$11) -> Oak Street Lofts | C8: =_xlfn.XLOOKUP(A8,'01_input_asset_master'!A$2:A$11,'01_input_asset_master'!H$2:H$11) -> 98000 | D8: =_xlfn.XLOOKUP(A8,'01_input_asset_master'!A$2:A$11,'01_input_asset_master'!I$2:I$11) -> 105 | E8: =_xlfn.XLOOKUP($A8,'11_calc_energy_summary'!$A$2:$A$11,'11_calc_energy_summary'!$M$2:$M$11) -> 48.199449 | F8: =_xlfn.XLOOKUP($A8,'11_calc_energy_summary'!$A$2:$A$11,'11_calc_energy_summary'!$V$2:$V$11) -> At/Below Benchmark | G8: =_xlfn.XLOOKUP(A8,'11_calc_energy_summary'!A$2:A$11,'11_calc_energy_summary'!P$2:P$11) -> 1152.31 | H8: =_xlfn.RANK.EQ(E8,$E$2:$E$11,0) -> 9 | I8: =_xlfn.XLOOKUP(A8,'12_calc_water_summary'!A$2:A$11,'12_calc_water_summary'!E$2:E$11) -> 20938.79 | J8: =_xlfn.XLOOKUP($A8,'12_calc_water_summary'!$A$2:$A$11,'12_calc_water_summary'!$J$2:$J$11) -> 199.41705 | K8: =_xlfn.XLOOKUP(A8,'12_calc_water_summary'!A$2:A$11,'12_calc_water_summary'!K$2:K$11) -> 484.29848 | L8: =_xlfn.XLOOKUP($A8,'12_calc_water_summary'!$A$2:$A$11,'12_calc_water_summary'!$O$2:$O$11) -> Efficient/Low | M8: =_xlfn.XLOOKUP(A8,'13_calc_waste_summary'!A$2:A$11,'13_calc_waste_summary'!H$2:H$11) -> 86.88 | N8: =_xlfn.XLOOKUP($A8,'13_calc_waste_summary'!$A$2:$A$11,'13_calc_waste_summary'!$L$2:$L$11) -> 0.82742857 | O8: =_xlfn.XLOOKUP($A8,'13_calc_waste_summary'!$A$2:$A$11,'13_calc_waste_summary'!$K$2:$K$11) -> 0.27808471 | P8: =_xlfn.XLOOKUP(A8,'13_calc_waste_summary'!A$2:A$11,'13_calc_waste_summary'!R$2:R$11) -> High Waste | Q8: =_xlfn.XLOOKUP(A8,'13_calc_waste_summary'!A$2:A$11,'13_calc_waste_summary'!S$2:S$11) -> Weak Diversion | R8: =_xlfn.XLOOKUP(A8,'14_calc_emissions_summary'!A$2:A$11,'14_calc_emissions_summary'!K$2:K$11) -> 473.50152 | S8: =_xlfn.XLOOKUP($A8,'14_calc_emissions_summary'!$A$2:$A$11,'14_calc_emissions_summary'!$L$2:$L$11) -> 4.8316482 | T8: =_xlfn.XLOOKUP(A8,'14_calc_emissions_summary'!A$2:A$11,'14_calc_emissions_summary'!M$2:M$11) -> 4.5095383 | U8: =_xlfn.XLOOKUP($A8,'14_calc_emissions_summary'!$A$2:$A$11,'14_calc_emissions_summary'!$P$2:$P$11) -> Lower Carbon Intensity | V8: =_xlfn.XLOOKUP(A8,'14_calc_emissions_summary'!A$2:A$11,'14_calc_emissions_summary'!Q$2:Q$11) -> 9 | W8: =_xlfn.XLOOKUP($A8,'11_calc_energy_summary'!$A$2:$A$11,'11_calc_energy_summary'!$S$2:$S$11) -> 1 | X8: =_xlfn.XLOOKUP(A8,'12_calc_water_summary'!A$2:A$11,'12_calc_water_summary'!N$2:N$11) -> 1 | Y8: =_xlfn.XLOOKUP(A8,'13_calc_waste_summary'!A$2:A$11,'13_calc_waste_summary'!Q$2:Q$11) -> 1 | Z8: =IF(F8="High Energy Use",3,IF(F8="Above Benchmark",2,1))+IF(L8="High Water Use",3,IF(L8="Moderate",2,1))+IF(P8="High Waste",3,IF(P8="Moderate",2,1))+IF(U8="High Carbon Intensity",3,IF(U8="Moderate Carbon Intensity",2,1))+IF(Q8="Weak Diversion",1,0)+IF(MIN(W8:Y8)<0.95,1,0) -> 7 | AA8: =_xlfn.RANK.EQ(Z8,$Z$2:$Z$11,0) -> 7 | AB8: =IF(Z8>=10,"High Portfolio Priority",IF(Z8>=8,"Medium Portfolio Priority","Lower Portfolio Priority")) -> Lower Portfolio Priority | AC8: =IF(AND(F8="Above Benchmark",U8="High Carbon Intensity",P8="High Waste",Q8="Weak Diversion"),"Comprehensive audit: energy, carbon, and waste/diversion",IF(AND(F8="Above Benchmark",U8="High Carbon Intensity"),"Energy and carbon retrofit focus",IF(AND(P8="High Waste",Q8="Weak Diversion"),"Waste audit + recycling/diversion program",IF(L8="High Water Use","Water audit + leak detection + fixture review","Maintain performance + monitor KPIs")))) -> Waste audit + recycling/diversion program | AD8: =IF(OR(F8="Above Benchmark",F8="High Energy Use"),1,0)+IF(L8="High Water Use",1,0)+IF(P8="High Waste",1,0)+IF(Q8="Weak Diversion",1,0)+IF(U8="High Carbon Intensity",1,0) -> 2 | AE8: =IF(AND(F8="Above Benchmark",U8="High Carbon Intensity"),"Energy + Carbon",IF(AND(P8="High Waste",Q8="Weak Diversion"),"Waste + Diversion",IF(F8="Above Benchmark","Energy",IF(U8="High Carbon Intensity","Carbon",IF(L8="High Water Use","Water","Monitor"))))) -> Waste + Diversion
A9: WI-MF-07 | B9: =_xlfn.XLOOKUP(A9,'01_input_asset_master'!A$2:A$11,'01_input_asset_master'!B$2:B$11) -> Fox River Flats | C9: =_xlfn.XLOOKUP(A9,'01_input_asset_master'!A$2:A$11,'01_input_asset_master'!H$2:H$11) -> 135000 | D9: =_xlfn.XLOOKUP(A9,'01_input_asset_master'!A$2:A$11,'01_input_asset_master'!I$2:I$11) -> 150 | E9: =_xlfn.XLOOKUP($A9,'11_calc_energy_summary'!$A$2:$A$11,'11_calc_energy_summary'!$M$2:$M$11) -> 51.800011 | F9: =_xlfn.XLOOKUP($A9,'11_calc_energy_summary'!$A$2:$A$11,'11_calc_energy_summary'!$V$2:$V$11) -> At/Below Benchmark | G9: =_xlfn.XLOOKUP(A9,'11_calc_energy_summary'!A$2:A$11,'11_calc_energy_summary'!P$2:P$11) -> 1163.3187 | H9: =_xlfn.RANK.EQ(E9,$E$2:$E$11,0) -> 8 | I9: =_xlfn.XLOOKUP(A9,'12_calc_water_summary'!A$2:A$11,'12_calc_water_summary'!E$2:E$11) -> 31331.91 | J9: =_xlfn.XLOOKUP($A9,'12_calc_water_summary'!$A$2:$A$11,'12_calc_water_summary'!$J$2:$J$11) -> 208.8794 | K9: =_xlfn.XLOOKUP(A9,'12_calc_water_summary'!A$2:A$11,'12_calc_water_summary'!K$2:K$11) -> 507.2784 | L9: =_xlfn.XLOOKUP($A9,'12_calc_water_summary'!$A$2:$A$11,'12_calc_water_summary'!$O$2:$O$11) -> Efficient/Low | M9: =_xlfn.XLOOKUP(A9,'13_calc_waste_summary'!A$2:A$11,'13_calc_waste_summary'!H$2:H$11) -> 119.42 | N9: =_xlfn.XLOOKUP($A9,'13_calc_waste_summary'!$A$2:$A$11,'13_calc_waste_summary'!$L$2:$L$11) -> 0.79613333 | O9: =_xlfn.XLOOKUP($A9,'13_calc_waste_summary'!$A$2:$A$11,'13_calc_waste_summary'!$K$2:$K$11) -> 0.26586836 | P9: =_xlfn.XLOOKUP(A9,'13_calc_waste_summary'!A$2:A$11,'13_calc_waste_summary'!R$2:R$11) -> Moderate | Q9: =_xlfn.XLOOKUP(A9,'13_calc_waste_summary'!A$2:A$11,'13_calc_waste_summary'!S$2:S$11) -> Weak Diversion | R9: =_xlfn.XLOOKUP(A9,'14_calc_emissions_summary'!A$2:A$11,'14_calc_emissions_summary'!K$2:K$11) -> 686.07954 | S9: =_xlfn.XLOOKUP($A9,'14_calc_emissions_summary'!$A$2:$A$11,'14_calc_emissions_summary'!$L$2:$L$11) -> 5.0820706 | T9: =_xlfn.XLOOKUP(A9,'14_calc_emissions_summary'!A$2:A$11,'14_calc_emissions_summary'!M$2:M$11) -> 4.5738636 | U9: =_xlfn.XLOOKUP($A9,'14_calc_emissions_summary'!$A$2:$A$11,'14_calc_emissions_summary'!$P$2:$P$11) -> Moderate Carbon Intensity | V9: =_xlfn.XLOOKUP(A9,'14_calc_emissions_summary'!A$2:A$11,'14_calc_emissions_summary'!Q$2:Q$11) -> 8 | W9: =_xlfn.XLOOKUP($A9,'11_calc_energy_summary'!$A$2:$A$11,'11_calc_energy_summary'!$S$2:$S$11) -> 1 | X9: =_xlfn.XLOOKUP(A9,'12_calc_water_summary'!A$2:A$11,'12_calc_water_summary'!N$2:N$11) -> 1 | Y9: =_xlfn.XLOOKUP(A9,'13_calc_waste_summary'!A$2:A$11,'13_calc_waste_summary'!Q$2:Q$11) -> 1 | Z9: =IF(F9="High Energy Use",3,IF(F9="Above Benchmark",2,1))+IF(L9="High Water Use",3,IF(L9="Moderate",2,1))+IF(P9="High Waste",3,IF(P9="Moderate",2,1))+IF(U9="High Carbon Intensity",3,IF(U9="Moderate Carbon Intensity",2,1))+IF(Q9="Weak Diversion",1,0)+IF(MIN(W9:Y9)<0.95,1,0) -> 7 | AA9: =_xlfn.RANK.EQ(Z9,$Z$2:$Z$11,0) -> 7 | AB9: =IF(Z9>=10,"High Portfolio Priority",IF(Z9>=8,"Medium Portfolio Priority","Lower Portfolio Priority")) -> Lower Portfolio Priority | AC9: =IF(AND(F9="Above Benchmark",U9="High Carbon Intensity",P9="High Waste",Q9="Weak Diversion"),"Comprehensive audit: energy, carbon, and waste/diversion",IF(AND(F9="Above Benchmark",U9="High Carbon Intensity"),"Energy and carbon retrofit focus",IF(AND(P9="High Waste",Q9="Weak Diversion"),"Waste audit + recycling/diversion program",IF(L9="High Water Use","Water audit + leak detection + fixture review","Maintain performance + monitor KPIs")))) -> Maintain performance + monitor KPIs | AD9: =IF(OR(F9="Above Benchmark",F9="High Energy Use"),1,0)+IF(L9="High Water Use",1,0)+IF(P9="High Waste",1,0)+IF(Q9="Weak Diversion",1,0)+IF(U9="High Carbon Intensity",1,0) -> 1 | AE9: =IF(AND(F9="Above Benchmark",U9="High Carbon Intensity"),"Energy + Carbon",IF(AND(P9="High Waste",Q9="Weak Diversion"),"Waste + Diversion",IF(F9="Above Benchmark","Energy",IF(U9="High Carbon Intensity","Carbon",IF(L9="High Water Use","Water","Monitor"))))) -> Monitor
A10: WI-MF-08 | B10: =_xlfn.XLOOKUP(A10,'01_input_asset_master'!A$2:A$11,'01_input_asset_master'!B$2:B$11) -> Prairie View Residences | C10: =_xlfn.XLOOKUP(A10,'01_input_asset_master'!A$2:A$11,'01_input_asset_master'!H$2:H$11) -> 110000 | D10: =_xlfn.XLOOKUP(A10,'01_input_asset_master'!A$2:A$11,'01_input_asset_master'!I$2:I$11) -> 120 | E10: =_xlfn.XLOOKUP($A10,'11_calc_energy_summary'!$A$2:$A$11,'11_calc_energy_summary'!$M$2:$M$11) -> 57.499573 | F10: =_xlfn.XLOOKUP($A10,'11_calc_energy_summary'!$A$2:$A$11,'11_calc_energy_summary'!$V$2:$V$11) -> At/Below Benchmark | G10: =_xlfn.XLOOKUP(A10,'11_calc_energy_summary'!A$2:A$11,'11_calc_energy_summary'!P$2:P$11) -> 1260.4526 | H10: =_xlfn.RANK.EQ(E10,$E$2:$E$11,0) -> 6 | I10: =_xlfn.XLOOKUP(A10,'12_calc_water_summary'!A$2:A$11,'12_calc_water_summary'!E$2:E$11) -> 27447.84 | J10: =_xlfn.XLOOKUP($A10,'12_calc_water_summary'!$A$2:$A$11,'12_calc_water_summary'!$J$2:$J$11) -> 228.732 | K10: =_xlfn.XLOOKUP(A10,'12_calc_water_summary'!A$2:A$11,'12_calc_water_summary'!K$2:K$11) -> 555.49183 | L10: =_xlfn.XLOOKUP($A10,'12_calc_water_summary'!$A$2:$A$11,'12_calc_water_summary'!$O$2:$O$11) -> Efficient/Low | M10: =_xlfn.XLOOKUP(A10,'13_calc_waste_summary'!A$2:A$11,'13_calc_waste_summary'!H$2:H$11) -> 92.52 | N10: =_xlfn.XLOOKUP($A10,'13_calc_waste_summary'!$A$2:$A$11,'13_calc_waste_summary'!$L$2:$L$11) -> 0.771 | O10: =_xlfn.XLOOKUP($A10,'13_calc_waste_summary'!$A$2:$A$11,'13_calc_waste_summary'!$K$2:$K$11) -> 0.269131 | P10: =_xlfn.XLOOKUP(A10,'13_calc_waste_summary'!A$2:A$11,'13_calc_waste_summary'!R$2:R$11) -> Moderate | Q10: =_xlfn.XLOOKUP(A10,'13_calc_waste_summary'!A$2:A$11,'13_calc_waste_summary'!S$2:S$11) -> Weak Diversion | R10: =_xlfn.XLOOKUP(A10,'14_calc_emissions_summary'!A$2:A$11,'14_calc_emissions_summary'!K$2:K$11) -> 599.34 | S10: =_xlfn.XLOOKUP($A10,'14_calc_emissions_summary'!$A$2:$A$11,'14_calc_emissions_summary'!$L$2:$L$11) -> 5.4485455 | T10: =_xlfn.XLOOKUP(A10,'14_calc_emissions_summary'!A$2:A$11,'14_calc_emissions_summary'!M$2:M$11) -> 4.9945 | U10: =_xlfn.XLOOKUP($A10,'14_calc_emissions_summary'!$A$2:$A$11,'14_calc_emissions_summary'!$P$2:$P$11) -> Moderate Carbon Intensity | V10: =_xlfn.XLOOKUP(A10,'14_calc_emissions_summary'!A$2:A$11,'14_calc_emissions_summary'!Q$2:Q$11) -> 6 | W10: =_xlfn.XLOOKUP($A10,'11_calc_energy_summary'!$A$2:$A$11,'11_calc_energy_summary'!$S$2:$S$11) -> 1 | X10: =_xlfn.XLOOKUP(A10,'12_calc_water_summary'!A$2:A$11,'12_calc_water_summary'!N$2:N$11) -> 1 | Y10: =_xlfn.XLOOKUP(A10,'13_calc_waste_summary'!A$2:A$11,'13_calc_waste_summary'!Q$2:Q$11) -> 1 | Z10: =IF(F10="High Energy Use",3,IF(F10="Above Benchmark",2,1))+IF(L10="High Water Use",3,IF(L10="Moderate",2,1))+IF(P10="High Waste",3,IF(P10="Moderate",2,1))+IF(U10="High Carbon Intensity",3,IF(U10="Moderate Carbon Intensity",2,1))+IF(Q10="Weak Diversion",1,0)+IF(MIN(W10:Y10)<0.95,1,0) -> 7 | AA10: =_xlfn.RANK.EQ(Z10,$Z$2:$Z$11,0) -> 7 | AB10: =IF(Z10>=10,"High Portfolio Priority",IF(Z10>=8,"Medium Portfolio Priority","Lower Portfolio Priority")) -> Lower Portfolio Priority | AC10: =IF(AND(F10="Above Benchmark",U10="High Carbon Intensity",P10="High Waste",Q10="Weak Diversion"),"Comprehensive audit: energy, carbon, and waste/diversion",IF(AND(F10="Above Benchmark",U10="High Carbon Intensity"),"Energy and carbon retrofit focus",IF(AND(P10="High Waste",Q10="Weak Diversion"),"Waste audit + recycling/diversion program",IF(L10="High Water Use","Water audit + leak detection + fixture review","Maintain performance + monitor KPIs")))) -> Maintain performance + monitor KPIs | AD10: =IF(OR(F10="Above Benchmark",F10="High Energy Use"),1,0)+IF(L10="High Water Use",1,0)+IF(P10="High Waste",1,0)+IF(Q10="Weak Diversion",1,0)+IF(U10="High Carbon Intensity",1,0) -> 1 | AE10: =IF(AND(F10="Above Benchmark",U10="High Carbon Intensity"),"Energy + Carbon",IF(AND(P10="High Waste",Q10="Weak Diversion"),"Waste + Diversion",IF(F10="Above Benchmark","Energy",IF(U10="High Carbon Intensity","Carbon",IF(L10="High Water Use","Water","Monitor"))))) -> Monitor
A11: WI-MF-09 | B11: =_xlfn.XLOOKUP(A11,'01_input_asset_master'!A$2:A$11,'01_input_asset_master'!B$2:B$11) -> Capitol Square Homes | C11: =_xlfn.XLOOKUP(A11,'01_input_asset_master'!A$2:A$11,'01_input_asset_master'!H$2:H$11) -> 175000 | D11: =_xlfn.XLOOKUP(A11,'01_input_asset_master'!A$2:A$11,'01_input_asset_master'!I$2:I$11) -> 190 | E11: =_xlfn.XLOOKUP($A11,'11_calc_energy_summary'!$A$2:$A$11,'11_calc_energy_summary'!$M$2:$M$11) -> 46.999578 | F11: =_xlfn.XLOOKUP($A11,'11_calc_energy_summary'!$A$2:$A$11,'11_calc_energy_summary'!$V$2:$V$11) -> At/Below Benchmark | G11: =_xlfn.XLOOKUP(A11,'11_calc_energy_summary'!A$2:A$11,'11_calc_energy_summary'!P$2:P$11) -> 1137.4734 | H11: =_xlfn.RANK.EQ(E11,$E$2:$E$11,0) -> 10 | I11: =_xlfn.XLOOKUP(A11,'12_calc_water_summary'!A$2:A$11,'12_calc_water_summary'!E$2:E$11) -> 38401.79 | J11: =_xlfn.XLOOKUP($A11,'12_calc_water_summary'!$A$2:$A$11,'12_calc_water_summary'!$J$2:$J$11) -> 202.11468 | K11: =_xlfn.XLOOKUP(A11,'12_calc_water_summary'!A$2:A$11,'12_calc_water_summary'!K$2:K$11) -> 490.84989 | L11: =_xlfn.XLOOKUP($A11,'12_calc_water_summary'!$A$2:$A$11,'12_calc_water_summary'!$O$2:$O$11) -> Efficient/Low | M11: =_xlfn.XLOOKUP(A11,'13_calc_waste_summary'!A$2:A$11,'13_calc_waste_summary'!H$2:H$11) -> 157.88 | N11: =_xlfn.XLOOKUP($A11,'13_calc_waste_summary'!$A$2:$A$11,'13_calc_waste_summary'!$L$2:$L$11) -> 0.83094737 | O11: =_xlfn.XLOOKUP($A11,'13_calc_waste_summary'!$A$2:$A$11,'13_calc_waste_summary'!$K$2:$K$11) -> 0.33278439 | P11: =_xlfn.XLOOKUP(A11,'13_calc_waste_summary'!A$2:A$11,'13_calc_waste_summary'!R$2:R$11) -> High Waste | Q11: =_xlfn.XLOOKUP(A11,'13_calc_waste_summary'!A$2:A$11,'13_calc_waste_summary'!S$2:S$11) -> Moderate Diversion | R11: =_xlfn.XLOOKUP(A11,'14_calc_emissions_summary'!A$2:A$11,'14_calc_emissions_summary'!K$2:K$11) -> 842.03311 | S11: =_xlfn.XLOOKUP($A11,'14_calc_emissions_summary'!$A$2:$A$11,'14_calc_emissions_summary'!$L$2:$L$11) -> 4.8116177 | T11: =_xlfn.XLOOKUP(A11,'14_calc_emissions_summary'!A$2:A$11,'14_calc_emissions_summary'!M$2:M$11) -> 4.4317532 | U11: =_xlfn.XLOOKUP($A11,'14_calc_emissions_summary'!$A$2:$A$11,'14_calc_emissions_summary'!$P$2:$P$11) -> Lower Carbon Intensity | V11: =_xlfn.XLOOKUP(A11,'14_calc_emissions_summary'!A$2:A$11,'14_calc_emissions_summary'!Q$2:Q$11) -> 10 | W11: =_xlfn.XLOOKUP($A11,'11_calc_energy_summary'!$A$2:$A$11,'11_calc_energy_summary'!$S$2:$S$11) -> 1 | X11: =_xlfn.XLOOKUP(A11,'12_calc_water_summary'!A$2:A$11,'12_calc_water_summary'!N$2:N$11) -> 1 | Y11: =_xlfn.XLOOKUP(A11,'13_calc_waste_summary'!A$2:A$11,'13_calc_waste_summary'!Q$2:Q$11) -> 1 | Z11: =IF(F11="High Energy Use",3,IF(F11="Above Benchmark",2,1))+IF(L11="High Water Use",3,IF(L11="Moderate",2,1))+IF(P11="High Waste",3,IF(P11="Moderate",2,1))+IF(U11="High Carbon Intensity",3,IF(U11="Moderate Carbon Intensity",2,1))+IF(Q11="Weak Diversion",1,0)+IF(MIN(W11:Y11)<0.95,1,0) -> 6 | AA11: =_xlfn.RANK.EQ(Z11,$Z$2:$Z$11,0) -> 10 | AB11: =IF(Z11>=10,"High Portfolio Priority",IF(Z11>=8,"Medium Portfolio Priority","Lower Portfolio Priority")) -> Lower Portfolio Priority | AC11: =IF(AND(F11="Above Benchmark",U11="High Carbon Intensity",P11="High Waste",Q11="Weak Diversion"),"Comprehensive audit: energy, carbon, and waste/diversion",IF(AND(F11="Above Benchmark",U11="High Carbon Intensity"),"Energy and carbon retrofit focus",IF(AND(P11="High Waste",Q11="Weak Diversion"),"Waste audit + recycling/diversion program",IF(L11="High Water Use","Water audit + leak detection + fixture review","Maintain performance + monitor KPIs")))) -> Maintain performance + monitor KPIs | AD11: =IF(OR(F11="Above Benchmark",F11="High Energy Use"),1,0)+IF(L11="High Water Use",1,0)+IF(P11="High Waste",1,0)+IF(Q11="Weak Diversion",1,0)+IF(U11="High Carbon Intensity",1,0) -> 1 | AE11: =IF(AND(F11="Above Benchmark",U11="High Carbon Intensity"),"Energy + Carbon",IF(AND(P11="High Waste",Q11="Weak Diversion"),"Waste + Diversion",IF(F11="Above Benchmark","Energy",IF(U11="High Carbon Intensity","Carbon",IF(L11="High Water Use","Water","Monitor"))))) -> Monitor

Sheet 18_output_executive_summary
A1: metric | B1: portfolio_result | C1: management_interpretation
A2: Highest integrated priority | B2: Lakeview Terrace; South Park Apartments | C2: First assets for comprehensive audit
A3: Main portfolio-wide weakness | B3: Waste diversion | C3: Most properties show weak diversion below 30% | F3: This screening analysis shows that the portfolio does not have a major data-coverage problem; it has an implementation-priority problem. Energy and carbon concerns are concentrated in a few assets, especially Lakeview Terrace and South Park Apartments. Waste diversion, however, is a portfolio-wide weakness. The recommended strategy is to start with comprehensive audits for the top two properties while also launching a portfolio-wide waste-diversion program.
A4: Highest energy priority | B4: South Park Apartments | C4: Highest Site EUI at 67.70 kBtu/sqft
A5: Highest carbon priority | B5: South Park Apartments | C5: Highest carbon intensity at 6.21 kg CO₂e/sqft
A6: Second carbon priority | B6: Lakeview Terrace | C6: High carbon intensity at 6.07 kg CO₂e/sqft
A7: Highest waste per unit | B7: South Park Apartments | C7: Highest waste generation at 0.853 tons/unit
A8: Water performance | B8: Efficient/Low across all properties | C8: Water is not the main intervention area in this screening
A9: Data coverage | B9: 100% for energy, water, and waste | C9: Data is complete enough for screening-level decision-making
A10: First recommended action | B10: Comprehensive audit for WI-MF-02 and WI-MF-06 | C10: Combine energy, carbon, and waste/diversion review
A11: Portfolio program recommendation | B11: Waste-diversion improvement program | C11: Recycling access, tenant education, contamination review, and vendor coordination

Sheet 07_input_community_acs
A1: property_id | B1: property_name | C1: city | D1: county | E1: state | F1: geoid_county | G1: geography_level | H1: median_household_income_usd_2020_2024 | I1: poverty_rate | J1: owner_occupied_rate | K1: renter_occupied_rate | L1: population_under_5_pct | M1: population_over_65_pct | N1: language_other_than_english_pct | O1: median_gross_rent_usd | P1: rent_burden_rate | Q1: rent_burden_note | R1: social_vulnerability_flag | S1: income_vs_wi_median_flag | T1: source_year | U1: source_name | V1: source_url
A2: WI-MF-01 | B2: Riverbend Apartments | C2: Madison | D2: Dane | E2: WI | F2: 55025 | G2: County | H2: 89975 | I2: 0.099 | J2: 0.571 | K2: 0.429 | L2: 0.047 | M2: 0.169 | N2: 0.115 | O2: 1398 | Q2: Not available in QuickFacts. Pull from ACS B25070/B25091 by census tract or county for true cost-burden rate. | R2: Moderate concern | S2: At/above WI median | T2: 2020-2024 ACS 5-year / QuickFacts V2025 | U2: U.S. Census Bureau QuickFacts | V2: https://www.census.gov/quickfacts/fact/table/danecountywisconsin/PST045225
A3: WI-MF-02 | B3: Lakeview Terrace | C3: Milwaukee | D3: Milwaukee | E3: WI | F3: 55079 | G3: County | H3: 64435 | I3: 0.168 | J3: 0.499 | K3: 0.501 | L3: 0.061 | M3: 0.162 | N3: 0.186 | O3: 1101 | Q3: Not available in QuickFacts. Pull from ACS B25070/B25091 by census tract or county for true cost-burden rate. | R3: Higher concern | S3: Below WI median | T3: 2020-2024 ACS 5-year / QuickFacts V2025 | U3: U.S. Census Bureau QuickFacts | V3: https://www.census.gov/quickfacts/fact/table/milwaukeecountywisconsin/INC110224
A4: WI-MF-03 | B4: Northside Commons | C4: Green Bay | D4: Brown | E4: WI | F4: 55009 | G4: County | H4: 79649 | I4: 0.082 | J4: 0.66 | K4: 0.34 | L4: 0.054 | M4: 0.184 | N4: 0.102 | O4: 1031 | Q4: Not available in QuickFacts. Pull from ACS B25070/B25091 by census tract or county for true cost-burden rate. | R4: Moderate concern | S4: At/above WI median | T4: 2020-2024 ACS 5-year / QuickFacts V2025 | U4: U.S. Census Bureau QuickFacts | V4: https://www.census.gov/quickfacts/fact/table/browncountywisconsin/POP060210
A5: WI-MF-04 | B5: Badger Ridge Homes | C5: Wausau | D5: Marathon | E5: WI | F5: 55073 | G5: County | H5: 77884 | I5: 0.075 | J5: 0.733 | K5: 0.267 | L5: 0.052 | M5: 0.214 | N5: 0.076 | O5: 999 | Q5: Not available in QuickFacts. Pull from ACS B25070/B25091 by census tract or county for true cost-burden rate. | R5: Lower concern | S5: At/above WI median | T5: 2020-2024 ACS 5-year / QuickFacts V2025 | U5: U.S. Census Bureau QuickFacts | V5: https://www.census.gov/quickfacts/fact/table/marathoncountywisconsin/PST040225
A6: WI-MF-05 | B6: Oak Street Lofts | C6: Eau Claire | D6: Eau Claire | E6: WI | F6: 55035 | G6: County | H6: 74546 | I6: 0.108 | J6: 0.61 | K6: 0.39 | L6: 0.046 | M6: 0.189 | N6: 0.067 | O6: 1064 | Q6: Not available in QuickFacts. Pull from ACS B25070/B25091 by census tract or county for true cost-burden rate. | R6: Moderate concern | S6: Below WI median | T6: 2020-2024 ACS 5-year / QuickFacts V2025 | U6: U.S. Census Bureau QuickFacts | V6: https://www.census.gov/quickfacts/fact/table/eauclairecountywisconsin/PST045225
A7: WI-MF-06 | B7: South Park Apartments | C7: Racine | D7: Racine | E7: WI | F7: 55101 | G7: County | H7: 78096 | I7: 0.117 | J7: 0.71 | K7: 0.29 | L7: 0.054 | M7: 0.202 | N7: 0.091 | O7: 1080 | Q7: Not available in QuickFacts. Pull from ACS B25070/B25091 by census tract or county for true cost-burden rate. | R7: Moderate concern | S7: At/above WI median | T7: 2020-2024 ACS 5-year / QuickFacts V2025 | U7: U.S. Census Bureau QuickFacts | V7: https://www.census.gov/quickfacts/fact/table/racinecountywisconsin/BZA010223
A8: WI-MF-07 | B8: Fox River Flats | C8: Appleton | D8: Outagamie | E8: WI | F8: 55087 | G8: County | H8: 85069 | I8: 0.066 | J8: 0.715 | K8: 0.285 | L8: 0.053 | M8: 0.186 | N8: 0.076 | O8: 1057 | Q8: Not available in QuickFacts. Pull from ACS B25070/B25091 by census tract or county for true cost-burden rate. | R8: Lower concern | S8: At/above WI median | T8: 2020-2024 ACS 5-year / QuickFacts V2025 | U8: U.S. Census Bureau QuickFacts | V8: https://www.census.gov/quickfacts/fact/table/outagamiecountywisconsin/LND110210
A9: WI-MF-08 | B9: Prairie View Residences | C9: La Crosse | D9: La Crosse | E9: WI | F9: 55063 | G9: County | H9: 73013 | I9: 0.113 | J9: 0.622 | K9: 0.378 | L9: 0.045 | M9: 0.203 | N9: 0.067 | O9: 1059 | Q9: Not available in QuickFacts. Pull from ACS B25070/B25091 by census tract or county for true cost-burden rate. | R9: Moderate concern | S9: Below WI median | T9: 2020-2024 ACS 5-year / QuickFacts V2025 | U9: U.S. Census Bureau QuickFacts | V9: https://www.census.gov/quickfacts/fact/table/lacrossecountywisconsin/PST045225
A10: WI-MF-09 | B10: Capitol Square Homes | C10: Madison | D10: Dane | E10: WI | F10: 55025 | G10: County | H10: 89975 | I10: 0.099 | J10: 0.571 | K10: 0.429 | L10: 0.047 | M10: 0.169 | N10: 0.115 | O10: 1398 | Q10: Not available in QuickFacts. Pull from ACS B25070/B25091 by census tract or county for true cost-burden rate. | R10: Moderate concern | S10: At/above WI median | T10: 2020-2024 ACS 5-year / QuickFacts V2025 | U10: U.S. Census Bureau QuickFacts | V10: https://www.census.gov/quickfacts/fact/table/danecountywisconsin/PST045225
A11: WI-MF-10 | B11: Harbor Point Apartments | C11: Kenosha | D11: Kenosha | E11: WI | F11: 55059 | G11: County | H11: 81239 | I11: 0.098 | J11: 0.667 | K11: 0.333 | L11: 0.05 | M11: 0.184 | N11: 0.131 | O11: 1219 | Q11: Not available in QuickFacts. Pull from ACS B25070/B25091 by census tract or county for true cost-burden rate. | R11: Moderate concern | S11: At/above WI median | T11: 2020-2024 ACS 5-year / QuickFacts V2025 | U11: U.S. Census Bureau QuickFacts | V11: https://www.census.gov/quickfacts/fact/table/kenoshacountywisconsin/PST045225

Sheet 08_input_climate_risk_fema
A1: property_id | B1: property_name | C1: city | D1: county | E1: state | F1: overall_risk_score_0_100 | G1: overall_risk_rating | H1: national_percentile | I1: expected_annual_loss_musd | J1: social_vulnerability_rating | K1: community_resilience_rating | L1: top_hazard_1 | M1: top_hazard_1_rating | N1: top_hazard_2 | O1: top_hazard_2_rating | P1: top_hazard_3 | Q1: top_hazard_3_rating | R1: data_granularity | S1: source_year_version | T1: source_name | U1: source_url | V1: notes
A2: WI-MF-01 | B2: Riverbend Apartments | C2: Madison | D2: Dane | E2: WI | F2: 93.9 | G2: Medium | H2: 94 | I2: 182 | J2: Not pulled | K2: Not pulled | L2: Cold Wave | M2: High | N2: Hail | O2: High | P2: Not pulled | Q2: Not pulled | R2: County | S2: FEMA NRI v1.20 / December 2025 | T2: DisasterRiskIndex.com using FEMA NRI / OpenFEMA | U2: https://disasterriskindex.com/wisconsin/dane | V2: County-level FEMA National Risk Index data; not address-specific. Use property coordinates/tract data for real diligence.
A3: WI-MF-02 | B3: Lakeview Terrace | C3: Milwaukee | D3: Milwaukee | E3: WI | F3: 98.4 | G3: High | H3: 98 | I3: 342 | J3: High | K3: Very High | L3: Cold Wave | M3: Very High | N3: Heat Wave | O3: High | P3: Tornado | Q3: Very High | R3: County | S3: FEMA NRI v1.20 / December 2025 | T3: DisasterRiskIndex.com using FEMA NRI / OpenFEMA | U3: https://disasterriskindex.com/wisconsin/milwaukee | V3: County-level FEMA National Risk Index data; not address-specific. Use property coordinates/tract data for real diligence.
A4: WI-MF-03 | B4: Northside Commons | C4: Green Bay | D4: Brown | E4: WI | F4: 90.0 | G4: Medium | H4: 90 | J4: Not pulled | K4: Not pulled | L4: Cold Wave | M4: High | N4: Hail | O4: High | P4: Lightning | Q4: High | R4: County | S4: FEMA NRI v1.20 / December 2025 | T4: DisasterRiskIndex.com using FEMA NRI / OpenFEMA | U4: https://disasterriskindex.com/wisconsin/brown | V4: County-level FEMA National Risk Index data; not address-specific. Use property coordinates/tract data for real diligence.
A5: WI-MF-04 | B5: Badger Ridge Homes | C5: Wausau | D5: Marathon | E5: WI | F5: 87.2 | G5: Medium | H5: 87 | J5: Not pulled | K5: Not pulled | L5: Not pulled | M5: Not pulled | N5: Not pulled | O5: Not pulled | P5: Not pulled | Q5: Not pulled | R5: County | S5: FEMA NRI v1.20 / December 2025 | T5: DisasterRiskIndex.com using FEMA NRI / OpenFEMA | U5: https://disasterriskindex.com/wisconsin/marathon | V5: County-level FEMA National Risk Index data; not address-specific. Use property coordinates/tract data for real diligence.
A6: WI-MF-05 | B6: Oak Street Lofts | C6: Eau Claire | D6: Eau Claire | E6: WI | F6: 78.3 | G6: Low | H6: 78 | J6: Not pulled | K6: Not pulled | L6: Not pulled | M6: Not pulled | N6: Not pulled | O6: Not pulled | P6: Not pulled | Q6: Not pulled | R6: County | S6: FEMA NRI v1.20 / December 2025 | T6: DisasterRiskIndex.com using FEMA NRI / OpenFEMA | U6: https://disasterriskindex.com/wisconsin/eau-claire | V6: County-level FEMA National Risk Index data; not address-specific. Use property coordinates/tract data for real diligence.
A7: WI-MF-06 | B7: South Park Apartments | C7: Racine | D7: Racine | E7: WI | F7: 85.4 | G7: Medium | H7: 85 | I7: 64 | J7: Low | K7: Very High | L7: Cold Wave | M7: High | N7: Tornado | O7: High | P7: Hail | Q7: Medium | R7: County | S7: FEMA NRI v1.20 / December 2025 | T7: DisasterRiskIndex.com using FEMA NRI / OpenFEMA | U7: https://disasterriskindex.com/wisconsin/racine | V7: County-level FEMA National Risk Index data; not address-specific. Use property coordinates/tract data for real diligence.
A8: WI-MF-07 | B8: Fox River Flats | C8: Appleton | D8: Outagamie | E8: WI | F8: 79.7 | G8: Low | H8: 80 | J8: Not pulled | K8: Not pulled | L8: Cold Wave | M8: High | N8: Hail | O8: Medium | P8: Lightning | Q8: High | R8: County | S8: FEMA NRI v1.20 / December 2025 | T8: DisasterRiskIndex.com using FEMA NRI / OpenFEMA | U8: https://disasterriskindex.com/wisconsin/outagamie | V8: County-level FEMA National Risk Index data; not address-specific. Use property coordinates/tract data for real diligence.
A9: WI-MF-08 | B9: Prairie View Residences | C9: La Crosse | D9: La Crosse | E9: WI | F9: 80.5 | G9: Low | H9: 81 | I9: 54 | J9: Very Low | K9: Very High | L9: Cold Wave | M9: High | N9: Hail | O9: High | P9: Landslide | Q9: Medium | R9: County | S9: FEMA NRI v1.20 / December 2025 | T9: DisasterRiskIndex.com using FEMA NRI / OpenFEMA | U9: https://disasterriskindex.com/wisconsin/la-crosse | V9: County-level FEMA National Risk Index data; not address-specific. Use property coordinates/tract data for real diligence.
A10: WI-MF-09 | B10: Capitol Square Homes | C10: Madison | D10: Dane | E10: WI | F10: 93.9 | G10: Medium | H10: 94 | I10: 182 | J10: Not pulled | K10: Not pulled | L10: Cold Wave | M10: High | N10: Hail | O10: High | P10: Not pulled | Q10: Not pulled | R10: County | S10: FEMA NRI v1.20 / December 2025 | T10: DisasterRiskIndex.com using FEMA NRI / OpenFEMA | U10: https://disasterriskindex.com/wisconsin/dane | V10: County-level FEMA National Risk Index data; not address-specific. Use property coordinates/tract data for real diligence.
A11: WI-MF-10 | B11: Harbor Point Apartments | C11: Kenosha | D11: Kenosha | E11: WI | F11: 85.0 | G11: Medium | H11: 85 | I11: 64 | J11: Low | K11: Very High | L11: Cold Wave | M11: High | N11: Lightning | O11: High | P11: Tornado | Q11: High | R11: County | S11: FEMA NRI v1.20 / December 2025 | T11: DisasterRiskIndex.com using FEMA NRI / OpenFEMA | U11: https://disasterriskindex.com/wisconsin/kenosha | V11: County-level FEMA National Risk Index data; not address-specific. Use property coordinates/tract data for real diligence.

Sheet 09_input_ej_cejst
A1: property_id | B1: property_name | C1: city | D1: county | E1: state | F1: address_or_latlong_status | G1: census_tract_status | H1: cejst_disadvantaged_proxy | I1: energy_burden_flag_proxy | J1: housing_burden_flag_proxy | K1: legacy_pollution_flag_proxy | L1: transportation_barrier_flag_proxy | M1: water_wastewater_flag_proxy | N1: low_income_flag_proxy | O1: tribal_or_rural_context_flag | P1: priority_lidac_screen | Q1: data_confidence | R1: recommended_next_step | S1: source_urls | T1: notes
A2: WI-MF-01 | B2: Riverbend Apartments | C2: Madison | D2: Dane | E2: WI | F2: Address/lat-long needed | G2: Census tract needed | H2: Not indicated by proxy / needs tract confirmation | I2: No/Unknown | J2: No/Unknown | K2: No/Unknown | L2: No/Unknown | M2: No/Unknown | N2: No/Unknown | O2: No/Unknown | P2: Low | Q2: Low - proxy only | R2: Geocode property address, join to CEJST Version 2.0 tract data, then replace proxy flags with official tract-level flags. | S2: https://public-environmental-data-partners.github.io/j40-cejst-2/en/ ; https://datacatalog.urban.org/dataset/climate-and-economic-justice-screening-tool-data ; https://arcgis.netl.doe.gov/portal/home/item.html?id=a8674b345a7245cab5787e8a0c4dee26 | T2: For GRESB/community-benefit screening only. Do not use as final LIDAC eligibility evidence.
A3: WI-MF-02 | B3: Lakeview Terrace | C3: Milwaukee | D3: Milwaukee | E3: WI | F3: Address/lat-long needed | G3: Census tract needed | H3: Likely / needs tract confirmation | I3: Yes - proxy | J3: Yes - proxy | K3: Review | L3: Review | M3: Review | N3: Yes - proxy | O3: No/Unknown | P3: High | Q3: Low - proxy only | R3: Geocode property address, join to CEJST Version 2.0 tract data, then replace proxy flags with official tract-level flags. | S3: https://public-environmental-data-partners.github.io/j40-cejst-2/en/ ; https://datacatalog.urban.org/dataset/climate-and-economic-justice-screening-tool-data ; https://arcgis.netl.doe.gov/portal/home/item.html?id=a8674b345a7245cab5787e8a0c4dee26 | T3: For GRESB/community-benefit screening only. Do not use as final LIDAC eligibility evidence.
A4: WI-MF-03 | B4: Northside Commons | C4: Green Bay | D4: Brown | E4: WI | F4: Address/lat-long needed | G4: Census tract needed | H4: Possible / needs tract confirmation | I4: No/Unknown | J4: Review | K4: Review | L4: Review | M4: No/Unknown | N4: No/Unknown | O4: No/Unknown | P4: Medium | Q4: Low - proxy only | R4: Geocode property address, join to CEJST Version 2.0 tract data, then replace proxy flags with official tract-level flags. | S4: https://public-environmental-data-partners.github.io/j40-cejst-2/en/ ; https://datacatalog.urban.org/dataset/climate-and-economic-justice-screening-tool-data ; https://arcgis.netl.doe.gov/portal/home/item.html?id=a8674b345a7245cab5787e8a0c4dee26 | T4: For GRESB/community-benefit screening only. Do not use as final LIDAC eligibility evidence.
A5: WI-MF-04 | B5: Badger Ridge Homes | C5: Wausau | D5: Marathon | E5: WI | F5: Address/lat-long needed | G5: Census tract needed | H5: Possible / needs tract confirmation | I5: Review | J5: Yes - proxy | K5: No/Unknown | L5: Review | M5: No/Unknown | N5: Review | O5: Rural market screen | P5: Medium | Q5: Low - proxy only | R5: Geocode property address, join to CEJST Version 2.0 tract data, then replace proxy flags with official tract-level flags. | S5: https://public-environmental-data-partners.github.io/j40-cejst-2/en/ ; https://datacatalog.urban.org/dataset/climate-and-economic-justice-screening-tool-data ; https://arcgis.netl.doe.gov/portal/home/item.html?id=a8674b345a7245cab5787e8a0c4dee26 | T5: For GRESB/community-benefit screening only. Do not use as final LIDAC eligibility evidence.
A6: WI-MF-05 | B6: Oak Street Lofts | C6: Eau Claire | D6: Eau Claire | E6: WI | F6: Address/lat-long needed | G6: Census tract needed | H6: Not indicated by proxy / needs tract confirmation | I6: No/Unknown | J6: No/Unknown | K6: No/Unknown | L6: No/Unknown | M6: No/Unknown | N6: No/Unknown | O6: Rural market screen | P6: Low | Q6: Low - proxy only | R6: Geocode property address, join to CEJST Version 2.0 tract data, then replace proxy flags with official tract-level flags. | S6: https://public-environmental-data-partners.github.io/j40-cejst-2/en/ ; https://datacatalog.urban.org/dataset/climate-and-economic-justice-screening-tool-data ; https://arcgis.netl.doe.gov/portal/home/item.html?id=a8674b345a7245cab5787e8a0c4dee26 | T6: For GRESB/community-benefit screening only. Do not use as final LIDAC eligibility evidence.
A7: WI-MF-06 | B7: South Park Apartments | C7: Racine | D7: Racine | E7: WI | F7: Address/lat-long needed | G7: Census tract needed | H7: Likely / needs tract confirmation | I7: Yes - proxy | J7: Yes - proxy | K7: Review | L7: Review | M7: Review | N7: Yes - proxy | O7: No/Unknown | P7: High | Q7: Low - proxy only | R7: Geocode property address, join to CEJST Version 2.0 tract data, then replace proxy flags with official tract-level flags. | S7: https://public-environmental-data-partners.github.io/j40-cejst-2/en/ ; https://datacatalog.urban.org/dataset/climate-and-economic-justice-screening-tool-data ; https://arcgis.netl.doe.gov/portal/home/item.html?id=a8674b345a7245cab5787e8a0c4dee26 | T7: For GRESB/community-benefit screening only. Do not use as final LIDAC eligibility evidence.
A8: WI-MF-07 | B8: Fox River Flats | C8: Appleton | D8: Outagamie | E8: WI | F8: Address/lat-long needed | G8: Census tract needed | H8: Not indicated by proxy / needs tract confirmation | I8: No/Unknown | J8: No/Unknown | K8: No/Unknown | L8: No/Unknown | M8: No/Unknown | N8: No/Unknown | O8: No/Unknown | P8: Low | Q8: Low - proxy only | R8: Geocode property address, join to CEJST Version 2.0 tract data, then replace proxy flags with official tract-level flags. | S8: https://public-environmental-data-partners.github.io/j40-cejst-2/en/ ; https://datacatalog.urban.org/dataset/climate-and-economic-justice-screening-tool-data ; https://arcgis.netl.doe.gov/portal/home/item.html?id=a8674b345a7245cab5787e8a0c4dee26 | T8: For GRESB/community-benefit screening only. Do not use as final LIDAC eligibility evidence.
A9: WI-MF-08 | B9: Prairie View Residences | C9: La Crosse | D9: La Crosse | E9: WI | F9: Address/lat-long needed | G9: Census tract needed | H9: Possible / needs tract confirmation | I9: Review | J9: Yes - proxy | K9: No/Unknown | L9: No/Unknown | M9: Review | N9: Review | O9: Rural market screen | P9: Medium | Q9: Low - proxy only | R9: Geocode property address, join to CEJST Version 2.0 tract data, then replace proxy flags with official tract-level flags. | S9: https://public-environmental-data-partners.github.io/j40-cejst-2/en/ ; https://datacatalog.urban.org/dataset/climate-and-economic-justice-screening-tool-data ; https://arcgis.netl.doe.gov/portal/home/item.html?id=a8674b345a7245cab5787e8a0c4dee26 | T9: For GRESB/community-benefit screening only. Do not use as final LIDAC eligibility evidence.
A10: WI-MF-09 | B10: Capitol Square Homes | C10: Madison | D10: Dane | E10: WI | F10: Address/lat-long needed | G10: Census tract needed | H10: Not indicated by proxy / needs tract confirmation | I10: No/Unknown | J10: No/Unknown | K10: No/Unknown | L10: No/Unknown | M10: No/Unknown | N10: No/Unknown | O10: No/Unknown | P10: Low | Q10: Low - proxy only | R10: Geocode property address, join to CEJST Version 2.0 tract data, then replace proxy flags with official tract-level flags. | S10: https://public-environmental-data-partners.github.io/j40-cejst-2/en/ ; https://datacatalog.urban.org/dataset/climate-and-economic-justice-screening-tool-data ; https://arcgis.netl.doe.gov/portal/home/item.html?id=a8674b345a7245cab5787e8a0c4dee26 | T10: For GRESB/community-benefit screening only. Do not use as final LIDAC eligibility evidence.
A11: WI-MF-10 | B11: Harbor Point Apartments | C11: Kenosha | D11: Kenosha | E11: WI | F11: Address/lat-long needed | G11: Census tract needed | H11: Likely / needs tract confirmation | I11: Yes - proxy | J11: Yes - proxy | K11: Review | L11: Review | M11: Review | N11: Yes - proxy | O11: No/Unknown | P11: High | Q11: Low - proxy only | R11: Geocode property address, join to CEJST Version 2.0 tract data, then replace proxy flags with official tract-level flags. | S11: https://public-environmental-data-partners.github.io/j40-cejst-2/en/ ; https://datacatalog.urban.org/dataset/climate-and-economic-justice-screening-tool-data ; https://arcgis.netl.doe.gov/portal/home/item.html?id=a8674b345a7245cab5787e8a0c4dee26 | T11: For GRESB/community-benefit screening only. Do not use as final LIDAC eligibility evidence.

Sheet 10_input_retrofit_options
A1: property_id | B1: property_name | C1: city | D1: county | E1: measure_id | F1: measure_name | G1: category | H1: capital_cost_usd | I1: eligible_incentive_usd | J1: annual_electricity_savings_kwh | K1: annual_gas_savings_therms | L1: annual_water_savings_gal | M1: annual_cost_savings_usd | N1: useful_life_years | O1: tenant_benefit_score_1_5 | P1: owner_benefit_score_1_5 | Q1: implementation_difficulty | R1: source_basis | S1: data_confidence | T1: notes
A2: WI-MF-01 | B2: Riverbend Apartments | C2: Madison | D2: Dane | E2: WI-MF-01-M01 | F2: LED common-area lighting retrofit | G2: Energy efficiency | H2: 73000 | I2: 8800 | J2: 43551 | K2: 0 | L2: 0 | M2: 6315 | N2: 10 | O2: 2 | P2: 5 | Q2: Low | R2: Focus on Energy Multifamily; Focus on Energy Business Rebates | S2: Screening estimate | T2: Common-area lighting measure; modeled as electricity savings only.
A3: WI-MF-01 | B3: Riverbend Apartments | C3: Madison | D3: Dane | E3: WI-MF-01-M02 | F3: Boiler tune-up and heating controls | G3: Energy efficiency | H3: 49200 | I3: 4900 | J3: 0 | K3: 4783 | L3: 0 | M3: 5261 | N3: 8 | O3: 3 | P3: 5 | Q3: Medium | R3: Focus on Energy Multifamily; Focus on Energy Business Rebates | S3: Screening estimate | T3: Best for older gas-heated multifamily properties; gas savings adjusted by building age.
A4: WI-MF-01 | B4: Riverbend Apartments | C4: Madison | D4: Dane | E4: WI-MF-01-M03 | F4: Smart thermostats / in-unit controls | G4: Energy efficiency / tenant comfort | H4: 87500 | I4: 8800 | J4: 14932 | K4: 2690 | L4: 0 | M4: 5124 | N4: 8 | O4: 5 | P4: 4 | Q4: Medium | R4: Focus on Energy Multifamily; ENERGY STAR Federal Tax Credits | S4: Screening estimate | T4: Improves comfort and energy management; higher tenant benefit.
A5: WI-MF-01 | B5: Riverbend Apartments | C5: Madison | D5: Dane | E5: WI-MF-01-M04 | F5: Low-flow fixtures and aerators | G5: Water efficiency | H5: 58100 | I5: 4600 | J5: 0 | K5: 897 | L5: 1473153 | M5: 11299 | N5: 10 | O5: 4 | P5: 4 | Q5: Low | R5: EPA WaterSense Multifamily; Focus on Energy Multifamily | S5: Screening estimate | T5: Water savings plus small hot-water natural gas savings.
A6: WI-MF-01 | B6: Riverbend Apartments | C6: Madison | D6: Dane | E6: WI-MF-01-M05 | F6: Smart leak detection / water monitoring | G6: Water resilience | H6: 47300 | I6: 2400 | J6: 0 | K6: 0 | L6: 947027 | M6: 6629 | N6: 10 | O6: 4 | P6: 5 | Q6: Medium | R6: EPA WaterSense Multifamily | S6: Screening estimate | T6: Reduces leak losses and supports GRESB data-quality/readiness.
A7: WI-MF-01 | B7: Riverbend Apartments | C7: Madison | D7: Dane | E7: WI-MF-01-M06 | F7: Air sealing and weatherization | G7: Envelope / resilience | H7: 112300 | I7: 11200 | J7: 7466 | K7: 3886 | L7: 0 | M7: 5357 | N7: 15 | O7: 5 | P7: 4 | Q7: Medium | R7: Focus on Energy Multifamily; ENERGY STAR Multifamily Housing | S7: Screening estimate | T7: Improves comfort, winter resilience, and heating efficiency.
A8: WI-MF-01 | B8: Riverbend Apartments | C8: Madison | D8: Dane | E8: WI-MF-01-M07 | F8: Heat pump water heater feasibility / pilot | G8: Electrification | H8: 205000 | I8: 24600 | J8: -43551 | K8: 5979 | L8: 0 | M8: 262 | N8: 12 | O8: 3 | P8: 3 | Q8: High | R8: ENERGY STAR Federal Tax Credits; Focus on Energy Multifamily | S8: Screening estimate | T8: Modeled as gas reduction with added electricity load; requires feasibility review.
A9: WI-MF-01 | B9: Riverbend Apartments | C9: Madison | D9: Dane | E9: WI-MF-01-M08 | F9: Rooftop solar PV feasibility and partial installation | G9: Renewable energy | H9: 187100 | I9: 25000 | J9: 149317 | K9: 0 | L9: 0 | M9: 21651 | N9: 20 | O9: 2 | P9: 4 | Q9: High | R9: Focus on Energy Solar for Homes; ENERGY STAR Federal Tax Credits | S9: Screening estimate | T9: Screening-level PV assumption; verify roof area, ownership, tax appetite, and interconnection.
A10: WI-MF-01 | B10: Riverbend Apartments | C10: Madison | D10: Dane | E10: WI-MF-01-M09 | F10: Waste vendor reporting + recycling engagement | G10: Waste / tenant engagement | H10: 12500 | I10: 0 | J10: 0 | K10: 0 | L10: 0 | M10: 3240 | N10: 3 | O10: 3 | P10: 3 | Q10: Low | R10: EPA WARM; ENERGY STAR Multifamily Housing | S10: Screening estimate | T10: Primary benefit is GRESB readiness, diversion tracking, and tenant engagement; direct utility savings not modeled.
A11: WI-MF-02 | B11: Lakeview Terrace | C11: Milwaukee | D11: Milwaukee | E11: WI-MF-02-M01 | F11: LED common-area lighting retrofit | G11: Energy efficiency | H11: 102100 | I11: 12300 | J11: 62448 | K11: 0 | L11: 0 | M11: 9055 | N11: 10 | O11: 2 | P11: 5 | Q11: Low | R11: Focus on Energy Multifamily; Focus on Energy Business Rebates | S11: Screening estimate | T11: Common-area lighting measure; modeled as electricity savings only.
A12: WI-MF-02 | B12: Lakeview Terrace | C12: Milwaukee | D12: Milwaukee | E12: WI-MF-02-M02 | F12: Boiler tune-up and heating controls | G12: Energy efficiency | H12: 66300 | I12: 6600 | J12: 0 | K12: 8669 | L12: 0 | M12: 9536 | N12: 8 | O12: 3 | P12: 5 | Q12: Medium | R12: Focus on Energy Multifamily; Focus on Energy Business Rebates | S12: Screening estimate | T12: Best for older gas-heated multifamily properties; gas savings adjusted by building age.
... A91: WI-MF-10 | B91: Harbor Point Apartments | C91: Kenosha | D91: Kenosha | E91: WI-MF-10-M09 | F91: Waste vendor reporting + recycling engagement | G91: Waste / tenant engagement | H91: 12700 | I91: 0 | J91: 0 | K91: 0 | L91: 0 | M91: 3150 | N91: 3 | O91: 3 | P91: 3 | Q91: Low | R91: EPA WARM; ENERGY STAR Multifamily Housing | S91: Screening estimate | T91: Primary benefit is GRESB readiness, diversion tracking, and tenant engagement; direct utility savings not modeled.

Sheet 16_calc_retrofit_finance
A1: property_id | B1: property_name | C1: retrofit_measure | D1: issue_addressed | E1: capital_cost_usd | F1: incentive_usd | G1: net_cost_usd | H1: annual_electricity_savings_kwh | I1: annual_gas_savings_therms | J1: annual_water_savings_gallons | K1: annual_waste_savings_usd | L1: annual_energy_cost_savings_usd | M1: annual_water_cost_savings_usd | N1: annual_total_savings_usd | O1: annual_emissions_reduction_tco2e | P1: simple_payback_years | Q1: cost_per_tco2e_reduced | R1: noi_impact_usd | S1: estimated_value_impact_usd | T1: implementation_difficulty | U1: investment_priority | V1: investment_decision | W1: finance_note
A2: WI-MF-02 | B2: Lakeview Terrace | C2: Energy audit | D2: Energy + carbon | E2: 12000 | F2: 0 | G2: =E2-F2 -> 12000 | H2: 0 | I2: 0 | J2: 0 | L2: =(H2*0.145)+(I2*1.1) -> 0 | M2: =J2*0.012 -> 0 | N2: =K2+L2+M2 -> 0 | O2: =((H2*0.527779)+(I2*5.31145))/1000 -> 0 | P2: =IF(N2=0,"No savings",G2/N2) -> No savings | Q2: =IF(O2=0,"No emissions reduction",G2/O2) -> No emissions reduction | R2: =N2 -> 0 | S2: =R2/0.05 -> 0 | T2: Low | U2: =IF(C2="Energy audit","Enabling Step",IF(P2="No savings","Low Priority",IF(AND(P2<=5,O2>10),"High Priority",IF(P2<=8,"Medium Priority","Low Priority")))) -> Enabling Step | V2: =IF(U2="High Priority","Advance to vendor quote / audit scope",IF(U2="Medium Priority","Include in operating improvement plan",IF(U2="Enabling Step","Complete before final capex decision","Monitor or defer"))) -> Complete before final capex decision | W2: =IF(S2>0,"Estimated value impact assumes annual savings are capitalized at a 5% cap rate","No direct value impact estimated") -> No direct value impact estimated | Z2: Electricity efficiency has the strongest financial and carbon case because it produces high annual savings, short payback, and the largest Scope 2 emissions reduction. Boiler/heating review is also attractive because it reduces natural gas use and Scope 1 emissions with a payback under four years. Waste diversion has modest financial value but is still operationally important because weak diversion is a portfolio-wide ESG issue.
A3: WI-MF-02 | B3: Lakeview Terrace | C3: Boiler/heating review | D3: Gas use + carbon | E3: 45000 | F3: 8000 | G3: =E3-F3 -> 37000 | H3: 0 | I3: 9000 | J3: 0 | K3: 0 | L3: =(H3*0.145)+(I3*1.1) -> 9900 | M3: =J3*0.012 -> 0 | N3: =K3+L3+M3 -> 9900 | O3: =((H3*0.527779)+(I3*5.31145))/1000 -> 47.80305 | P3: =IF(N3=0,"No savings",G3/N3) -> 3.7373737 | Q3: =IF(O3=0,"No emissions reduction",G3/O3) -> 774.00919 | R3: =N3 -> 9900 | S3: =R3/0.05 -> 198000 | T3: Medium | U3: =IF(C3="Energy audit","Enabling Step",IF(P3="No savings","Low Priority",IF(AND(P3<=5,O3>10),"High Priority",IF(P3<=8,"Medium Priority","Low Priority")))) -> High Priority | V3: =IF(U3="High Priority","Advance to vendor quote / audit scope",IF(U3="Medium Priority","Include in operating improvement plan",IF(U3="Enabling Step","Complete before final capex decision","Monitor or defer"))) -> Advance to vendor quote / audit scope | W3: =IF(S3>0,"Estimated value impact assumes annual savings are capitalized at a 5% cap rate","No direct value impact estimated") -> Estimated value impact assumes annual savings are capitalized at a 5% cap rate
A4: WI-MF-02 | B4: Lakeview Terrace | C4: Electricity efficiency | D4: Electricity use + Scope 2 | E4: 65000 | F4: 10000 | G4: =E4-F4 -> 55000 | H4: 180000 | I4: 0 | J4: 0 | K4: 0 | L4: =(H4*0.145)+(I4*1.1) -> 26100 | M4: =J4*0.012 -> 0 | N4: =K4+L4+M4 -> 26100 | O4: =((H4*0.527779)+(I4*5.31145))/1000 -> 95.00022 | P4: =IF(N4=0,"No savings",G4/N4) -> 2.1072797 | Q4: =IF(O4=0,"No emissions reduction",G4/O4) -> 578.94603 | R4: =N4 -> 26100 | S4: =R4/0.05 -> 522000 | T4: Medium | U4: =IF(C4="Energy audit","Enabling Step",IF(P4="No savings","Low Priority",IF(AND(P4<=5,O4>10),"High Priority",IF(P4<=8,"Medium Priority","Low Priority")))) -> High Priority | V4: =IF(U4="High Priority","Advance to vendor quote / audit scope",IF(U4="Medium Priority","Include in operating improvement plan",IF(U4="Enabling Step","Complete before final capex decision","Monitor or defer"))) -> Advance to vendor quote / audit scope | W4: =IF(S4>0,"Estimated value impact assumes annual savings are capitalized at a 5% cap rate","No direct value impact estimated") -> Estimated value impact assumes annual savings are capitalized at a 5% cap rate
A5: WI-MF-02 | B5: Lakeview Terrace | C5: Waste diversion program | D5: Waste + diversion | E5: 15000 | F5: 0 | G5: =E5-F5 -> 15000 | H5: 0 | I5: 0 | J5: 0 | K5: 5000 | L5: =(H5*0.145)+(I5*1.1) -> 0 | M5: =J5*0.012 -> 0 | N5: =K5+L5+M5 -> 5000 | O5: =((H5*0.527779)+(I5*5.31145))/1000 -> 0 | P5: =IF(N5=0,"No savings",G5/N5) -> 3 | Q5: =IF(O5=0,"No emissions reduction",G5/O5) -> No emissions reduction | R5: =N5 -> 5000 | S5: =R5/0.05 -> 100000 | T5: Low | U5: =IF(C5="Energy audit","Enabling Step",IF(P5="No savings","Low Priority",IF(AND(P5<=5,O5>10),"High Priority",IF(P5<=8,"Medium Priority","Low Priority")))) -> Medium Priority | V5: =IF(U5="High Priority","Advance to vendor quote / audit scope",IF(U5="Medium Priority","Include in operating improvement plan",IF(U5="Enabling Step","Complete before final capex decision","Monitor or defer"))) -> Include in operating improvement plan | W5: =IF(S5>0,"Estimated value impact assumes annual savings are capitalized at a 5% cap rate","No direct value impact estimated") -> Estimated value impact assumes annual savings are capitalized at a 5% cap rate
A6: WI-MF-06 | B6: South Park Apartments | C6: Energy audit | D6: Energy + carbon | E6: 12000 | F6: 0 | G6: =E6-F6 -> 12000 | H6: 0 | I6: 0 | J6: 0 | K6: 0 | L6: =(H6*0.145)+(I6*1.1) -> 0 | M6: =J6*0.012 -> 0 | N6: =K6+L6+M6 -> 0 | O6: =((H6*0.527779)+(I6*5.31145))/1000 -> 0 | P6: =IF(N6=0,"No savings",G6/N6) -> No savings | Q6: =IF(O6=0,"No emissions reduction",G6/O6) -> No emissions reduction | R6: =N6 -> 0 | S6: =R6/0.05 -> 0 | T6: Low | U6: =IF(C6="Energy audit","Enabling Step",IF(P6="No savings","Low Priority",IF(AND(P6<=5,O6>10),"High Priority",IF(P6<=8,"Medium Priority","Low Priority")))) -> Enabling Step | V6: =IF(U6="High Priority","Advance to vendor quote / audit scope",IF(U6="Medium Priority","Include in operating improvement plan",IF(U6="Enabling Step","Complete before final capex decision","Monitor or defer"))) -> Complete before final capex decision | W6: =IF(S6>0,"Estimated value impact assumes annual savings are capitalized at a 5% cap rate","No direct value impact estimated") -> No direct value impact estimated
A7: WI-MF-06 | B7: South Park Apartments | C7: Boiler/heating review | D7: Gas use + carbon | E7: 45000 | F7: 8000 | G7: =E7-F7 -> 37000 | H7: 0 | I7: 9000 | J7: 0 | K7: 0 | L7: =(H7*0.145)+(I7*1.1) -> 9900 | M7: =J7*0.012 -> 0 | N7: =K7+L7+M7 -> 9900 | O7: =((H7*0.527779)+(I7*5.31145))/1000 -> 47.80305 | P7: =IF(N7=0,"No savings",G7/N7) -> 3.7373737 | Q7: =IF(O7=0,"No emissions reduction",G7/O7) -> 774.00919 | R7: =N7 -> 9900 | S7: =R7/0.05 -> 198000 | T7: Medium | U7: =IF(C7="Energy audit","Enabling Step",IF(P7="No savings","Low Priority",IF(AND(P7<=5,O7>10),"High Priority",IF(P7<=8,"Medium Priority","Low Priority")))) -> High Priority | V7: =IF(U7="High Priority","Advance to vendor quote / audit scope",IF(U7="Medium Priority","Include in operating improvement plan",IF(U7="Enabling Step","Complete before final capex decision","Monitor or defer"))) -> Advance to vendor quote / audit scope | W7: =IF(S7>0,"Estimated value impact assumes annual savings are capitalized at a 5% cap rate","No direct value impact estimated") -> Estimated value impact assumes annual savings are capitalized at a 5% cap rate
A8: WI-MF-06 | B8: South Park Apartments | C8: Electricity efficiency | D8: Electricity use + Scope 2 | E8: 65000 | F8: 10000 | G8: =E8-F8 -> 55000 | H8: 180000 | I8: 0 | J8: 0 | K8: 0 | L8: =(H8*0.145)+(I8*1.1) -> 26100 | M8: =J8*0.012 -> 0 | N8: =K8+L8+M8 -> 26100 | O8: =((H8*0.527779)+(I8*5.31145))/1000 -> 95.00022 | P8: =IF(N8=0,"No savings",G8/N8) -> 2.1072797 | Q8: =IF(O8=0,"No emissions reduction",G8/O8) -> 578.94603 | R8: =N8 -> 26100 | S8: =R8/0.05 -> 522000 | T8: Medium | U8: =IF(C8="Energy audit","Enabling Step",IF(P8="No savings","Low Priority",IF(AND(P8<=5,O8>10),"High Priority",IF(P8<=8,"Medium Priority","Low Priority")))) -> High Priority | V8: =IF(U8="High Priority","Advance to vendor quote / audit scope",IF(U8="Medium Priority","Include in operating improvement plan",IF(U8="Enabling Step","Complete before final capex decision","Monitor or defer"))) -> Advance to vendor quote / audit scope | W8: =IF(S8>0,"Estimated value impact assumes annual savings are capitalized at a 5% cap rate","No direct value impact estimated") -> Estimated value impact assumes annual savings are capitalized at a 5% cap rate
A9: WI-MF-06 | B9: South Park Apartments | C9: Waste diversion program | D9: Waste + diversion | E9: 15000 | F9: 0 | G9: =E9-F9 -> 15000 | H9: 0 | I9: 0 | J9: 0 | K9: 5000 | L9: =(H9*0.145)+(I9*1.1) -> 0 | M9: =J9*0.012 -> 0 | N9: =K9+L9+M9 -> 5000 | O9: =((H9*0.527779)+(I9*5.31145))/1000 -> 0 | P9: =IF(N9=0,"No savings",G9/N9) -> 3 | Q9: =IF(O9=0,"No emissions reduction",G9/O9) -> No emissions reduction | R9: =N9 -> 5000 | S9: =R9/0.05 -> 100000 | T9: Low | U9: =IF(C9="Energy audit","Enabling Step",IF(P9="No savings","Low Priority",IF(AND(P9<=5,O9>10),"High Priority",IF(P9<=8,"Medium Priority","Low Priority")))) -> Medium Priority | V9: =IF(U9="High Priority","Advance to vendor quote / audit scope",IF(U9="Medium Priority","Include in operating improvement plan",IF(U9="Enabling Step","Complete before final capex decision","Monitor or defer"))) -> Include in operating improvement plan | W9: =IF(S9>0,"Estimated value impact assumes annual savings are capitalized at a 5% cap rate","No direct value impact estimated") -> Estimated value impact assumes annual savings are capitalized at a 5% cap rate
A10: WI-MF-10 | B10: Harbor Point Apartments | C10: Domestic hot water efficiency | D10: Gas + water | E10: 50000 | F10: 7500 | G10: =E10-F10 -> 42500 | H10: 0 | I10: 7000 | J10: 250000 | K10: 0 | L10: =(H10*0.145)+(I10*1.1) -> 7700 | M10: =J10*0.012 -> 3000 | N10: =K10+L10+M10 -> 10700 | O10: =((H10*0.527779)+(I10*5.31145))/1000 -> 37.18015 | P10: =IF(N10=0,"No savings",G10/N10) -> 3.9719626 | Q10: =IF(O10=0,"No emissions reduction",G10/O10) -> 1143.0831 | R10: =N10 -> 10700 | S10: =R10/0.05 -> 214000 | T10: Medium | U10: =IF(C10="Energy audit","Enabling Step",IF(P10="No savings","Low Priority",IF(AND(P10<=5,O10>10),"High Priority",IF(P10<=8,"Medium Priority","Low Priority")))) -> High Priority | V10: =IF(U10="High Priority","Advance to vendor quote / audit scope",IF(U10="Medium Priority","Include in operating improvement plan",IF(U10="Enabling Step","Complete before final capex decision","Monitor or defer"))) -> Advance to vendor quote / audit scope | W10: =IF(S10>0,"Estimated value impact assumes annual savings are capitalized at a 5% cap rate","No direct value impact estimated") -> Estimated value impact assumes annual savings are capitalized at a 5% cap rate
A11: WI-MF-10 | B11: Harbor Point Apartments | C11: Envelope air sealing | D11: Heating load | E11: 85000 | F11: 12000 | G11: =E11-F11 -> 73000 | H11: 0 | I11: 8000 | J11: 0 | K11: 0 | L11: =(H11*0.145)+(I11*1.1) -> 8800 | M11: =J11*0.012 -> 0 | N11: =K11+L11+M11 -> 8800 | O11: =((H11*0.527779)+(I11*5.31145))/1000 -> 42.4916 | P11: =IF(N11=0,"No savings",G11/N11) -> 8.2954545 | Q11: =IF(O11=0,"No emissions reduction",G11/O11) -> 1717.9866 | R11: =N11 -> 8800 | S11: =R11/0.05 -> 176000 | T11: High | U11: =IF(C11="Energy audit","Enabling Step",IF(P11="No savings","Low Priority",IF(AND(P11<=5,O11>10),"High Priority",IF(P11<=8,"Medium Priority","Low Priority")))) -> Low Priority | V11: =IF(U11="High Priority","Advance to vendor quote / audit scope",IF(U11="Medium Priority","Include in operating improvement plan",IF(U11="Enabling Step","Complete before final capex decision","Monitor or defer"))) -> Monitor or defer | W11: =IF(S11>0,"Estimated value impact assumes annual savings are capitalized at a 5% cap rate","No direct value impact estimated") -> Estimated value impact assumes annual savings are capitalized at a 5% cap rate | Z11: Retrofit financial screening shows that electricity-efficiency upgrades and boiler/heating reviews are the strongest near-term investment candidates for the highest-priority properties. Electricity efficiency at Lakeview Terrace and South Park Apartments shows an estimated payback of approximately 2.1 years, annual savings of $26,100, and emissions reduction of about 95 tCO₂e per property. Boiler/heating review shows an estimated payback of approximately 3.7 years and reduces Scope 1 emissions by about 47.8 tCO₂e per property. Waste-diversion programs have weaker direct carbon benefits but remain important because weak diversion is the most consistent portfolio-wide ESG issue.
A12: WI-MF-10 | B12: Harbor Point Apartments | C12: Waste diversion program | D12: Waste + diversion | E12: 15000 | F12: 0 | G12: =E12-F12 -> 15000 | H12: 0 | I12: 0 | J12: 0 | K12: 5000 | L12: =(H12*0.145)+(I12*1.1) -> 0 | M12: =J12*0.012 -> 0 | N12: =K12+L12+M12 -> 5000 | O12: =((H12*0.527779)+(I12*5.31145))/1000 -> 0 | P12: =IF(N12=0,"No savings",G12/N12) -> 3 | Q12: =IF(O12=0,"No emissions reduction",G12/O12) -> No emissions reduction | R12: =N12 -> 5000 | S12: =R12/0.05 -> 100000 | T12: Low | U12: =IF(C12="Energy audit","Enabling Step",IF(P12="No savings","Low Priority",IF(AND(P12<=5,O12>10),"High Priority",IF(P12<=8,"Medium Priority","Low Priority")))) -> Medium Priority | V12: =IF(U12="High Priority","Advance to vendor quote / audit scope",IF(U12="Medium Priority","Include in operating improvement plan",IF(U12="Enabling Step","Complete before final capex decision","Monitor or defer"))) -> Include in operating improvement plan | W12: =IF(S12>0,"Estimated value impact assumes annual savings are capitalized at a 5% cap rate","No direct value impact estimated") -> Estimated value impact assumes annual savings are capitalized at a 5% cap rate
A13: WI-MF-04 | B13: Badger Ridge Homes | C13: Energy audit | D13: Energy + carbon | E13: 12000 | F13: 0 | G13: =E13-F13 -> 12000 | L13: =(H13*0.145)+(I13*1.1) -> 0 | M13: =J13*0.012 -> 0 | N13: =K13+L13+M13 -> 0 | O13: =((H13*0.527779)+(I13*5.31145))/1000 -> 0 | P13: =IF(N13=0,"No savings",G13/N13) -> No savings | Q13: =IF(O13=0,"No emissions reduction",G13/O13) -> No emissions reduction | R13: =N13 -> 0 | S13: =R13/0.05 -> 0 | T13: Low | U13: =IF(C13="Energy audit","Enabling Step",IF(P13="No savings","Low Priority",IF(AND(P13<=5,O13>10),"High Priority",IF(P13<=8,"Medium Priority","Low Priority")))) -> Enabling Step | V13: =IF(U13="High Priority","Advance to vendor quote / audit scope",IF(U13="Medium Priority","Include in operating improvement plan",IF(U13="Enabling Step","Complete before final capex decision","Monitor or defer"))) -> Complete before final capex decision | W13: =IF(S13>0,"Estimated value impact assumes annual savings are capitalized at a 5% cap rate","No direct value impact estimated") -> No direct value impact estimated
A14: WI-MF-04 | B14: Badger Ridge Homes | C14: Waste diversion program | D14: Waste + diversion | E14: 15000 | F14: 0 | G14: =E14-F14 -> 15000 | H14: 0 | I14: 0 | J14: 0 | K14: 5000 | L14: =(H14*0.145)+(I14*1.1) -> 0 | M14: =J14*0.012 -> 0 | N14: =K14+L14+M14 -> 5000 | O14: =((H14*0.527779)+(I14*5.31145))/1000 -> 0 | P14: =IF(N14=0,"No savings",G14/N14) -> 3 | Q14: =IF(O14=0,"No emissions reduction",G14/O14) -> No emissions reduction | R14: =N14 -> 5000 | S14: =R14/0.05 -> 100000 | T14: Low | U14: =IF(C14="Energy audit","Enabling Step",IF(P14="No savings","Low Priority",IF(AND(P14<=5,O14>10),"High Priority",IF(P14<=8,"Medium Priority","Low Priority")))) -> Medium Priority | V14: =IF(U14="High Priority","Advance to vendor quote / audit scope",IF(U14="Medium Priority","Include in operating improvement plan",IF(U14="Enabling Step","Complete before final capex decision","Monitor or defer"))) -> Include in operating improvement plan | W14: =IF(S14>0,"Estimated value impact assumes annual savings are capitalized at a 5% cap rate","No direct value impact estimated") -> Estimated value impact assumes annual savings are capitalized at a 5% cap rate

Sheet 17_output_investment_summary
A1: investment_rank | B1: property_id | C1: property_name | D1: retrofit_measure | E1: issue_addressed | F1: net_cost_usd | G1: annual_total_savings_usd | H1: simple_payback_years | I1: annual_emissions_reduction_tco2e | J1: cost_per_tco2e_reduced | K1: estimated_value_impact_usd | L1: implementation_difficulty | M1: investment_priority | N1: investment_decision
A2: 1 | B2: WI-MF-02 | C2: =_xlfn.XLOOKUP(B2,'01_input_asset_master'!A$2:A$11,'01_input_asset_master'!B$2:B$11) -> Lakeview Terrace | D2: Electricity efficiency | E2: =IF(D2="Energy audit","Energy + carbon",IF(D2="Boiler/heating review","Natural gas + Scope 1 carbon",IF(D2="Electricity efficiency","Electricity + Scope 2 carbon",IF(D2="Waste diversion program","Waste + diversion",IF(D2="Domestic hot water efficiency","Gas + water + cost",IF(D2="Envelope air sealing","Heating load","Other")))))) -> Electricity + Scope 2 carbon | F2: {=_xlfn.XLOOKUP($B2&"|"&$D2,'16_calc_retrofit_finance'!$A$2:$A$14&"|"&'16_calc_retrofit_finance'!$C$2:$C$14,'16_calc_retrofit_finance'!$G$2:$G$14,"Not found")} -> 55000 | G2: {=_xlfn.XLOOKUP($B2&"|"&$D2,'16_calc_retrofit_finance'!$A$2:$A$14&"|"&'16_calc_retrofit_finance'!$C$2:$C$14,'16_calc_retrofit_finance'!$N$2:$N$14,"Not found")} -> 26100 | H2: {=_xlfn.XLOOKUP($B2&"|"&$D2,'16_calc_retrofit_finance'!$A$2:$A$14&"|"&'16_calc_retrofit_finance'!$C$2:$C$14,'16_calc_retrofit_finance'!$P$2:$P$14,"Not found")} -> 2.1072797 | I2: {=_xlfn.XLOOKUP($B2&"|"&$D2,'16_calc_retrofit_finance'!$A$2:$A$14&"|"&'16_calc_retrofit_finance'!$C$2:$C$14,'16_calc_retrofit_finance'!$O$2:$O$14,"Not found")} -> 95.00022 | J2: {=_xlfn.XLOOKUP($B2&"|"&$D2,'16_calc_retrofit_finance'!$A$2:$A$14&"|"&'16_calc_retrofit_finance'!$C$2:$C$14,'16_calc_retrofit_finance'!$Q$2:$Q$14,"Not found")} -> 578.94603 | K2: {=_xlfn.XLOOKUP($B2&"|"&$D2,'16_calc_retrofit_finance'!$A$2:$A$14&"|"&'16_calc_retrofit_finance'!$C$2:$C$14,'16_calc_retrofit_finance'!$S$2:$S$14,"Not found")} -> 522000 | L2: {=_xlfn.XLOOKUP($B2&"|"&$D2,'16_calc_retrofit_finance'!$A$2:$A$14&"|"&'16_calc_retrofit_finance'!$C$2:$C$14,'16_calc_retrofit_finance'!$T$2:$T$14,"Not found")} -> Medium | M2: {=_xlfn.XLOOKUP($B2&"|"&$D2,'16_calc_retrofit_finance'!$A$2:$A$14&"|"&'16_calc_retrofit_finance'!$C$2:$C$14,'16_calc_retrofit_finance'!$U$2:$U$14,"Not found")} -> High Priority | N2: =IF(M2="High Priority","Advance to vendor quote / audit scope",IF(M2="Medium Priority","Include in operating improvement plan",IF(M2="Enabling Step","Complete before final capex decision","Monitor or defer"))) -> Advance to vendor quote / audit scope | P2: The investment priority summary shows that electricity-efficiency upgrades at Lakeview Terrace and South Park Apartments are the strongest near-term investments, with estimated paybacks of 2.1 years, annual savings of $26,100 per property, and emissions reductions of about 95 tCO₂e per property. Boiler/heating review at the same two properties also performs well, with paybacks under four years and Scope 1 emissions reductions of about 47.8 tCO₂e per property. Domestic hot water efficiency at Harbor Point Apartments is also attractive because it combines gas, water, cost, and carbon benefits. Waste-diversion programs have weaker direct carbon benefits, but they should be included in operating plans because weak diversion is the most consistent portfolio-wide ESG issue.
A3: 1 | B3: WI-MF-06 | C3: =_xlfn.XLOOKUP(B3,'01_input_asset_master'!A$2:A$11,'01_input_asset_master'!B$2:B$11) -> South Park Apartments | D3: Electricity efficiency | E3: =IF(D3="Energy audit","Energy + carbon",IF(D3="Boiler/heating review","Natural gas + Scope 1 carbon",IF(D3="Electricity efficiency","Electricity + Scope 2 carbon",IF(D3="Waste diversion program","Waste + diversion",IF(D3="Domestic hot water efficiency","Gas + water + cost",IF(D3="Envelope air sealing","Heating load","Other")))))) -> Electricity + Scope 2 carbon | F3: {=_xlfn.XLOOKUP($B3&"|"&$D3,'16_calc_retrofit_finance'!$A$2:$A$14&"|"&'16_calc_retrofit_finance'!$C$2:$C$14,'16_calc_retrofit_finance'!$G$2:$G$14,"Not found")} -> 55000 | G3: {=_xlfn.XLOOKUP($B3&"|"&$D3,'16_calc_retrofit_finance'!$A$2:$A$14&"|"&'16_calc_retrofit_finance'!$C$2:$C$14,'16_calc_retrofit_finance'!$N$2:$N$14,"Not found")} -> 26100 | H3: {=_xlfn.XLOOKUP($B3&"|"&$D3,'16_calc_retrofit_finance'!$A$2:$A$14&"|"&'16_calc_retrofit_finance'!$C$2:$C$14,'16_calc_retrofit_finance'!$P$2:$P$14,"Not found")} -> 2.1072797 | I3: {=_xlfn.XLOOKUP($B3&"|"&$D3,'16_calc_retrofit_finance'!$A$2:$A$14&"|"&'16_calc_retrofit_finance'!$C$2:$C$14,'16_calc_retrofit_finance'!$O$2:$O$14,"Not found")} -> 95.00022 | J3: {=_xlfn.XLOOKUP($B3&"|"&$D3,'16_calc_retrofit_finance'!$A$2:$A$14&"|"&'16_calc_retrofit_finance'!$C$2:$C$14,'16_calc_retrofit_finance'!$Q$2:$Q$14,"Not found")} -> 578.94603 | K3: {=_xlfn.XLOOKUP($B3&"|"&$D3,'16_calc_retrofit_finance'!$A$2:$A$14&"|"&'16_calc_retrofit_finance'!$C$2:$C$14,'16_calc_retrofit_finance'!$S$2:$S$14,"Not found")} -> 522000 | L3: {=_xlfn.XLOOKUP($B3&"|"&$D3,'16_calc_retrofit_finance'!$A$2:$A$14&"|"&'16_calc_retrofit_finance'!$C$2:$C$14,'16_calc_retrofit_finance'!$T$2:$T$14,"Not found")} -> Medium | M3: {=_xlfn.XLOOKUP($B3&"|"&$D3,'16_calc_retrofit_finance'!$A$2:$A$14&"|"&'16_calc_retrofit_finance'!$C$2:$C$14,'16_calc_retrofit_finance'!$U$2:$U$14,"Not found")} -> High Priority | N3: =IF(M3="High Priority","Advance to vendor quote / audit scope",IF(M3="Medium Priority","Include in operating improvement plan",IF(M3="Enabling Step","Complete before final capex decision","Monitor or defer"))) -> Advance to vendor quote / audit scope
A4: 3 | B4: WI-MF-02 | C4: =_xlfn.XLOOKUP(B4,'01_input_asset_master'!A$2:A$11,'01_input_asset_master'!B$2:B$11) -> Lakeview Terrace | D4: Boiler/heating review | E4: =IF(D4="Energy audit","Energy + carbon",IF(D4="Boiler/heating review","Natural gas + Scope 1 carbon",IF(D4="Electricity efficiency","Electricity + Scope 2 carbon",IF(D4="Waste diversion program","Waste + diversion",IF(D4="Domestic hot water efficiency","Gas + water + cost",IF(D4="Envelope air sealing","Heating load","Other")))))) -> Natural gas + Scope 1 carbon | F4: {=_xlfn.XLOOKUP($B4&"|"&$D4,'16_calc_retrofit_finance'!$A$2:$A$14&"|"&'16_calc_retrofit_finance'!$C$2:$C$14,'16_calc_retrofit_finance'!$G$2:$G$14,"Not found")} -> 37000 | G4: {=_xlfn.XLOOKUP($B4&"|"&$D4,'16_calc_retrofit_finance'!$A$2:$A$14&"|"&'16_calc_retrofit_finance'!$C$2:$C$14,'16_calc_retrofit_finance'!$N$2:$N$14,"Not found")} -> 9900 | H4: {=_xlfn.XLOOKUP($B4&"|"&$D4,'16_calc_retrofit_finance'!$A$2:$A$14&"|"&'16_calc_retrofit_finance'!$C$2:$C$14,'16_calc_retrofit_finance'!$P$2:$P$14,"Not found")} -> 3.7373737 | I4: {=_xlfn.XLOOKUP($B4&"|"&$D4,'16_calc_retrofit_finance'!$A$2:$A$14&"|"&'16_calc_retrofit_finance'!$C$2:$C$14,'16_calc_retrofit_finance'!$O$2:$O$14,"Not found")} -> 47.80305 | J4: {=_xlfn.XLOOKUP($B4&"|"&$D4,'16_calc_retrofit_finance'!$A$2:$A$14&"|"&'16_calc_retrofit_finance'!$C$2:$C$14,'16_calc_retrofit_finance'!$Q$2:$Q$14,"Not found")} -> 774.00919 | K4: {=_xlfn.XLOOKUP($B4&"|"&$D4,'16_calc_retrofit_finance'!$A$2:$A$14&"|"&'16_calc_retrofit_finance'!$C$2:$C$14,'16_calc_retrofit_finance'!$S$2:$S$14,"Not found")} -> 198000 | L4: {=_xlfn.XLOOKUP($B4&"|"&$D4,'16_calc_retrofit_finance'!$A$2:$A$14&"|"&'16_calc_retrofit_finance'!$C$2:$C$14,'16_calc_retrofit_finance'!$T$2:$T$14,"Not found")} -> Medium | M4: {=_xlfn.XLOOKUP($B4&"|"&$D4,'16_calc_retrofit_finance'!$A$2:$A$14&"|"&'16_calc_retrofit_finance'!$C$2:$C$14,'16_calc_retrofit_finance'!$U$2:$U$14,"Not found")} -> High Priority | N4: =IF(M4="High Priority","Advance to vendor quote / audit scope",IF(M4="Medium Priority","Include in operating improvement plan",IF(M4="Enabling Step","Complete before final capex decision","Monitor or defer"))) -> Advance to vendor quote / audit scope
A5: 3 | B5: WI-MF-06 | C5: =_xlfn.XLOOKUP(B5,'01_input_asset_master'!A$2:A$11,'01_input_asset_master'!B$2:B$11) -> South Park Apartments | D5: Boiler/heating review | E5: =IF(D5="Energy audit","Energy + carbon",IF(D5="Boiler/heating review","Natural gas + Scope 1 carbon",IF(D5="Electricity efficiency","Electricity + Scope 2 carbon",IF(D5="Waste diversion program","Waste + diversion",IF(D5="Domestic hot water efficiency","Gas + water + cost",IF(D5="Envelope air sealing","Heating load","Other")))))) -> Natural gas + Scope 1 carbon | F5: {=_xlfn.XLOOKUP($B5&"|"&$D5,'16_calc_retrofit_finance'!$A$2:$A$14&"|"&'16_calc_retrofit_finance'!$C$2:$C$14,'16_calc_retrofit_finance'!$G$2:$G$14,"Not found")} -> 37000 | G5: {=_xlfn.XLOOKUP($B5&"|"&$D5,'16_calc_retrofit_finance'!$A$2:$A$14&"|"&'16_calc_retrofit_finance'!$C$2:$C$14,'16_calc_retrofit_finance'!$N$2:$N$14,"Not found")} -> 9900 | H5: {=_xlfn.XLOOKUP($B5&"|"&$D5,'16_calc_retrofit_finance'!$A$2:$A$14&"|"&'16_calc_retrofit_finance'!$C$2:$C$14,'16_calc_retrofit_finance'!$P$2:$P$14,"Not found")} -> 3.7373737 | I5: {=_xlfn.XLOOKUP($B5&"|"&$D5,'16_calc_retrofit_finance'!$A$2:$A$14&"|"&'16_calc_retrofit_finance'!$C$2:$C$14,'16_calc_retrofit_finance'!$O$2:$O$14,"Not found")} -> 47.80305 | J5: {=_xlfn.XLOOKUP($B5&"|"&$D5,'16_calc_retrofit_finance'!$A$2:$A$14&"|"&'16_calc_retrofit_finance'!$C$2:$C$14,'16_calc_retrofit_finance'!$Q$2:$Q$14,"Not found")} -> 774.00919 | K5: {=_xlfn.XLOOKUP($B5&"|"&$D5,'16_calc_retrofit_finance'!$A$2:$A$14&"|"&'16_calc_retrofit_finance'!$C$2:$C$14,'16_calc_retrofit_finance'!$S$2:$S$14,"Not found")} -> 198000 | L5: {=_xlfn.XLOOKUP($B5&"|"&$D5,'16_calc_retrofit_finance'!$A$2:$A$14&"|"&'16_calc_retrofit_finance'!$C$2:$C$14,'16_calc_retrofit_finance'!$T$2:$T$14,"Not found")} -> Medium | M5: {=_xlfn.XLOOKUP($B5&"|"&$D5,'16_calc_retrofit_finance'!$A$2:$A$14&"|"&'16_calc_retrofit_finance'!$C$2:$C$14,'16_calc_retrofit_finance'!$U$2:$U$14,"Not found")} -> High Priority | N5: =IF(M5="High Priority","Advance to vendor quote / audit scope",IF(M5="Medium Priority","Include in operating improvement plan",IF(M5="Enabling Step","Complete before final capex decision","Monitor or defer"))) -> Advance to vendor quote / audit scope
A6: 5 | B6: WI-MF-10 | C6: =_xlfn.XLOOKUP(B6,'01_input_asset_master'!A$2:A$11,'01_input_asset_master'!B$2:B$11) -> Harbor Point Apartments | D6: Domestic hot water efficiency | E6: =IF(D6="Energy audit","Energy + carbon",IF(D6="Boiler/heating review","Natural gas + Scope 1 carbon",IF(D6="Electricity efficiency","Electricity + Scope 2 carbon",IF(D6="Waste diversion program","Waste + diversion",IF(D6="Domestic hot water efficiency","Gas + water + cost",IF(D6="Envelope air sealing","Heating load","Other")))))) -> Gas + water + cost | F6: {=_xlfn.XLOOKUP($B6&"|"&$D6,'16_calc_retrofit_finance'!$A$2:$A$14&"|"&'16_calc_retrofit_finance'!$C$2:$C$14,'16_calc_retrofit_finance'!$G$2:$G$14,"Not found")} -> 42500 | G6: {=_xlfn.XLOOKUP($B6&"|"&$D6,'16_calc_retrofit_finance'!$A$2:$A$14&"|"&'16_calc_retrofit_finance'!$C$2:$C$14,'16_calc_retrofit_finance'!$N$2:$N$14,"Not found")} -> 10700 | H6: {=_xlfn.XLOOKUP($B6&"|"&$D6,'16_calc_retrofit_finance'!$A$2:$A$14&"|"&'16_calc_retrofit_finance'!$C$2:$C$14,'16_calc_retrofit_finance'!$P$2:$P$14,"Not found")} -> 3.9719626 | I6: {=_xlfn.XLOOKUP($B6&"|"&$D6,'16_calc_retrofit_finance'!$A$2:$A$14&"|"&'16_calc_retrofit_finance'!$C$2:$C$14,'16_calc_retrofit_finance'!$O$2:$O$14,"Not found")} -> 37.18015 | J6: {=_xlfn.XLOOKUP($B6&"|"&$D6,'16_calc_retrofit_finance'!$A$2:$A$14&"|"&'16_calc_retrofit_finance'!$C$2:$C$14,'16_calc_retrofit_finance'!$Q$2:$Q$14,"Not found")} -> 1143.0831 | K6: {=_xlfn.XLOOKUP($B6&"|"&$D6,'16_calc_retrofit_finance'!$A$2:$A$14&"|"&'16_calc_retrofit_finance'!$C$2:$C$14,'16_calc_retrofit_finance'!$S$2:$S$14,"Not found")} -> 214000 | L6: {=_xlfn.XLOOKUP($B6&"|"&$D6,'16_calc_retrofit_finance'!$A$2:$A$14&"|"&'16_calc_retrofit_finance'!$C$2:$C$14,'16_calc_retrofit_finance'!$T$2:$T$14,"Not found")} -> Medium | M6: {=_xlfn.XLOOKUP($B6&"|"&$D6,'16_calc_retrofit_finance'!$A$2:$A$14&"|"&'16_calc_retrofit_finance'!$C$2:$C$14,'16_calc_retrofit_finance'!$U$2:$U$14,"Not found")} -> High Priority | N6: =IF(M6="High Priority","Advance to vendor quote / audit scope",IF(M6="Medium Priority","Include in operating improvement plan",IF(M6="Enabling Step","Complete before final capex decision","Monitor or defer"))) -> Advance to vendor quote / audit scope
A7: 6 | B7: WI-MF-02 | C7: =_xlfn.XLOOKUP(B7,'01_input_asset_master'!A$2:A$11,'01_input_asset_master'!B$2:B$11) -> Lakeview Terrace | D7: Waste diversion program | E7: =IF(D7="Energy audit","Energy + carbon",IF(D7="Boiler/heating review","Natural gas + Scope 1 carbon",IF(D7="Electricity efficiency","Electricity + Scope 2 carbon",IF(D7="Waste diversion program","Waste + diversion",IF(D7="Domestic hot water efficiency","Gas + water + cost",IF(D7="Envelope air sealing","Heating load","Other")))))) -> Waste + diversion | F7: {=_xlfn.XLOOKUP($B7&"|"&$D7,'16_calc_retrofit_finance'!$A$2:$A$14&"|"&'16_calc_retrofit_finance'!$C$2:$C$14,'16_calc_retrofit_finance'!$G$2:$G$14,"Not found")} -> 15000 | G7: {=_xlfn.XLOOKUP($B7&"|"&$D7,'16_calc_retrofit_finance'!$A$2:$A$14&"|"&'16_calc_retrofit_finance'!$C$2:$C$14,'16_calc_retrofit_finance'!$N$2:$N$14,"Not found")} -> 5000 | H7: {=_xlfn.XLOOKUP($B7&"|"&$D7,'16_calc_retrofit_finance'!$A$2:$A$14&"|"&'16_calc_retrofit_finance'!$C$2:$C$14,'16_calc_retrofit_finance'!$P$2:$P$14,"Not found")} -> 3 | I7: {=_xlfn.XLOOKUP($B7&"|"&$D7,'16_calc_retrofit_finance'!$A$2:$A$14&"|"&'16_calc_retrofit_finance'!$C$2:$C$14,'16_calc_retrofit_finance'!$O$2:$O$14,"Not found")} -> 0 | J7: {=_xlfn.XLOOKUP($B7&"|"&$D7,'16_calc_retrofit_finance'!$A$2:$A$14&"|"&'16_calc_retrofit_finance'!$C$2:$C$14,'16_calc_retrofit_finance'!$Q$2:$Q$14,"Not found")} -> No emissions reduction | K7: {=_xlfn.XLOOKUP($B7&"|"&$D7,'16_calc_retrofit_finance'!$A$2:$A$14&"|"&'16_calc_retrofit_finance'!$C$2:$C$14,'16_calc_retrofit_finance'!$S$2:$S$14,"Not found")} -> 100000 | L7: {=_xlfn.XLOOKUP($B7&"|"&$D7,'16_calc_retrofit_finance'!$A$2:$A$14&"|"&'16_calc_retrofit_finance'!$C$2:$C$14,'16_calc_retrofit_finance'!$T$2:$T$14,"Not found")} -> Low | M7: {=_xlfn.XLOOKUP($B7&"|"&$D7,'16_calc_retrofit_finance'!$A$2:$A$14&"|"&'16_calc_retrofit_finance'!$C$2:$C$14,'16_calc_retrofit_finance'!$U$2:$U$14,"Not found")} -> Medium Priority | N7: =IF(M7="High Priority","Advance to vendor quote / audit scope",IF(M7="Medium Priority","Include in operating improvement plan",IF(M7="Enabling Step","Complete before final capex decision","Monitor or defer"))) -> Include in operating improvement plan
A8: 6 | B8: WI-MF-06 | C8: =_xlfn.XLOOKUP(B8,'01_input_asset_master'!A$2:A$11,'01_input_asset_master'!B$2:B$11) -> South Park Apartments | D8: Waste diversion program | E8: =IF(D8="Energy audit","Energy + carbon",IF(D8="Boiler/heating review","Natural gas + Scope 1 carbon",IF(D8="Electricity efficiency","Electricity + Scope 2 carbon",IF(D8="Waste diversion program","Waste + diversion",IF(D8="Domestic hot water efficiency","Gas + water + cost",IF(D8="Envelope air sealing","Heating load","Other")))))) -> Waste + diversion | F8: {=_xlfn.XLOOKUP($B8&"|"&$D8,'16_calc_retrofit_finance'!$A$2:$A$14&"|"&'16_calc_retrofit_finance'!$C$2:$C$14,'16_calc_retrofit_finance'!$G$2:$G$14,"Not found")} -> 15000 | G8: {=_xlfn.XLOOKUP($B8&"|"&$D8,'16_calc_retrofit_finance'!$A$2:$A$14&"|"&'16_calc_retrofit_finance'!$C$2:$C$14,'16_calc_retrofit_finance'!$N$2:$N$14,"Not found")} -> 5000 | H8: {=_xlfn.XLOOKUP($B8&"|"&$D8,'16_calc_retrofit_finance'!$A$2:$A$14&"|"&'16_calc_retrofit_finance'!$C$2:$C$14,'16_calc_retrofit_finance'!$P$2:$P$14,"Not found")} -> 3 | I8: {=_xlfn.XLOOKUP($B8&"|"&$D8,'16_calc_retrofit_finance'!$A$2:$A$14&"|"&'16_calc_retrofit_finance'!$C$2:$C$14,'16_calc_retrofit_finance'!$O$2:$O$14,"Not found")} -> 0 | J8: {=_xlfn.XLOOKUP($B8&"|"&$D8,'16_calc_retrofit_finance'!$A$2:$A$14&"|"&'16_calc_retrofit_finance'!$C$2:$C$14,'16_calc_retrofit_finance'!$Q$2:$Q$14,"Not found")} -> No emissions reduction | K8: {=_xlfn.XLOOKUP($B8&"|"&$D8,'16_calc_retrofit_finance'!$A$2:$A$14&"|"&'16_calc_retrofit_finance'!$C$2:$C$14,'16_calc_retrofit_finance'!$S$2:$S$14,"Not found")} -> 100000 | L8: {=_xlfn.XLOOKUP($B8&"|"&$D8,'16_calc_retrofit_finance'!$A$2:$A$14&"|"&'16_calc_retrofit_finance'!$C$2:$C$14,'16_calc_retrofit_finance'!$T$2:$T$14,"Not found")} -> Low | M8: {=_xlfn.XLOOKUP($B8&"|"&$D8,'16_calc_retrofit_finance'!$A$2:$A$14&"|"&'16_calc_retrofit_finance'!$C$2:$C$14,'16_calc_retrofit_finance'!$U$2:$U$14,"Not found")} -> Medium Priority | N8: =IF(M8="High Priority","Advance to vendor quote / audit scope",IF(M8="Medium Priority","Include in operating improvement plan",IF(M8="Enabling Step","Complete before final capex decision","Monitor or defer"))) -> Include in operating improvement plan
A9: 6 | B9: WI-MF-10 | C9: =_xlfn.XLOOKUP(B9,'01_input_asset_master'!A$2:A$11,'01_input_asset_master'!B$2:B$11) -> Harbor Point Apartments | D9: Waste diversion program | E9: =IF(D9="Energy audit","Energy + carbon",IF(D9="Boiler/heating review","Natural gas + Scope 1 carbon",IF(D9="Electricity efficiency","Electricity + Scope 2 carbon",IF(D9="Waste diversion program","Waste + diversion",IF(D9="Domestic hot water efficiency","Gas + water + cost",IF(D9="Envelope air sealing","Heating load","Other")))))) -> Waste + diversion | F9: {=_xlfn.XLOOKUP($B9&"|"&$D9,'16_calc_retrofit_finance'!$A$2:$A$14&"|"&'16_calc_retrofit_finance'!$C$2:$C$14,'16_calc_retrofit_finance'!$G$2:$G$14,"Not found")} -> 15000 | G9: {=_xlfn.XLOOKUP($B9&"|"&$D9,'16_calc_retrofit_finance'!$A$2:$A$14&"|"&'16_calc_retrofit_finance'!$C$2:$C$14,'16_calc_retrofit_finance'!$N$2:$N$14,"Not found")} -> 5000 | H9: {=_xlfn.XLOOKUP($B9&"|"&$D9,'16_calc_retrofit_finance'!$A$2:$A$14&"|"&'16_calc_retrofit_finance'!$C$2:$C$14,'16_calc_retrofit_finance'!$P$2:$P$14,"Not found")} -> 3 | I9: {=_xlfn.XLOOKUP($B9&"|"&$D9,'16_calc_retrofit_finance'!$A$2:$A$14&"|"&'16_calc_retrofit_finance'!$C$2:$C$14,'16_calc_retrofit_finance'!$O$2:$O$14,"Not found")} -> 0 | J9: {=_xlfn.XLOOKUP($B9&"|"&$D9,'16_calc_retrofit_finance'!$A$2:$A$14&"|"&'16_calc_retrofit_finance'!$C$2:$C$14,'16_calc_retrofit_finance'!$Q$2:$Q$14,"Not found")} -> No emissions reduction | K9: {=_xlfn.XLOOKUP($B9&"|"&$D9,'16_calc_retrofit_finance'!$A$2:$A$14&"|"&'16_calc_retrofit_finance'!$C$2:$C$14,'16_calc_retrofit_finance'!$S$2:$S$14,"Not found")} -> 100000 | L9: {=_xlfn.XLOOKUP($B9&"|"&$D9,'16_calc_retrofit_finance'!$A$2:$A$14&"|"&'16_calc_retrofit_finance'!$C$2:$C$14,'16_calc_retrofit_finance'!$T$2:$T$14,"Not found")} -> Low | M9: {=_xlfn.XLOOKUP($B9&"|"&$D9,'16_calc_retrofit_finance'!$A$2:$A$14&"|"&'16_calc_retrofit_finance'!$C$2:$C$14,'16_calc_retrofit_finance'!$U$2:$U$14,"Not found")} -> Medium Priority | N9: =IF(M9="High Priority","Advance to vendor quote / audit scope",IF(M9="Medium Priority","Include in operating improvement plan",IF(M9="Enabling Step","Complete before final capex decision","Monitor or defer"))) -> Include in operating improvement plan
A10: 6 | B10: WI-MF-04 | C10: =_xlfn.XLOOKUP(B10,'01_input_asset_master'!A$2:A$11,'01_input_asset_master'!B$2:B$11) -> Badger Ridge Homes | D10: Waste diversion program | E10: =IF(D10="Energy audit","Energy + carbon",IF(D10="Boiler/heating review","Natural gas + Scope 1 carbon",IF(D10="Electricity efficiency","Electricity + Scope 2 carbon",IF(D10="Waste diversion program","Waste + diversion",IF(D10="Domestic hot water efficiency","Gas + water + cost",IF(D10="Envelope air sealing","Heating load","Other")))))) -> Waste + diversion | F10: {=_xlfn.XLOOKUP($B10&"|"&$D10,'16_calc_retrofit_finance'!$A$2:$A$14&"|"&'16_calc_retrofit_finance'!$C$2:$C$14,'16_calc_retrofit_finance'!$G$2:$G$14,"Not found")} -> 15000 | G10: {=_xlfn.XLOOKUP($B10&"|"&$D10,'16_calc_retrofit_finance'!$A$2:$A$14&"|"&'16_calc_retrofit_finance'!$C$2:$C$14,'16_calc_retrofit_finance'!$N$2:$N$14,"Not found")} -> 5000 | H10: {=_xlfn.XLOOKUP($B10&"|"&$D10,'16_calc_retrofit_finance'!$A$2:$A$14&"|"&'16_calc_retrofit_finance'!$C$2:$C$14,'16_calc_retrofit_finance'!$P$2:$P$14,"Not found")} -> 3 | I10: {=_xlfn.XLOOKUP($B10&"|"&$D10,'16_calc_retrofit_finance'!$A$2:$A$14&"|"&'16_calc_retrofit_finance'!$C$2:$C$14,'16_calc_retrofit_finance'!$O$2:$O$14,"Not found")} -> 0 | J10: {=_xlfn.XLOOKUP($B10&"|"&$D10,'16_calc_retrofit_finance'!$A$2:$A$14&"|"&'16_calc_retrofit_finance'!$C$2:$C$14,'16_calc_retrofit_finance'!$Q$2:$Q$14,"Not found")} -> No emissions reduction | K10: {=_xlfn.XLOOKUP($B10&"|"&$D10,'16_calc_retrofit_finance'!$A$2:$A$14&"|"&'16_calc_retrofit_finance'!$C$2:$C$14,'16_calc_retrofit_finance'!$S$2:$S$14,"Not found")} -> 100000 | L10: {=_xlfn.XLOOKUP($B10&"|"&$D10,'16_calc_retrofit_finance'!$A$2:$A$14&"|"&'16_calc_retrofit_finance'!$C$2:$C$14,'16_calc_retrofit_finance'!$T$2:$T$14,"Not found")} -> Low | M10: {=_xlfn.XLOOKUP($B10&"|"&$D10,'16_calc_retrofit_finance'!$A$2:$A$14&"|"&'16_calc_retrofit_finance'!$C$2:$C$14,'16_calc_retrofit_finance'!$U$2:$U$14,"Not found")} -> Medium Priority | N10: =IF(M10="High Priority","Advance to vendor quote / audit scope",IF(M10="Medium Priority","Include in operating improvement plan",IF(M10="Enabling Step","Complete before final capex decision","Monitor or defer"))) -> Include in operating improvement plan

Sheet 19_output_gresb_readiness
A1: indicator_id | B1: gresb_area | C1: indicator_name | D1: evidence_required | E1: current_status | F1: evidence_available_yes_no | G1: data_source_to_check | H1: responsible_team | I1: priority | J1: notes | K1: source_url
